Workbook

Sheet All-Hands Attendance
A1: Phone Number | B1: School ID | C1: Name | D1: Email | E1: Mentor Name | F1: Nov. or Exp. | G1: Year in DECA | H1: Pod # 0 | I1: 45917 | J1: 45924 | K1: 45931 | L1: 45938 | M1: 45945 | N1: 45952 | O1: 45959 | P1: 45966 | Q1: 45973 | R1: 45980 | S1: 45994 | T1: 46001 | U1: =T1+28 -> 46029 | V1: =U1+7 -> 46036 | W1: =V1+7 -> 46043 | X1: =W1+7 -> 46050 | Y1: =X1+7 -> 46057 | Z1: =Y1+7 -> 46064 | AA1: =Z1+28 -> 46092
C2: Amber Chang | D2: ambery.chang@warriorlife.net | E2: Aaron Vu | F2: N | G2: 1st Year | H2: 1 | I2: 1 | J2: 1 | K2: 1 | L2: 1 | M2: 1 | N2: 1 | O2: 1 | P2: 1 | Q2: 1 | R2: 1 | S2: 1 | T2: 1 | U2: 1 | V2: 1 | W2: 1 | X2: 1 | Y2: 1 | Z2: 1 | AA2: 1
C3: Nina Ling | D3: nina.ling@warriorlife.net | E3: Aaron Vu | F3: N | G3: 1st Year | H3: 1 | I3: 1 | J3: 1 | K3: 1 | L3: 1 | M3: 1 | N3: 1 | O3: 1 | P3: 1 | Q3: 1 | R3: 1 | S3: 1 | T3: 1 | U3: 1 | V3: 1 | W3: 1 | X3: 1 | Y3: 1 | Z3: 1 | AA3: 1
C4: Elize Kaldani | D4: elize.kaldani@warriorlife.net | E4: Aaron Vu | F4: N | G4: 1st Year | H4: 1 | I4: 1 | J4: 1 | K4: 1 | L4: 1 | M4: 1 | N4: 1 | O4: 1 | P4: 1 | Q4: 1 | R4: 1 | S4: 1 | T4: 1 | U4: 1 | V4: 1 | W4: 1 | X4: 1 | Y4: 1 | Z4: 1 | AA4: 1
C5: Geralyn Loo | D5: geralyn.loo@warriorlife.net | E5: Aaron Vu | F5: N | G5: 1st Year | H5: 1 | I5: 1 | J5: 1 | K5: 1 | L5: 1 | M5: 1 | N5: 1 | O5: 1 | P5: 1 | Q5: 1 | R5: 0.5 | S5: 1 | T5: 1 | U5: 1 | V5: 1 | W5: 1 | X5: 1 | Y5: 1 | Z5: 1 | AA5: 1
C6: Kashvi Lath | D6: kashvi.lath@warriorlife.net | E6: Aaron Vu | F6: N | G6: 1st Year | H6: 1 | I6: 1 | J6: 1 | K6: 1 | L6: 1 | M6: 1 | N6: 1 | O6: 1 | P6: 1 | Q6: 1 | R6: 1 | S6: 1 | T6: 1 | U6: 1 | V6: 1 | W6: 1 | X6: 1 | Y6: 1 | Z6: 1 | AA6: 1
C7: Gary Zhang | D7: shuhan.zhang@warriorlife.net | E7: Alicia Tang | F7: E | G7: 3rd Year | H7: 2 | I7: 1 | J7: 1 | K7: 0 | L7: 1 | M7: 1 | N7: 0.5 | O7: 1 | P7: 1 | Q7: 1 | R7: 0.5 | S7: 1 | T7: 1 | U7: 1 | V7: 1 | W7: 1 | X7: 1 | Y7: 1 | Z7: 1
C8: Paul Shi | D8: yunbo.shi@warriorlife.net | E8: Alicia Tang | F8: N | G8: 2nd Year | H8: 2 | I8: 1 | J8: 0.5 | K8: 1 | L8: 0.5 | M8: 1 | N8: 1 | O8: 1 | P8: 1 | Q8: 1 | R8: 1 | S8: 1 | T8: 1 | U8: 1 | V8: 0.5 | W8: 1 | X8: 1 | Y8: 1 | Z8: 0
C9: Sofia Yiu | D9: sofia.yiu@warriorlife.net | E9: Alicia Tang | F9: N | G9: 1st Year | H9: 2 | I9: 1 | J9: 1 | K9: 1 | L9: 1 | M9: 1 | N9: 1 | O9: 1 | P9: 1 | Q9: 1 | R9: 1 | S9: 1 | T9: 1 | U9: 1 | V9: 1 | W9: 1 | X9: 1 | Y9: 1 | Z9: 1 | AA9: 1
C10: Sunny Wang | D10: ziqing.wang@warriorlife.net | E10: Alicia Tang | F10: N | G10: 1st Year | H10: 2 | I10: 1 | J10: 1 | K10: 1 | L10: 1 | M10: 1 | N10: 1 | O10: 1 | P10: 1 | Q10: 1 | R10: 1 | S10: 1 | T10: 1 | U10: 1 | V10: 1 | W10: 1 | X10: 1 | Y10: 1 | Z10: 1 | AA10: 1
C11: Arkopriya Aich | D11: arkopriya.aich@warriorlife.net | E11: Alicia Tang | F11: N | G11: 2nd Year | H11: 2 | I11: 1 | J11: 1 | K11: 1 | L11: 1 | M11: 1 | N11: 0 | O11: 1 | P11: 1 | Q11: 1 | R11: 1 | S11: 1 | T11: 0.5 | U11: 1 | V11: 0 | W11: 0 | X11: 0 | Y11: 1 | Z11: 0
C12: Cherrilyn Huynh | D12: t.huynh@warriorlife.net | E12: Arissa Cao | F12: N | G12: 2nd Year | H12: 3 | I12: 1 | J12: 1 | K12: 1 | L12: 1 | M12: 1 | N12: 1 | O12: 0 | P12: 0 | Q12: 0 | R12: 1 | S12: 0 | U12: 1
C13: Madi Nguyen | D13: ct.nguyen@warriorlife.net | E13: Arissa Cao | F13: N | G13: 1st Year | H13: 3 | I13: 1 | J13: 1 | K13: 1 | L13: 1 | M13: 0 | N13: 1 | O13: 1 | P13: 1 | Q13: 1 | R13: 1 | S13: 1 | T13: 1 | U13: 1 | V13: 1 | W13: 1 | X13: 0.5 | Y13: 0.5 | Z13: 1
C14: Keshav Satagopan | D14: sk.satagopan@warriorlife.net | E14: Arissa Cao | F14: E | G14: 2nd Year | H14: 3 | I14: 1 | J14: 1 | K14: 1 | L14: 0.5 | M14: 1 | N14: 1 | O14: 0.5 | P14: 1 | Q14: 1 | R14: 1 | S14: 1 | T14: 1 | U14: 1 | V14: 1 | W14: 1 | X14: 1 | Y14: 1 | Z14: 1 | AA14: 1
C15: Jaden Park | D15: Jaden.park@warriorlife.net | E15: Arissa Cao | F15: E | G15: 3rd Year | H15: 3 | I15: 1 | J15: 1 | K15: 1 | L15: 1 | M15: 1 | N15: 1 | O15: 1 | P15: 1 | Q15: 1 | R15: 1 | S15: 1 | T15: 1 | U15: 1 | V15: 1 | W15: 1 | X15: 1 | Y15: 1 | Z15: 1 | AA15: 1
C16: Sradha Namala | D16: sradha.namala@warriorlife.net | E16: Arissa Cao | F16: N | G16: 1st Year | H16: 3 | I16: 1 | J16: 1 | K16: 1 | L16: 1 | M16: 1 | N16: 1 | O16: 1 | P16: 1 | Q16: 1 | R16: 1 | S16: 1 | T16: 1 | U16: 1 | V16: 1 | W16: 1 | X16: 1 | Y16: 1 | Z16: 1
C17: Franklin Dao | D17: franklin.dao@warriorlife.net | E17: Ayden Wang | F17: E | G17: 3rd Year | H17: 4 | I17: 1 | J17: 1 | K17: 1 | L17: 1 | M17: 1 | N17: 1 | O17: 1 | P17: 1 | Q17: 1 | R17: 1 | S17: 1 | T17: 1 | U17: 1 | V17: 1 | W17: 1 | X17: 1 | Y17: 1 | Z17: 1 | AA17: 1
C18: Samuel Xiao | D18: samuel.xiao@warriorlife.net | E18: Ayden Wang | F18: E | G18: 3rd Year | H18: 4 | I18: 1 | J18: 1 | K18: 1 | L18: 1 | M18: 1 | N18: 1 | O18: 1 | P18: 1 | Q18: 1 | R18: 1 | S18: 1 | T18: 1 | U18: 1 | V18: 1 | W18: 1 | X18: 1 | Y18: 1 | Z18: 1 | AA18: 1
C19: Aubrey Santos | D19: aubrey.santos@warriorlife.net | E19: Ayden Wang | F19: N | G19: 1st Year | H19: 4 | I19: 1 | J19: 0.5 | K19: 1 | L19: 1 | M19: 1 | N19: 1 | O19: 1 | P19: 0.5 | Q19: 1 | R19: 1 | S19: 1 | T19: 1 | U19: 1 | V19: 1 | W19: 1 | X19: 1 | Y19: 1 | Z19: 1
C20: Riyana Baldua | D20: riyana.baldua@warriorlife.net | E20: Ayden Wang | F20: N | G20: 2nd Year | H20: 4 | I20: 1 | J20: 1 | K20: 1 | L20: 0.5 | M20: 1 | N20: 1 | O20: 1 | P20: 1 | Q20: 1 | R20: 1 | S20: 1 | T20: 1 | U20: 1 | V20: 1 | W20: 1 | X20: 1 | Y20: 1 | Z20: 1
C21: Maahir Satwani | D21: maahir.satwani@warriorlife.net | E21: Ayden Wang | F21: N | G21: 1st Year | H21: 4 | I21: 1 | J21: 1 | K21: 1 | L21: 1 | M21: 0.5 | N21: 1 | O21: 1 | P21: 1 | Q21: 1 | R21: 1 | S21: 1 | T21: 1 | U21: 1 | V21: 1 | W21: 1 | X21: 1 | Y21: 1 | Z21: 1
C22: Suvir Maniktala | D22: suvir.maniktala@warriorlife.net | E22: Ayden Wang | F22: N | G22: 2nd Year | H22: 4 | I22: 1 | J22: 1 | K22: 1 | L22: 1 | M22: 0 | N22: 1 | O22: 1 | P22: 1 | Q22: 1 | R22: 1 | S22: 1 | T22: 1 | U22: 1 | V22: 1 | W22: 1 | X22: 1 | Y22: 1 | AA22: 1
C23: Ethan Teh | D23: ethan.teh@warriorlife.net | E23: Chloe Ding | F23: N | G23: 2nd Year | H23: 5 | I23: 1 | J23: 1 | K23: 1 | L23: 1 | M23: 1 | N23: 1 | O23: 1 | P23: 1 | Q23: 1 | R23: 1 | S23: 1 | T23: 1 | U23: 1 | V23: 1 | W23: 1 | X23: 1 | Y23: 1 | Z23: 1
C24: Jason Tang | D24: jason.tang@warriorlife.net | E24: Chloe Ding | F24: N | G24: 2nd Year | H24: 5 | I24: 0.5 | J24: 1 | K24: 1 | L24: 1 | M24: 1 | N24: 1 | O24: 1 | P24: 1 | Q24: 1 | R24: 1 | S24: 1 | T24: 1 | U24: 1 | V24: 1 | W24: 1 | X24: 1 | Y24: 0 | Z24: 1
C25: Gordon Lee | D25: gordon.lee@warriorlife.net | E25: Chloe Ding | F25: N | G25: 1st Year | H25: 5 | I25: 1 | J25: 1 | K25: 1 | L25: 1 | M25: 1 | N25: 1 | O25: 1 | P25: 1 | Q25: 1 | R25: 1 | S25: 1 | T25: 1 | U25: 1 | V25: 1 | W25: 1 | X25: 1 | Y25: 0 | Z25: 1 | AA25: 1
C26: Matthew Zhu | D26: matthew.zhu@warriorlife.net | E26: Chloe Ding | F26: N | G26: 2nd Year | H26: 5 | I26: 1 | J26: 1 | K26: 1 | L26: 1 | M26: 1 | N26: 1 | O26: 1 | P26: 1 | Q26: 1 | R26: 1 | S26: 1 | T26: 1 | U26: 0.5 | V26: 1 | W26: 1 | X26: 1 | Y26: 1 | Z26: 1 | AA26: 1
C27: Isabella Su | D27: isabella.su@warriorlife.net | E27: Chloe Zhong | F27: N | G27: 1st Year | H27: 6 | I27: 1 | J27: 1 | K27: 1 | L27: 1 | M27: 1 | N27: 1 | O27: 1 | P27: 1 | Q27: 1 | R27: 1 | S27: 1 | T27: 1 | U27: 0.5 | V27: 1 | W27: 1 | X27: 1 | Y27: 1 | Z27: 1 | AA27: 1
C28: Ashley Park | D28: ashley.park@warriorlife.net | E28: Chloe Zhong | F28: E | G28: 3rd Year | H28: 6 | I28: 1 | J28: 0.5 | K28: 1 | L28: 1 | M28: 1 | N28: 1 | O28: 1 | P28: 1 | Q28: 1 | R28: 1 | S28: 1 | T28: 1 | U28: 1 | V28: 1 | W28: 1 | X28: 1 | Y28: 1 | Z28: 1 | AA28: 1
C29: Jihoo Lee | D29: jihoo.lee@warriorlife.net | E29: Chloe Zhong | F29: E | G29: 3rd Year | H29: 6 | I29: 1 | J29: 1 | K29: 1 | L29: 1 | M29: 1 | N29: 0.5 | O29: 1 | P29: 1 | Q29: 1 | R29: 1 | S29: 1 | T29: 1 | U29: 0.5 | V29: 1 | W29: 1 | X29: 1 | Y29: 1 | Z29: 1 | AA29: 0
C30: Lucas Wang | D30: lucasj.wang@warriorlife.net | E30: Chloe Zhong | F30: E | G30: 3rd Year | H30: 6 | I30: 1 | J30: 1 | K30: 1 | L30: 1 | M30: 1 | N30: 0.5 | O30: 1 | P30: 1 | Q30: 1 | R30: 1 | S30: 1 | T30: 1 | U30: 1 | V30: 1 | W30: 1 | X30: 1 | Y30: 1 | Z30: 1 | AA30: 0
C31: Kayla Tan | D31: kayla.tan@warriorlife.net | E31: Chloe Zhong | F31: E | G31: 2nd Year | H31: 6 | I31: 1 | J31: 1 | K31: 1 | L31: 1 | M31: 1 | N31: 1 | O31: 1 | P31: 1 | Q31: 1 | R31: 1 | S31: 1 | T31: 1 | U31: 1 | V31: 1 | W31: 1 | X31: 1 | Y31: 1 | Z31: 1 | AA31: 1
C32: Sofia Choo | D32: sofia.choo@warriorlife.net | E32: Chloe Zhong | F32: N | G32: 2nd Year | H32: 6 | I32: 1 | J32: 1 | K32: 1 | L32: 1 | M32: 1 | N32: 0 | O32: 0 | P32: 0 | Q32: 0 | R32: 0 | S32: 0 | T32: 0 | U32: 0 | V32: 0 | W32: 0 | X32: 0 | Y32: 0 | Z32: 0 | AA32: 0
C33: Grace Frieder | D33: grace.frieder@warriorlife.net | E33: Elaine Wang | F33: N | G33: 1st Year | H33: 7 | I33: 1 | J33: 1 | K33: 1 | L33: 1 | M33: 1 | N33: 1 | O33: 1 | P33: 1 | Q33: 1 | R33: 1 | S33: 1 | T33: 1 | U33: 1 | V33: 1 | W33: 1 | X33: 1 | Y33: 1 | Z33: 1 | AA33: 1
C34: Hailey Taylor | D34: hailey.taylor@warriorlife.net | E34: Elaine Wang | F34: N | G34: 1st Year | H34: 7 | I34: 1 | J34: 1 | K34: 1 | L34: 1 | M34: 1 | N34: 1 | O34: 1 | P34: 1 | Q34: 1 | R34: 1 | S34: 1 | T34: 1 | U34: 1 | V34: 1 | W34: 1 | X34: 1 | Y34: 0.5 | Z34: 1 | AA34: 1
C35: Kate Borba | D35: kate.borba@warriorlife.net | E35: Elaine Wang | F35: N | G35: 1st Year | H35: 7 | I35: 1 | J35: 0.5 | K35: 1 | L35: 1 | M35: 1 | N35: 1 | O35: 1 | P35: 1 | Q35: 1 | R35: 1 | S35: 1 | T35: 1 | U35: 1 | V35: 1 | W35: 1 | X35: 1 | Y35: 1 | Z35: 0.5 | AA35: 1
C36: Aditya Poduri | D36: aditya.poduri@warriorlife.net | E36: Elaine Wang | F36: N | G36: 2nd Year | H36: 7 | I36: 1 | J36: 1 | K36: 1 | L36: 1 | M36: 1 | N36: 1 | O36: 1 | P36: 1 | Q36: 0.5 | R36: 1 | S36: 1 | T36: 1 | U36: 1 | V36: 1 | W36: 1 | X36: 1 | Y36: 1 | Z36: 1 | AA36: 1
C37: Jonathan Cheng | D37: jonathan.cheng@warriorlife.net | E37: Elaine Wang | F37: E | G37: 4th Year | H37: 7 | I37: 0 | J37: 0 | K37: 1 | L37: 1 | M37: 1 | N37: 1 | O37: 1 | P37: 1 | Q37: 1 | R37: 1 | S37: 1 | T37: 1 | U37: 1 | V37: 0 | W37: 0 | X37: 0 | Y37: 0 | Z37: 0 | AA37: 0
C38: Michael Deng | D38: michael.deng@warriorlife.net | E38: Elaine Wang | F38: E | G38: 4th Year | H38: 7 | I38: 1 | J38: 1 | K38: 1 | L38: 1 | M38: 1 | N38: 1 | O38: 1 | P38: 1 | Q38: 1 | R38: 1 | S38: 1 | T38: 1 | U38: 1 | V38: 1 | W38: 0 | X38: 0 | Z38: 0
C39: Julia Li | D39: julia.li@warriorlife.net | E39: Elizabeth Huang | F39: E | G39: 2nd Year | H39: 8 | I39: 1 | J39: 1 | K39: 1 | L39: 1 | M39: 1 | N39: 1 | O39: 1 | P39: 1 | Q39: 0.5 | R39: 1 | S39: 1 | T39: 1 | U39: 1 | V39: 1 | W39: 1 | X39: 1 | Y39: 0 | Z39: 1 | AA39: 1
C40: Tiffany Zhang | D40: tiffany.zhang@warriorlife.net | E40: Elizabeth Huang | F40: E | G40: 2nd Year | H40: 8 | I40: 1 | J40: 1 | K40: 1 | L40: 1 | M40: 1 | N40: 1 | O40: 1 | P40: 1 | Q40: 1 | R40: 1 | S40: 1 | T40: 1 | U40: 1 | V40: 1 | W40: 1 | X40: 1 | Y40: 1 | Z40: 1 | AA40: 1
C41: Jamie Jang | D41: woobin.jang@warriorlife.net | E41: Elizabeth Huang | F41: N | G41: 2nd Year | H41: 8 | I41: 1 | J41: 1 | K41: 1 | L41: 1 | M41: 1 | N41: 1 | O41: 1 | P41: 1 | Q41: 1 | R41: 1 | S41: 1 | T41: 1 | U41: 1 | V41: 1 | W41: 1 | X41: 1 | Y41: 1 | Z41: 1 | AA41: 1
C42: Hanna Handy | D42: hanna.handy@warriorlife.net | E42: Elizabeth Huang | F42: N | G42: 1st Year | H42: 8 | I42: 1 | J42: 1 | K42: 1 | L42: 1 | M42: 0 | N42: 1 | O42: 1 | P42: 1 | Q42: 1 | R42: 1 | S42: 1 | T42: 1 | U42: 1 | V42: 0 | W42: 0 | X42: 0 | Y42: 0 | Z42: 0 | AA42: 0
C43: Jennaly Fangonilo | D43: jennaly.fangonilo@warriorlife.net | E43: Elizabeth Huang | F43: E | G43: 3rd Year | H43: 8 | I43: 1 | J43: 1 | K43: 1 | L43: 1 | M43: 1 | N43: 1 | O43: 1 | P43: 1 | Q43: 1 | R43: 1 | S43: 1 | T43: 1 | U43: 1 | V43: 1 | W43: 1 | X43: 1 | Y43: 1 | Z43: 1 | AA43: 1
C44: Gabby Lynch | D44: gabriele.lynch@warriorlife.net | E44: Elizabeth Huang | F44: N | G44: 1st Year | H44: 8 | I44: 1 | J44: 1 | K44: 1 | L44: 1 | M44: 1 | N44: 1 | O44: 1 | P44: 1 | Q44: 1 | R44: 1 | S44: 1 | T44: 1 | U44: 1 | V44: 1 | W44: 1 | X44: 1 | Y44: 1 | Z44: 1 | AA44: 1
C45: Joey Zhu | D45: joey.zhu@warriorlife.net | E45: Elizabeth Huang | F45: N | G45: 1st Year | H45: 8 | I45: 1 | J45: 1 | K45: 1 | L45: 1 | M45: 1 | N45: 1 | O45: 0 | P45: 1 | Q45: 1 | R45: 1 | S45: 1 | T45: 1 | U45: 1 | V45: 1 | W45: 1 | X45: 1 | Y45: 1 | Z45: 1 | AA45: 0
C46: Nathaniel Kommu | D46: nathaniel.kommu@warriorlife.net | E46: Emily Tang | F46: N | G46: 2nd Year | H46: 9 | I46: 1 | J46: 1 | K46: 1 | L46: 1 | M46: 1 | N46: 1 | O46: 1 | P46: 1 | Q46: 1 | R46: 1 | S46: 1 | T46: 1 | U46: 1 | V46: 1 | W46: 1 | X46: 1 | Y46: 1 | Z46: 1 | AA46: 0
C47: Jessica Ma | D47: jessica.ma@warriorlife.net | E47: Emily Tang | F47: N | G47: 2nd Year | H47: 9 | I47: 1 | J47: 1 | K47: 1 | L47: 1 | M47: 1 | N47: 1 | O47: 1 | P47: 1 | Q47: 1 | R47: 1 | S47: 1 | T47: 1 | U47: 1 | V47: 1 | W47: 1 | X47: 1 | Y47: 1 | Z47: 1 | AA47: 1
C48: Kevin Ou | D48: kevin.ou@warriorlife.net | E48: Emily Tang | F48: N | G48: 1st Year | H48: 9 | I48: 1 | J48: 1 | K48: 1 | L48: 1 | M48: 1 | N48: 1 | O48: 1 | P48: 1 | Q48: 1 | R48: 1 | S48: 1 | T48: 1 | U48: 1 | V48: 1 | W48: 1 | X48: 1 | Y48: 1 | Z48: 1 | AA48: 1
C49: Michael Qi | D49: michael.qi@warriorlife.net | E49: Emily Tang | F49: N | G49: 1st Year | H49: 9 | I49: 1 | J49: 0.5 | K49: 1 | L49: 1 | M49: 1 | N49: 1 | O49: 1 | P49: 1 | Q49: 1 | R49: 1 | S49: 1 | T49: 1 | U49: 1 | V49: 1 | W49: 1 | X49: 1 | Y49: 1 | Z49: 1 | AA49: 1
C50: Shawn Wang | D50: zixuan.wang@warriorlife.net | E50: Emily Tang | F50: N | G50: 1st Year | H50: 9 | I50: 1 | J50: 1 | K50: 1 | L50: 1 | M50: 1 | N50: 1 | O50: 1 | P50: 1 | Q50: 1 | R50: 1 | S50: 1 | T50: 1 | U50: 1 | V50: 1 | W50: 1 | X50: 1 | Y50: 1 | Z50: 0 | AA50: 1
... C56: Brooke Harvey | D56: brooke.harvey@warriorlife.net | E56: Grace Xu | F56: N | G56: 1st Year | H56: 10 | I56: 1 | J56: 1 | K56: 1 | L56: 1 | M56: 1 | N56: 1 | O56: 1 | P56: 1 | Q56: 1 | R56: 1 | S56: 1 | T56: 1 | U56: 1 | V56: 1 | W56: 1 | X56: 1 | Y56: 1 | Z56: 1 | AA56: 1
C57: James Yu | D57: james.yu@warriorlife.net | E57: Hannah Li | F57: N | G57: 1st Year | H57: 11 | I57: 1 | J57: 1 | K57: 1 | L57: 1 | M57: 1 | N57: 1 | O57: 1 | P57: 1 | Q57: 1 | R57: 1 | S57: 0 | T57: 0 | U57: 1 | W57: 1
C58: Anay Kalchuri | D58: anay.kalchuri@warriorlife.net | E58: Hannah Li | F58: E | G58: 2nd Year | H58: 11 | I58: 1 | J58: 1 | K58: 1 | L58: 1 | M58: 1 | N58: 1 | O58: 1 | P58: 1 | Q58: 1 | R58: 1 | S58: 1 | T58: 1 | U58: 1 | V58: 1 | W58: 1 | X58: 1 | Y58: 1 | Z58: 1 | AA58: 1
C59: Yamilet Quintana | D59: yamilet.quintana@warriorlife.net | E59: Hannah Li | F59: N | G59: 1st Year | H59: 11 | I59: 1 | J59: 1 | K59: 1 | L59: 1 | M59: 1 | N59: 1 | O59: 1 | P59: 1 | Q59: 1 | R59: 1 | S59: 0.5 | T59: 1 | U59: 1 | V59: 1 | W59: 1 | X59: 1 | Y59: 1 | Z59: 1 | AA59: 1
C60: Eric Jia | D60: eric.jia@warriorlife.net | E60: Hannah Li | F60: E | G60: 3rd Year | H60: 11 | I60: 1 | J60: 1 | K60: 1 | L60: 1 | M60: 1 | N60: 1 | O60: 1 | P60: 1 | Q60: 1 | R60: 1 | S60: 1 | T60: 1 | U60: 1 | V60: 1 | W60: 1 | X60: 1 | Y60: 1 | Z60: 1 | AA60: 1
C61: Jordan Kim | D61: jordan.kim@warriorlife.net | E61: Hannah Li | F61: N | G61: 2nd Year | H61: 11 | I61: 1 | J61: 1 | K61: 1 | L61: 1 | M61: 1 | N61: 1 | O61: 1 | P61: 1 | Q61: 1 | R61: 1 | S61: 1 | T61: 1 | U61: 1 | V61: 1 | W61: 1 | X61: 1 | Y61: 1 | Z61: 1 | AA61: 1
C62: Joshwyn Hong | D62: joshwyn.hong@warriorlife.net | E62: Isabella Yu | F62: N | G62: 1st Year | H62: 12 | I62: 1 | J62: 1 | K62: 1 | L62: 1 | M62: 1 | N62: 1 | O62: 1 | P62: 1 | Q62: 1 | R62: 1 | S62: 1 | T62: 0 | U62: 1 | V62: 1 | W62: 1 | X62: 1 | Y62: 1 | Z62: 1 | AA62: 1
C63: Kinshuk Pandey | D63: kinshuk.pandey@warriorlife.net | E63: Isabella Yu | F63: N | G63: 1st Year | H63: 12 | I63: 1 | J63: 1 | K63: 1 | L63: 1 | M63: 1 | N63: 1 | O63: 0.5 | P63: 1 | Q63: 1 | R63: 1 | S63: 1 | T63: 1 | U63: 1 | V63: 1 | W63: 1 | X63: 1 | Y63: 1 | Z63: 1
C64: Lukshman Senthil | D64: lukshman.senthil@warriorlife.net | E64: Isabella Yu | F64: N | G64: 1st Year | H64: 12 | I64: 1 | J64: 1 | K64: 1 | L64: 1 | M64: 1 | N64: 1 | O64: 1 | P64: 1 | Q64: 1 | R64: 1 | S64: 1 | T64: 1 | U64: 1 | V64: 1 | W64: 1 | X64: 1 | Y64: 1 | Z64: 1
C65: Shalom Kommu | D65: shalom.kommu@warriorlife.net | E65: Isabella Yu | F65: N | G65: 1st Year | H65: 12 | I65: 1 | J65: 1 | K65: 1 | L65: 1 | M65: 0.5 | N65: 1 | O65: 1 | P65: 1 | Q65: 1 | R65: 1 | S65: 1 | T65: 1 | U65: 1 | V65: 1 | W65: 1 | X65: 0.5 | Y65: 1 | Z65: 1 | AA65: 1
C66: Ava Shu | D66: ava.shu@warriorlife.net | E66: Isabella Yu | F66: N | G66: 1st Year | H66: 12 | I66: 1 | J66: 1 | K66: 1 | L66: 1 | M66: 1 | N66: 1 | O66: 0 | P66: 1 | Q66: 1 | R66: 1 | S66: 1 | T66: 1 | U66: 1 | V66: 1 | W66: 1 | X66: 1 | Y66: 0 | Z66: 1
C67: Elaine Choi | D67: elaine.choi@warriorlife.net | E67: Isabella Yu | F67: N | G67: 1st Year | H67: 12 | I67: 1 | J67: 1 | K67: 1 | L67: 1 | M67: 1 | N67: 1 | O67: 1 | P67: 1 | Q67: 1 | R67: 1 | S67: 1 | T67: 1 | U67: 1 | V67: 1 | W67: 1 | X67: 1 | Y67: 1 | Z67: 1
C68: Alyssa Doan | D68: alyssa.doan@warriorlife.net | E68: Jayden Peterson | F68: E | G68: 4th Year | H68: 13 | I68: 1 | J68: 1 | K68: 1 | L68: 0 | M68: 1 | N68: 0.5 | O68: 1 | P68: 1 | Q68: 1 | R68: 1 | S68: 1 | T68: 1 | U68: 1 | V68: 1 | W68: 1 | X68: 1 | Y68: 1 | Z68: 1 | AA68: 1
C69: Armaan Arya | D69: armaan.arya@warriorlife.net | E69: Jayden Peterson | F69: E | G69: 2nd Year | H69: 13 | I69: 1 | J69: 0.5 | K69: 1 | L69: 1 | M69: 1 | N69: 1 | O69: 1 | P69: 1 | Q69: 1 | R69: 1 | S69: 1 | T69: 1 | U69: 1 | V69: 1 | W69: 1 | X69: 1 | Y69: 1 | Z69: 1 | AA69: 1
C70: Kalie Bach | D70: an.bach@warriorlife.net | E70: Jayden Peterson | F70: N | G70: 2nd Year | H70: 13 | I70: 1 | J70: 1 | K70: 1 | L70: 1 | M70: 1 | N70: 1 | O70: 1 | P70: 1 | Q70: 1 | R70: 1 | S70: 1 | T70: 1 | U70: 1 | V70: 1 | W70: 1 | X70: 1 | Y70: 1 | Z70: 1 | AA70: 1
C71: Dana Sun | D71: dana.sun@warriorlife.net | E71: Jayden Peterson | F71: N | G71: 2nd Year | H71: 13 | I71: 1 | J71: 1 | K71: 1 | L71: 0.5 | M71: 1 | N71: 1 | O71: 1 | P71: 1 | Q71: 1 | R71: 1 | S71: 1 | T71: 1 | U71: 1 | V71: 1 | W71: 1 | X71: 1 | Y71: 1 | Z71: 1 | AA71: 1
C72: Nishanth Duvedi | D72: nishanth.duvedi@warriorlife.net | E72: Jayden Peterson | F72: N | G72: 2nd Year | H72: 13 | I72: 1 | J72: 1 | K72: 1 | L72: 1 | M72: 1 | N72: 1 | O72: 1 | P72: 1 | Q72: 1 | R72: 1 | S72: 1 | T72: 1 | U72: 1 | V72: 1 | W72: 1 | X72: 1 | Y72: 1 | Z72: 1 | AA72: 1
C73: Saira Bhatia | D73: saira.bhatia@warriorlife.net | E73: Kyle Chen | F73: N | G73: 2nd Year | H73: 14 | I73: 1 | J73: 1 | K73: 1 | L73: 1 | M73: 1 | N73: 1 | O73: 1 | P73: 1 | Q73: 1 | R73: 1 | S73: 1 | T73: 1 | U73: 1 | V73: 1 | W73: 1 | X73: 1 | Y73: 1 | Z73: 1 | AA73: 1
C74: Ella Weng | D74: shanzhi.weng@warriorlife.net | E74: Kyle Chen | F74: N | G74: 2nd Year | H74: 14 | I74: 1 | J74: 1 | K74: 1 | L74: 1 | M74: 1 | N74: 1 | O74: 1 | P74: 1 | Q74: 1 | R74: 1 | S74: 1 | T74: 1 | U74: 1 | V74: 1 | W74: 1 | X74: 1 | Y74: 1 | Z74: 1 | AA74: 1
C75: Tristan Sansone | D75: tristan.sansone@warriorlife.net | E75: Kyle Chen | F75: E | G75: 4th Year | H75: 14 | I75: 1 | J75: 1 | K75: 1 | L75: 1 | M75: 1 | N75: 1 | O75: 1 | P75: 1 | Q75: 1 | R75: 1 | S75: 1 | T75: 1 | U75: 1 | V75: 1 | W75: 1 | X75: 1 | Y75: 1 | Z75: 1 | AA75: 1
C76: Preston Lee | D76: preston.lee@warriorlife.net | E76: Kyle Chen | F76: E | G76: 2nd Year | H76: 14 | I76: 1 | J76: 1 | K76: 1 | L76: 1 | M76: 1 | N76: 1 | O76: 1 | P76: 1 | Q76: 0 | R76: 1 | S76: 1 | T76: 1 | U76: 1 | V76: 1 | W76: 1 | X76: 1 | Y76: 0 | Z76: 1 | AA76: 1
C77: Romir Bhatt | D77: romir.bhatt@warriorlife.net | E77: Kyle Chen | F77: E | G77: 3rd Year | H77: 14 | I77: 1 | J77: 1 | K77: 1 | L77: 1 | M77: 1 | N77: 1 | O77: 1 | P77: 1 | Q77: 1 | R77: 1 | S77: 1 | T77: 1 | U77: 1 | V77: 1 | W77: 1 | X77: 1 | Y77: 1 | Z77: 1 | AA77: 1
C78: Tiffany Le | D78: tiffany.le@warriorlife.net | E78: Kyle Chen | F78: E | G78: 3rd Year | H78: 14 | I78: 1 | J78: 1 | K78: 1 | L78: 0.5 | M78: 0.5 | N78: 0.5 | O78: 1 | P78: 1 | Q78: 1 | R78: 1 | S78: 0 | T78: 1 | U78: 1 | V78: 1 | W78: 1 | X78: 1 | Y78: 0 | Z78: 1 | AA78: 1
C79: Timothy Feng | D79: timothy.feng@warriorlife.net | E79: Melody Leong | F79: N | G79: 1st Year | H79: 15 | I79: 1 | J79: 1 | K79: 1 | L79: 1 | M79: 1 | N79: 1 | O79: 1 | P79: 1 | Q79: 1 | R79: 0.5 | S79: 1 | T79: 1 | U79: 1 | V79: 1 | W79: 1 | X79: 1 | Y79: 1 | Z79: 1
C80: Andrew Huang | D80: andrew.huang@warriorlife.net | E80: Melody Leong | F80: N | H80: 15 | I80: 1 | J80: 1 | K80: 0 | L80: 1 | M80: 1 | N80: 0 | O80: 1 | P80: 1 | Q80: 1 | R80: 1 | S80: 1 | T80: 1 | U80: 1 | V80: 1 | W80: 1 | X80: 1 | Y80: 1 | Z80: 1
C81: Nathan Pham | D81: nathan.pham@warriorlife.net | E81: Melody Leong | F81: E | G81: 3rd Year | H81: 15 | I81: 1 | J81: 1 | K81: 0 | L81: 1 | M81: 1 | N81: 1 | O81: 1 | P81: 1 | Q81: 1 | R81: 1 | S81: 1 | T81: 1 | U81: 1 | V81: 1 | W81: 1 | X81: 0 | Y81: 1 | Z81: 1
C82: Sidharth Swaminathan | D82: s.swaminathan@warriorlife.net | E82: Melody Leong | F82: N | G82: 1st Year | H82: 15 | I82: 1 | J82: 1 | K82: 1 | L82: 1 | M82: 1 | N82: 1 | O82: 1 | P82: 1 | Q82: 1 | R82: 1 | S82: 1 | T82: 1 | U82: 1 | V82: 1 | W82: 1 | X82: 1 | Y82: 1 | Z82: 1
C83: Braden Fong | D83: braden.fong@warriorlife.net | E83: Melody Leong | F83: N | G83: 2nd Year | H83: 15 | I83: 0.5 | J83: 1 | K83: 1 | L83: 1 | M83: 1 | N83: 0.5 | O83: 1 | P83: 1 | Q83: 1 | R83: 1 | S83: 1 | T83: 1 | U83: 1 | V83: 1 | W83: 1 | X83: 1 | Y83: 1 | Z83: 1
C84: John Kirchenbauer | D84: john.kirchenbauer@warriorlife.net | E84: Melody Leong | F84: N | G84: 2nd Year | H84: 15 | I84: 1 | J84: 1 | K84: 1 | L84: 1 | M84: 1 | N84: 0.5 | O84: 0.5 | P84: 1 | Q84: 1 | R84: 0.5 | S84: 1 | T84: 1 | U84: 1 | V84: 1 | W84: 1 | X84: 1 | Y84: 1 | Z84: 1
C85: Ivy Guo | D85: ivy.guo@warriorlife.net | E85: Mia Tran | F85: N | G85: 1st Year | H85: 16 | I85: 1 | J85: 1 | K85: 1 | L85: 1 | M85: 1 | N85: 1 | O85: 0.5 | P85: 1 | Q85: 1 | R85: 1 | S85: 1 | T85: 1 | U85: 1 | V85: 1 | W85: 1 | X85: 1 | Y85: 1 | Z85: 1 | AA85: 0.5
C86: Sophie Yu | D86: chunka.yu@warriorlife.net | E86: Mia Tran | F86: N | G86: 1st Year | H86: 16 | I86: 1 | J86: 1 | K86: 1 | L86: 1 | M86: 1 | N86: 1 | O86: 1 | P86: 1 | Q86: 1 | R86: 1 | S86: 1 | T86: 1 | U86: 1 | V86: 1 | W86: 1 | X86: 1 | Y86: 1 | Z86: 1 | AA86: 1
C87: Hongyao Fan | D87: hongyao.fan@warriorlife.net | E87: Mia Tran | F87: N | G87: 1st Year | H87: 16 | I87: 1 | J87: 1 | K87: 1 | L87: 1 | M87: 1 | N87: 1 | O87: 0.5 | P87: 0 | Q87: 0 | R87: 1 | S87: 0 | T87: 0 | U87: 1 | V87: 0 | W87: 0 | X87: 0 | Y87: 0 | Z87: 0 | AA87: 0
C88: Jenny Lee | D88: jenny.lee@warriorlife.net | E88: Mia Tran | F88: N | G88: 1st Year | H88: 16 | I88: 1 | J88: 1 | K88: 1 | L88: 1 | M88: 1 | N88: 1 | O88: 1 | P88: 1 | Q88: 1 | R88: 1 | S88: 1 | T88: 1 | U88: 1 | V88: 1 | W88: 0.5 | X88: 1 | Y88: 1 | Z88: 1 | AA88: 1
C89: Jayden Leggio | D89: jayden.leggio@warriorlife.net | E89: Mia Tran | F89: E | G89: 3rd Year | H89: 25 | I89: 1 | J89: 1 | K89: 0.5 | L89: 1 | M89: 1 | N89: 1 | O89: 1 | P89: 1 | Q89: 1 | R89: 1 | S89: 1 | T89: 1 | U89: 1 | V89: 0 | W89: 0 | X89: 0 | Y89: 0 | Z89: 0 | AA89: 0
C90: Lucas Moyers | D90: lucas.moyers@warriorlife.net | E90: Mia Tran | F90: N | G90: 2nd Year | H90: 25 | I90: 1 | J90: 1 | K90: 1 | L90: 1 | M90: 1 | N90: 0.5 | O90: 1 | P90: 1 | Q90: 1 | R90: 1 | S90: 1 | T90: 1 | U90: 1 | V90: 0 | W90: 0 | X90: 0 | Y90: 0 | Z90: 0 | AA90: 0
C91: Micah Bass | D91: micah.bass@warriorlife.net | E91: Natalie Zhang | F91: N | G91: 1st Year | H91: 17 | I91: 1 | J91: 1 | K91: 1 | L91: 1 | M91: 1 | N91: 1 | O91: 1 | P91: 1 | Q91: 1 | R91: 1 | S91: 0 | T91: 1 | U91: 1 | V91: 0 | W91: 0 | X91: 0 | Y91: 0 | Z91: 0 | AA91: 0
C92: William Qu | D92: william.qu@warriorlife.net | E92: Natalie Zhang | F92: N | G92: 1st Year | H92: 17 | I92: 1 | J92: 1 | K92: 1 | L92: 1 | M92: 1 | N92: 1 | O92: 1 | P92: 1 | Q92: 1 | R92: 1 | S92: 1 | T92: 1 | U92: 1 | V92: 1 | W92: 1 | X92: 0.5 | Y92: 1 | Z92: 1 | AA92: 0
C93: Zayd Bashadi | D93: zayd.bashadi@warriorlife.net | E93: Natalie Zhang | F93: N | G93: 1st Year | H93: 17 | I93: 1 | J93: 1 | K93: 1 | L93: 1 | M93: 1 | N93: 1 | O93: 1 | P93: 1 | Q93: 1 | R93: 1 | S93: 1 | T93: 1 | U93: 1 | V93: 1 | W93: 1 | X93: 1 | Y93: 1 | Z93: 1 | AA93: 0
C94: Arthur Huang | D94: arthur.huang@warriorlife.net | E94: Natalie Zhang | F94: N | G94: 1st Year | H94: 17 | I94: 1 | J94: 1 | K94: 1 | L94: 1 | M94: 1 | N94: 1 | O94: 1 | P94: 1 | Q94: 1 | R94: 1 | S94: 1 | T94: 1 | U94: 1 | V94: 1 | W94: 1 | X94: 1 | Y94: 1 | Z94: 1 | AA94: 1
C95: Daniel Dorn | D95: d.dorndecarvalho@warriorlife.net | E95: Natalie Zhang | F95: N | G95: 1st Year | H95: 17 | I95: 0.5 | J95: 1 | K95: 1 | L95: 1 | M95: 1 | N95: 1 | O95: 1 | P95: 0 | Q95: 0 | R95: 1 | S95: 0 | T95: 0 | U95: 0 | V95: 0 | W95: 0 | X95: 0 | Y95: 0 | Z95: 0 | AA95: 0
C96: Purab Shah | D96: purab.shah@warriorlife.net | E96: Natalie Zhang | F96: N | G96: 2nd Year | H96: 17 | I96: 1 | J96: 1 | K96: 1 | L96: 1 | M96: 1 | N96: 1 | O96: 1 | P96: 1 | Q96: 1 | R96: 1 | S96: 1 | T96: 1 | U96: 1 | V96: 1 | W96: 1 | X96: 1 | Y96: 1 | Z96: 1 | AA96: 1
C97: Ethan Chen | D97: ethan.chen@warriorlife.net | E97: Nicholas Kiang | F97: N | G97: 1st Year | H97: 18 | I97: 1 | J97: 1 | K97: 1 | L97: 1 | M97: =MIN(M92:N96) -> 1 | N97: 1 | O97: 1 | P97: 1 | Q97: 1 | R97: 1 | S97: 1 | T97: 1 | U97: 1 | V97: 1 | W97: 0 | X97: 1 | Y97: 1 | Z97: 1
C98: Gordon Li | D98: gordon.li@warriorlife.net | E98: Nicholas Kiang | F98: N | G98: 1st Year | H98: 18 | I98: 1 | J98: 1 | K98: 0 | L98: 1 | M98: 1 | N98: 1 | O98: 1 | P98: 1 | Q98: 1 | R98: 1 | S98: 0.5 | T98: 1 | U98: 1 | V98: 1 | W98: 1 | X98: 1 | Y98: 1 | Z98: 1
C99: Chloe Xiao | D99: chloe.xiao@warriorlife.net | E99: Nicholas Kiang | F99: N | G99: 2nd Year | H99: 18 | I99: 1 | J99: 1 | K99: 1 | L99: 1 | M99: 1 | N99: 1 | O99: 1 | P99: 1 | Q99: 1 | R99: 1 | S99: 1 | T99: 1 | U99: 1 | V99: 1 | W99: 0 | X99: 1 | Y99: 1 | Z99: 1
C100: Karen Xiao | D100: karen.xiao@warriorlife.net | E100: Nicholas Kiang | F100: N | G100: 2nd Year | H100: 18 | I100: 1 | J100: 1 | K100: 1 | L100: 1 | M100: 1 | N100: 1 | O100: 1 | P100: 1 | Q100: 1 | R100: 1 | S100: 1 | T100: 1 | U100: 1 | V100: 1 | W100: 1 | X100: 1 | Y100: 1 | Z100: 1
C101: Jaylyn Chong | D101: jaylyn.chong@warriorlife.net | E101: Nicholas Kiang | F101: E | G101: 4th year | H101: 18 | I101: 1 | J101: 1 | K101: 1 | L101: 1 | M101: 1 | N101: 1 | O101: 1 | P101: 1 | Q101: 1 | R101: 1 | S101: 1 | T101: 1 | U101: 1 | V101: 1 | W101: 1 | X101: 1 | Y101: 1 | Z101: 1
C102: Eila Mcginley | D102: eila.mcginley@warriorlife.net | E102: Nicholas Kiang | F102: N | G102: 2nd Year | H102: 18 | I102: 1 | J102: 1 | K102: 1 | L102: 1 | M102: 1 | N102: 1 | O102: 1 | P102: 1 | Q102: 1 | R102: 1 | S102: 1 | T102: 1 | U102: 1 | V102: 1 | W102: 1 | X102: 1 | Y102: 1 | Z102: 1
C103: Julia Zhou | D103: julia.zhou@warriorlife.net | E103: Nicholas Kiang | F103: N | G103: 2nd Year | H103: 18 | I103: 1 | J103: 1 | K103: 1 | L103: 1 | M103: 1 | N103: 1 | O103: 1 | P103: 1 | Q103: 1 | R103: 1 | S103: 1 | T103: 1 | U103: 1 | V103: 1 | W103: 1 | X103: 1 | Y103: 1 | Z103: 1
C104: Isabella Denena | D104: isabella.denena@warriorlife.net | E104: Om Loomba | F104: E | G104: 4th Year | H104: 19 | I104: 1 | J104: 1 | K104: 1 | L104: 1 | M104: 1 | N104: 1 | O104: 1 | P104: 1 | Q104: 1 | R104: 1 | S104: 1 | T104: 1 | U104: 1 | V104: 1 | W104: 1 | X104: 1 | Y104: 1 | Z104: 1
C105: Yoon Koo | D105: jayoon.koo@warriorlife.net | E105: Om Loomba | F105: N | G105: 2nd Year | H105: 19 | I105: 1 | J105: 1 | K105: 1 | L105: 1 | M105: 1 | N105: 1 | O105: 1 | P105: 1 | Q105: 1 | R105: 1 | S105: 1 | T105: 1 | U105: 1 | V105: 1 | W105: 1 | X105: 1 | Y105: 1 | Z105: 1
...

Sheet Workshop Attendance 
A1: Timestamp | B1: Email Address | C1: Legal first name | D1: Last name | E1: Workshop Room | F1: What mentee category are you in? (Analytics will track so dont lie) | G1: Who is your mentor? | H1: What's the answer to today's question? | L1: Email | M1: Mentor Name | N1: Nov. or Exp. | O1: Year in DECA | P1: Pod # 0 | Q1: Event | R1: =S1-7 -> 45917 | S1: =T1-7 -> 45924 | T1: =U1-7 -> 45931 | U1: 45938 | V1: 45945 | W1: 45952 | X1: =W1+7 -> 45959 | Y1: =X1+7 -> 45966 | Z1: =Y1+7 -> 45973 | AA1: =Z1+7 -> 45980 | AB1: =AA1+14 -> 45994 | AC1: =AB1+7 -> 46001 | AD1: =AC1+28 -> 46029 | AE1: =AD1+7 -> 46036 | AF1: =AE1+7 -> 46043 | AG1: =AF1+7 -> 46050 | AH1: =AG1+7 -> 46057 | AI1: =AH1+7 -> 46064
A2: 45917.647 | B2: aditya.poduri@warriorlife.net | C2: Aditya | D2: Poduri | E2: G106 | F2: Novice (1st year or 2nd years who haven't placed top 10 (SCDC) or get top 3 (SVCDC)) | G2: Elaine Wang | H2: Make sure not to include too many icons, that can end up becoming a bit redundant. | K2: Amber Chang | L2: ambery.chang@warriorlife.net | M2: Aaron Vu | N2: N | O2: 1st Year | P2: 1 | Q2: BOR | R2: =IF(COUNTIF(B$2:B$149,L2)=0,0,1) -> 1 | S2: =IF(COUNTIF(B$150:B$274,L2)=0,0,1) -> 1 | T2: =IF(COUNTIF(B$275:B$401,L2)=0,0,1) -> 0 | U2: =IFERROR(__xludf.DUMMYFUNCTION("IFERROR(IF(Match(L2,IMPORTRANGE(""https://docs.google.com/spreadsheets/d/1CAXKDiOnZb21bZOY_nacH9xI9AiD-nH8ZZQAwYKkVC0/edit?usp=drivesdk"",""Completed Exams!A1:A135""),0),1), 0)"),0.0) -> 0 | V2: =IF(COUNTIF(B$416:B$535,L2)=0,0,1) -> 1 | W2: 1 | X2: =IF(COUNTIF(B$603:B$725,L2)=0,0,1) -> 1 | Y2: =IF(COUNTIF(B$725:B$844,L2)=0,0,1) -> 1 | Z2: =IF(COUNTIF(B$845:B$969,L2)=0,0,1) -> 1 | AA2: =IF(COUNTIF(B$971:B$1124,L2)=0,0,1) -> 1 | AB2: =IFERROR(__xludf.DUMMYFUNCTION("IFERROR(IF(Match(L2,IMPORTRANGE(""https://docs.google.com/spreadsheets/d/1n1sT_Q_W3mKmn2Yrd8qcNzuRD4zr4DB9gqARnjQ30B4/edit?gid=1918970062#gid=1918970062"",""Form Responses 1!B2:B49""),0),1), 0)"),0.0) -> 0 | AC2: =IF(COUNTIF(B$1145:B$1305,L2)=0,0,1) -> 1 | AD2: 1 | AE2: =IFERROR(__xludf.DUMMYFUNCTION("IFERROR(IF(Match(L2,IMPORTRANGE(""https://docs.google.com/spreadsheets/d/1hvckjcCpxEuDQDPrBMml_I1kBhYyjrgR8qBKC9QGVUc/edit?resourcekey=&gid=230793720#gid=230793720"",""Form Responses 1!B2:B199""),0),1), 0)"),0.0) -> 0 | AF2: =IFERROR(__xludf.DUMMYFUNCTION("IFERROR(IF(Match(L2,IMPORTRANGE(""https://docs.google.com/spreadsheets/d/1UY0hI2S83Fmafa5P-C1LM9yqe4v4qIKTnVy_CzLzRPs/edit?resourcekey=&gid=1583835601#gid=1583835601"",""Form Responses 1!B2:B194""),0),1), 0)"),0.0) -> 0 | AG2: =IFERROR(__xludf.DUMMYFUNCTION("IFERROR(IF(Match(L2,IMPORTRANGE(""https://docs.google.com/spreadsheets/d/1hO4mQ22n6cudUygJ2ss_JeJdm2Ua_7hJl_79lWWEtic/edit?resourcekey=&gid=2087212010#gid=2087212010"",""Form Responses 1!B2:B104""),0),1), 0)"),0.0) -> 0 | AH2: =IFERROR(__xludf.DUMMYFUNCTION("IFERROR(IF(Match(L2,IMPORTRANGE(""https://docs.google.com/spreadsheets/d/1HbfCXhSXbtTODKKY1MOFwJccyhgDKD0J9sO1k5l_6lM/edit?resourcekey=&gid=1616384832#gid=1616384832"",""Form Responses 1!E2:E143""),0),1), 0)"),0.0) -> 0
A3: 45917.647 | B3: armaan.vidhani@warriorlife.net | C3: Armaan | D3: Vidhani | E3: G130 | F3: Novice (1st year or 2nd years who haven't placed top 10 (SCDC) or get top 3 (SVCDC)) | G3: Revathi | H3: I’ve learned not to use that many icons. | K3: Nina Ling | L3: nina.ling@warriorlife.net | M3: Aaron Vu | N3: N | O3: 1st Year | P3: 1 | Q3: BOR | R3: =IF(COUNTIF(B$2:B$149,L3)=0,0,1) -> 1 | S3: =IF(COUNTIF(B$150:B$274,L3)=0,0,1) -> 1 | T3: =IF(COUNTIF(B$275:B$401,L3)=0,0,1) -> 1 | U3: =IFERROR(__xludf.DUMMYFUNCTION("IFERROR(IF(Match(L3,IMPORTRANGE(""https://docs.google.com/spreadsheets/d/1CAXKDiOnZb21bZOY_nacH9xI9AiD-nH8ZZQAwYKkVC0/edit?usp=drivesdk"",""Completed Exams!A1:A135""),0),1), 0)"),0.0) -> 0 | V3: =IF(COUNTIF(B$416:B$535,L3)=0,0,1) -> 1 | W3: =IF(COUNTIF(B$535:B$602,L3)=0,0,1) -> 0 | X3: =IF(COUNTIF(B$603:B$725,L3)=0,0,1) -> 1 | Y3: =IF(COUNTIF(B$725:B$844,L3)=0,0,1) -> 1 | Z3: =IF(COUNTIF(B$845:B$969,L3)=0,0,1) -> 1 | AA3: =IF(COUNTIF(B$971:B$1124,L3)=0,0,1) -> 1 | AB3: 1 | AC3: =IF(COUNTIF(B$1145:B$1305,L3)=0,0,1) -> 1 | AD3: 1 | AE3: =IFERROR(__xludf.DUMMYFUNCTION("IFERROR(IF(Match(L3,IMPORTRANGE(""https://docs.google.com/spreadsheets/d/1hvckjcCpxEuDQDPrBMml_I1kBhYyjrgR8qBKC9QGVUc/edit?resourcekey=&gid=230793720#gid=230793720"",""Form Responses 1!B2:B199""),0),1), 0)"),0.0) -> 0 | AF3: =IFERROR(__xludf.DUMMYFUNCTION("IFERROR(IF(Match(L3,IMPORTRANGE(""https://docs.google.com/spreadsheets/d/1UY0hI2S83Fmafa5P-C1LM9yqe4v4qIKTnVy_CzLzRPs/edit?resourcekey=&gid=1583835601#gid=1583835601"",""Form Responses 1!B2:B194""),0),1), 0)"),0.0) -> 0 | AG3: =IFERROR(__xludf.DUMMYFUNCTION("IFERROR(IF(Match(L3,IMPORTRANGE(""https://docs.google.com/spreadsheets/d/1hO4mQ22n6cudUygJ2ss_JeJdm2Ua_7hJl_79lWWEtic/edit?resourcekey=&gid=2087212010#gid=2087212010"",""Form Responses 1!B2:B104""),0),1), 0)"),0.0) -> 0 | AH3: =IFERROR(__xludf.DUMMYFUNCTION("IFERROR(IF(Match(L3,IMPORTRANGE(""https://docs.google.com/spreadsheets/d/1HbfCXhSXbtTODKKY1MOFwJccyhgDKD0J9sO1k5l_6lM/edit?resourcekey=&gid=1616384832#gid=1616384832"",""Form Responses 1!E2:E143""),0),1), 0)"),0.0) -> 0
A4: 45917.647 | B4: tan.pham@warriorlife.net | C4: Tan | D4: Pham | E4: G130 | F4: Experienced (2nd years who have placed top 10 (SCDC) or get top 3 (SVCDC) or 3rd and 4th years) | G4: Sophia White | H4: Templates are your best friend. | K4: Elize Kaldani | L4: elize.kaldani@warriorlife.net | M4: Aaron Vu | N4: N | O4: 1st Year | P4: 1 | Q4: BOR | R4: =IF(COUNTIF(B$2:B$149,L4)=0,0,1) -> 1 | S4: =IF(COUNTIF(B$150:B$274,L4)=0,0,1) -> 1 | T4: =IF(COUNTIF(B$275:B$401,L4)=0,0,1) -> 1 | U4: =IFERROR(__xludf.DUMMYFUNCTION("IFERROR(IF(Match(L4,IMPORTRANGE(""https://docs.google.com/spreadsheets/d/1CAXKDiOnZb21bZOY_nacH9xI9AiD-nH8ZZQAwYKkVC0/edit?usp=drivesdk"",""Completed Exams!A1:A135""),0),1), 0)"),0.0) -> 0 | V4: =IF(COUNTIF(B$416:B$535,L4)=0,0,1) -> 1 | W4: 1 | X4: =IF(COUNTIF(B$603:B$725,L4)=0,0,1) -> 0 | Y4: =IF(COUNTIF(B$725:B$844,L4)=0,0,1) -> 1 | Z4: =IF(COUNTIF(B$845:B$969,L4)=0,0,1) -> 1 | AA4: =IF(COUNTIF(B$971:B$1124,L4)=0,0,1) -> 1 | AB4: =IFERROR(__xludf.DUMMYFUNCTION("IFERROR(IF(Match(L4,IMPORTRANGE(""https://docs.google.com/spreadsheets/d/1n1sT_Q_W3mKmn2Yrd8qcNzuRD4zr4DB9gqARnjQ30B4/edit?gid=1918970062#gid=1918970062"",""Form Responses 1!B2:B49""),0),1), 0)"),0.0) -> 0 | AC4: =IF(COUNTIF(B$1145:B$1305,L4)=0,0,1) -> 1 | AD4: 1 | AE4: =IFERROR(__xludf.DUMMYFUNCTION("IFERROR(IF(Match(L4,IMPORTRANGE(""https://docs.google.com/spreadsheets/d/1hvckjcCpxEuDQDPrBMml_I1kBhYyjrgR8qBKC9QGVUc/edit?resourcekey=&gid=230793720#gid=230793720"",""Form Responses 1!B2:B199""),0),1), 0)"),0.0) -> 0 | AF4: =IFERROR(__xludf.DUMMYFUNCTION("IFERROR(IF(Match(L4,IMPORTRANGE(""https://docs.google.com/spreadsheets/d/1UY0hI2S83Fmafa5P-C1LM9yqe4v4qIKTnVy_CzLzRPs/edit?resourcekey=&gid=1583835601#gid=1583835601"",""Form Responses 1!B2:B194""),0),1), 0)"),0.0) -> 0 | AG4: =IFERROR(__xludf.DUMMYFUNCTION("IFERROR(IF(Match(L4,IMPORTRANGE(""https://docs.google.com/spreadsheets/d/1hO4mQ22n6cudUygJ2ss_JeJdm2Ua_7hJl_79lWWEtic/edit?resourcekey=&gid=2087212010#gid=2087212010"",""Form Responses 1!B2:B104""),0),1), 0)"),0.0) -> 0 | AH4: =IFERROR(__xludf.DUMMYFUNCTION("IFERROR(IF(Match(L4,IMPORTRANGE(""https://docs.google.com/spreadsheets/d/1HbfCXhSXbtTODKKY1MOFwJccyhgDKD0J9sO1k5l_6lM/edit?resourcekey=&gid=1616384832#gid=1616384832"",""Form Responses 1!E2:E143""),0),1), 0)"),0.0) -> 0
A5: 45917.647 | B5: nathaniel.kommu@warriorlife.net | C5: Nathaniel | D5: Kommu | E5: G130 | F5: Novice (1st year or 2nd years who haven't placed top 10 (SCDC) or top 3 (SVCDC)) | G5: Emily Tang | H5: Split information into multiple parts | K5: Geralyn Loo | L5: geralyn.loo@warriorlife.net | M5: Aaron Vu | N5: N | O5: 1st Year | P5: 1 | Q5: BMOR | R5: =IF(COUNTIF(B$2:B$149,L5)=0,0,1) -> 1 | S5: =IF(COUNTIF(B$150:B$274,L5)=0,0,1) -> 1 | T5: =IF(COUNTIF(B$275:B$401,L5)=0,0,1) -> 1 | U5: =IFERROR(__xludf.DUMMYFUNCTION("IFERROR(IF(Match(L5,IMPORTRANGE(""https://docs.google.com/spreadsheets/d/1CAXKDiOnZb21bZOY_nacH9xI9AiD-nH8ZZQAwYKkVC0/edit?usp=drivesdk"",""Completed Exams!A1:A135""),0),1), 0)"),0.0) -> 0 | V5: =IF(COUNTIF(B$416:B$535,L5)=0,0,1) -> 1 | W5: =IF(COUNTIF(B$535:B$602,L5)=0,0,1) -> 1 | X5: =IF(COUNTIF(B$603:B$725,L5)=0,0,1) -> 1 | Y5: =IF(COUNTIF(B$725:B$844,L5)=0,0,1) -> 1 | Z5: =IF(COUNTIF(B$845:B$969,L5)=0,0,1) -> 1 | AA5: =IF(COUNTIF(B$971:B$1124,L5)=0,0,1) -> 1 | AB5: =IFERROR(__xludf.DUMMYFUNCTION("IFERROR(IF(Match(L5,IMPORTRANGE(""https://docs.google.com/spreadsheets/d/1n1sT_Q_W3mKmn2Yrd8qcNzuRD4zr4DB9gqARnjQ30B4/edit?gid=1918970062#gid=1918970062"",""Form Responses 1!B2:B49""),0),1), 0)"),0.0) -> 0 | AC5: =IF(COUNTIF(B$1145:B$1305,L5)=0,0,1) -> 1 | AD5: 1 | AE5: =IFERROR(__xludf.DUMMYFUNCTION("IFERROR(IF(Match(L5,IMPORTRANGE(""https://docs.google.com/spreadsheets/d/1hvckjcCpxEuDQDPrBMml_I1kBhYyjrgR8qBKC9QGVUc/edit?resourcekey=&gid=230793720#gid=230793720"",""Form Responses 1!B2:B199""),0),1), 0)"),0.0) -> 0 | AF5: =IFERROR(__xludf.DUMMYFUNCTION("IFERROR(IF(Match(L5,IMPORTRANGE(""https://docs.google.com/spreadsheets/d/1UY0hI2S83Fmafa5P-C1LM9yqe4v4qIKTnVy_CzLzRPs/edit?resourcekey=&gid=1583835601#gid=1583835601"",""Form Responses 1!B2:B194""),0),1), 0)"),0.0) -> 0 | AG5: =IFERROR(__xludf.DUMMYFUNCTION("IFERROR(IF(Match(L5,IMPORTRANGE(""https://docs.google.com/spreadsheets/d/1hO4mQ22n6cudUygJ2ss_JeJdm2Ua_7hJl_79lWWEtic/edit?resourcekey=&gid=2087212010#gid=2087212010"",""Form Responses 1!B2:B104""),0),1), 0)"),0.0) -> 0 | AH5: =IFERROR(__xludf.DUMMYFUNCTION("IFERROR(IF(Match(L5,IMPORTRANGE(""https://docs.google.com/spreadsheets/d/1HbfCXhSXbtTODKKY1MOFwJccyhgDKD0J9sO1k5l_6lM/edit?resourcekey=&gid=1616384832#gid=1616384832"",""Form Responses 1!E2:E143""),0),1), 0)"),0.0) -> 0
A6: 45917.647 | B6: allen.tu@warriorlife.net | C6: Allen | D6: Tu | E6: G130 | F6: Experienced (2nd years who have placed top 10 (SCDC) or top 3 (SVCDC) or 3rd and 4th years) | G6: Suneri | H6: Don’t use a lot of icons | K6: Kashvi Lath | L6: kashvi.lath@warriorlife.net | M6: Aaron Vu | N6: N | O6: 1st Year | P6: 1 | Q6: BOR | R6: =IF(COUNTIF(B$2:B$149,L6)=0,0,1) -> 1 | S6: =IF(COUNTIF(B$150:B$274,L6)=0,0,1) -> 1 | T6: =IF(COUNTIF(B$275:B$401,L6)=0,0,1) -> 1 | U6: =IFERROR(__xludf.DUMMYFUNCTION("IFERROR(IF(Match(L6,IMPORTRANGE(""https://docs.google.com/spreadsheets/d/1CAXKDiOnZb21bZOY_nacH9xI9AiD-nH8ZZQAwYKkVC0/edit?usp=drivesdk"",""Completed Exams!A1:A135""),0),1), 0)"),0.0) -> 0 | V6: =IF(COUNTIF(B$416:B$535,L6)=0,0,1) -> 1 | W6: =IF(COUNTIF(B$535:B$602,L6)=0,0,1) -> 1 | X6: =IF(COUNTIF(B$603:B$725,L6)=0,0,1) -> 1 | Y6: =IF(COUNTIF(B$725:B$844,L6)=0,0,1) -> 1 | Z6: =IF(COUNTIF(B$845:B$969,L6)=0,0,1) -> 1 | AA6: =IF(COUNTIF(B$971:B$1124,L6)=0,0,1) -> 1 | AB6: 1 | AC6: =IF(COUNTIF(B$1145:B$1305,L6)=0,0,1) -> 1 | AD6: 1 | AE6: =IFERROR(__xludf.DUMMYFUNCTION("IFERROR(IF(Match(L6,IMPORTRANGE(""https://docs.google.com/spreadsheets/d/1hvckjcCpxEuDQDPrBMml_I1kBhYyjrgR8qBKC9QGVUc/edit?resourcekey=&gid=230793720#gid=230793720"",""Form Responses 1!B2:B199""),0),1), 0)"),0.0) -> 0 | AF6: =IFERROR(__xludf.DUMMYFUNCTION("IFERROR(IF(Match(L6,IMPORTRANGE(""https://docs.google.com/spreadsheets/d/1UY0hI2S83Fmafa5P-C1LM9yqe4v4qIKTnVy_CzLzRPs/edit?resourcekey=&gid=1583835601#gid=1583835601"",""Form Responses 1!B2:B194""),0),1), 0)"),0.0) -> 0 | AG6: =IFERROR(__xludf.DUMMYFUNCTION("IFERROR(IF(Match(L6,IMPORTRANGE(""https://docs.google.com/spreadsheets/d/1hO4mQ22n6cudUygJ2ss_JeJdm2Ua_7hJl_79lWWEtic/edit?resourcekey=&gid=2087212010#gid=2087212010"",""Form Responses 1!B2:B104""),0),1), 0)"),0.0) -> 0 | AH6: =IFERROR(__xludf.DUMMYFUNCTION("IFERROR(IF(Match(L6,IMPORTRANGE(""https://docs.google.com/spreadsheets/d/1HbfCXhSXbtTODKKY1MOFwJccyhgDKD0J9sO1k5l_6lM/edit?resourcekey=&gid=1616384832#gid=1616384832"",""Form Responses 1!E2:E143""),0),1), 0)"),0.0) -> 0
A7: 45917.647 | B7: kayla.tan@warriorlife.net | C7: Kayla | D7: Tan | E7: G130 | F7: Experienced (2nd years who have placed top 10 (SCDC) or top 3 (SVCDC) or 3rd and 4th years) | G7: Jayden | H7: Less icons are better | K7: Gary Zhang | L7: shuhan.zhang@warriorlife.net | M7: Alicia Tang | N7: E | O7: 3rd Year | P7: 2 | Q7: ESB | R7: =IF(COUNTIF(B$2:B$149,L7)=0,0,1) -> 1 | S7: =IF(COUNTIF(B$150:B$274,L7)=0,0,1) -> 0 | T7: =IF(COUNTIF(B$275:B$401,L7)=0,0,1) -> 0 | U7: 1 | V7: =IF(COUNTIF(B$416:B$535,L7)=0,0,1) -> 0 | W7: =IF(COUNTIF(B$535:B$602,L7)=0,0,1) -> 1 | X7: =IF(COUNTIF(B$603:B$725,L7)=0,0,1) -> 0 | Y7: =IF(COUNTIF(B$725:B$844,L7)=0,0,1) -> 0 | Z7: =IF(COUNTIF(B$845:B$969,L7)=0,0,1) -> 0 | AA7: 0.5 | AB7: =IFERROR(__xludf.DUMMYFUNCTION("IFERROR(IF(Match(L7,IMPORTRANGE(""https://docs.google.com/spreadsheets/d/1n1sT_Q_W3mKmn2Yrd8qcNzuRD4zr4DB9gqARnjQ30B4/edit?gid=1918970062#gid=1918970062"",""Form Responses 1!B2:B49""),0),1), 0)"),0.0) -> 0 | AC7: =IF(COUNTIF(B$1145:B$1305,L7)=0,0,1) -> 1 | AD7: 0 | AE7: =IFERROR(__xludf.DUMMYFUNCTION("IFERROR(IF(Match(L7,IMPORTRANGE(""https://docs.google.com/spreadsheets/d/1hvckjcCpxEuDQDPrBMml_I1kBhYyjrgR8qBKC9QGVUc/edit?resourcekey=&gid=230793720#gid=230793720"",""Form Responses 1!B2:B199""),0),1), 0)"),0.0) -> 0 | AF7: =IFERROR(__xludf.DUMMYFUNCTION("IFERROR(IF(Match(L7,IMPORTRANGE(""https://docs.google.com/spreadsheets/d/1UY0hI2S83Fmafa5P-C1LM9yqe4v4qIKTnVy_CzLzRPs/edit?resourcekey=&gid=1583835601#gid=1583835601"",""Form Responses 1!B2:B194""),0),1), 0)"),0.0) -> 0 | AG7: =IFERROR(__xludf.DUMMYFUNCTION("IFERROR(IF(Match(L7,IMPORTRANGE(""https://docs.google.com/spreadsheets/d/1hO4mQ22n6cudUygJ2ss_JeJdm2Ua_7hJl_79lWWEtic/edit?resourcekey=&gid=2087212010#gid=2087212010"",""Form Responses 1!B2:B104""),0),1), 0)"),0.0) -> 0 | AH7: 0.5
A8: 45917.647 | B8: marisol.chou@warriorlife.net | C8: Marisol | D8: Chou | E8: G109 | F8: Novice (1st year or 2nd years who haven't placed top 10 (SCDC) or top 3 (SVCDC)) | G8: Riday Appannagari | H8: pick nice colors for the design! | K8: Paul Shi | L8: yunbo.shi@warriorlife.net | M8: Alicia Tang | N8: N | O8: 2nd Year | P8: 2 | Q8: ESB | R8: =IF(COUNTIF(B$2:B$149,L8)=0,0,1) -> 0 | S8: =IF(COUNTIF(B$150:B$274,L8)=0,0,1) -> 1 | T8: =IF(COUNTIF(B$275:B$401,L8)=0,0,1) -> 1 | U8: =IFERROR(__xludf.DUMMYFUNCTION("IFERROR(IF(Match(L8,IMPORTRANGE(""https://docs.google.com/spreadsheets/d/1CAXKDiOnZb21bZOY_nacH9xI9AiD-nH8ZZQAwYKkVC0/edit?usp=drivesdk"",""Completed Exams!A1:A135""),0),1), 0)"),0.0) -> 0 | V8: =IF(COUNTIF(B$416:B$535,L8)=0,0,1) -> 1 | W8: =IF(COUNTIF(B$535:B$602,L8)=0,0,1) -> 1 | X8: =IF(COUNTIF(B$603:B$725,L8)=0,0,1) -> 1 | Y8: =IF(COUNTIF(B$725:B$844,L8)=0,0,1) -> 1 | Z8: =IF(COUNTIF(B$845:B$969,L8)=0,0,1) -> 1 | AA8: =IF(COUNTIF(B$971:B$1124,L8)=0,0,1) -> 1 | AB8: =IFERROR(__xludf.DUMMYFUNCTION("IFERROR(IF(Match(L8,IMPORTRANGE(""https://docs.google.com/spreadsheets/d/1n1sT_Q_W3mKmn2Yrd8qcNzuRD4zr4DB9gqARnjQ30B4/edit?gid=1918970062#gid=1918970062"",""Form Responses 1!B2:B49""),0),1), 0)"),0.0) -> 0 | AC8: =IF(COUNTIF(B$1145:B$1305,L8)=0,0,1) -> 1 | AD8: 1 | AE8: 0.5 | AF8: =IFERROR(__xludf.DUMMYFUNCTION("IFERROR(IF(Match(L8,IMPORTRANGE(""https://docs.google.com/spreadsheets/d/1UY0hI2S83Fmafa5P-C1LM9yqe4v4qIKTnVy_CzLzRPs/edit?resourcekey=&gid=1583835601#gid=1583835601"",""Form Responses 1!B2:B194""),0),1), 0)"),0.0) -> 0 | AG8: =IFERROR(__xludf.DUMMYFUNCTION("IFERROR(IF(Match(L8,IMPORTRANGE(""https://docs.google.com/spreadsheets/d/1hO4mQ22n6cudUygJ2ss_JeJdm2Ua_7hJl_79lWWEtic/edit?resourcekey=&gid=2087212010#gid=2087212010"",""Form Responses 1!B2:B104""),0),1), 0)"),0.0) -> 0 | AH8: =IFERROR(__xludf.DUMMYFUNCTION("IFERROR(IF(Match(L8,IMPORTRANGE(""https://docs.google.com/spreadsheets/d/1HbfCXhSXbtTODKKY1MOFwJccyhgDKD0J9sO1k5l_6lM/edit?resourcekey=&gid=1616384832#gid=1616384832"",""Form Responses 1!E2:E143""),0),1), 0)"),0.0) -> 0
A9: 45917.647 | B9: zayd.bashadi@warriorlife.net | C9: Zayd | D9: Bashadi | E9: G130 | F9: Novice (1st year or 2nd years who haven't placed top 10 (SCDC) or top 3 (SVCDC)) | G9: Jayden | H9: Templets are good | K9: Sofia Yiu | L9: sofia.yiu@warriorlife.net | M9: Alicia Tang | N9: N | O9: 1st Year | P9: 2 | Q9: SEOR | R9: =IF(COUNTIF(B$2:B$149,L9)=0,0,1) -> 1 | S9: =IF(COUNTIF(B$150:B$274,L9)=0,0,1) -> 1 | T9: =IF(COUNTIF(B$275:B$401,L9)=0,0,1) -> 1 | U9: =IFERROR(__xludf.DUMMYFUNCTION("IFERROR(IF(Match(L9,IMPORTRANGE(""https://docs.google.com/spreadsheets/d/1CAXKDiOnZb21bZOY_nacH9xI9AiD-nH8ZZQAwYKkVC0/edit?usp=drivesdk"",""Completed Exams!A1:A135""),0),1), 0)"),0.0) -> 0 | V9: =IF(COUNTIF(B$416:B$535,L9)=0,0,1) -> 1 | W9: 0.5 | X9: =IF(COUNTIF(B$603:B$725,L9)=0,0,1) -> 1 | Y9: =IF(COUNTIF(B$725:B$844,L9)=0,0,1) -> 1 | Z9: =IF(COUNTIF(B$845:B$969,L9)=0,0,1) -> 1 | AA9: =IF(COUNTIF(B$971:B$1124,L9)=0,0,1) -> 1 | AB9: 1 | AC9: =IF(COUNTIF(B$1145:B$1305,L9)=0,0,1) -> 1 | AD9: 1 | AE9: =IFERROR(__xludf.DUMMYFUNCTION("IFERROR(IF(Match(L9,IMPORTRANGE(""https://docs.google.com/spreadsheets/d/1hvckjcCpxEuDQDPrBMml_I1kBhYyjrgR8qBKC9QGVUc/edit?resourcekey=&gid=230793720#gid=230793720"",""Form Responses 1!B2:B199""),0),1), 0)"),0.0) -> 0 | AF9: =IFERROR(__xludf.DUMMYFUNCTION("IFERROR(IF(Match(L9,IMPORTRANGE(""https://docs.google.com/spreadsheets/d/1UY0hI2S83Fmafa5P-C1LM9yqe4v4qIKTnVy_CzLzRPs/edit?resourcekey=&gid=1583835601#gid=1583835601"",""Form Responses 1!B2:B194""),0),1), 0)"),0.0) -> 0 | AG9: =IFERROR(__xludf.DUMMYFUNCTION("IFERROR(IF(Match(L9,IMPORTRANGE(""https://docs.google.com/spreadsheets/d/1hO4mQ22n6cudUygJ2ss_JeJdm2Ua_7hJl_79lWWEtic/edit?resourcekey=&gid=2087212010#gid=2087212010"",""Form Responses 1!B2:B104""),0),1), 0)"),0.0) -> 0 | AH9: =IFERROR(__xludf.DUMMYFUNCTION("IFERROR(IF(Match(L9,IMPORTRANGE(""https://docs.google.com/spreadsheets/d/1HbfCXhSXbtTODKKY1MOFwJccyhgDKD0J9sO1k5l_6lM/edit?resourcekey=&gid=1616384832#gid=1616384832"",""Form Responses 1!E2:E143""),0),1), 0)"),0.0) -> 0
A10: 45917.647 | B10: tiara.wang@warriorlife.net | C10: Tiara | D10: Wang | E10: G130 | F10: Experienced (2nd years who have placed top 10 (SCDC) or top 3 (SVCDC) or 3rd and 4th years) | G10: Suneri | H10: I learned about the whiteboard option on canva | K10: Sunny Wang | L10: ziqing.wang@warriorlife.net | M10: Alicia Tang | N10: N | O10: 1st Year | P10: 2 | Q10: SEOR | R10: =IF(COUNTIF(B$2:B$149,L10)=0,0,1) -> 1 | S10: =IF(COUNTIF(B$150:B$274,L10)=0,0,1) -> 1 | T10: =IF(COUNTIF(B$275:B$401,L10)=0,0,1) -> 1 | U10: =IFERROR(__xludf.DUMMYFUNCTION("IFERROR(IF(Match(L10,IMPORTRANGE(""https://docs.google.com/spreadsheets/d/1CAXKDiOnZb21bZOY_nacH9xI9AiD-nH8ZZQAwYKkVC0/edit?usp=drivesdk"",""Completed Exams!A1:A135""),0),1), 0)"),0.0) -> 0 | V10: =IF(COUNTIF(B$416:B$535,L10)=0,0,1) -> 1 | W10: 0.5 | X10: =IF(COUNTIF(B$603:B$725,L10)=0,0,1) -> 1 | Y10: =IF(COUNTIF(B$725:B$844,L10)=0,0,1) -> 1 | Z10: =IF(COUNTIF(B$845:B$969,L10)=0,0,1) -> 1 | AA10: =IF(COUNTIF(B$971:B$1124,L10)=0,0,1) -> 1 | AB10: =IFERROR(__xludf.DUMMYFUNCTION("IFERROR(IF(Match(L10,IMPORTRANGE(""https://docs.google.com/spreadsheets/d/1n1sT_Q_W3mKmn2Yrd8qcNzuRD4zr4DB9gqARnjQ30B4/edit?gid=1918970062#gid=1918970062"",""Form Responses 1!B2:B49""),0),1), 0)"),0.0) -> 0 | AC10: =IF(COUNTIF(B$1145:B$1305,L10)=0,0,1) -> 1 | AD10: 1 | AE10: =IFERROR(__xludf.DUMMYFUNCTION("IFERROR(IF(Match(L10,IMPORTRANGE(""https://docs.google.com/spreadsheets/d/1hvckjcCpxEuDQDPrBMml_I1kBhYyjrgR8qBKC9QGVUc/edit?resourcekey=&gid=230793720#gid=230793720"",""Form Responses 1!B2:B199""),0),1), 0)"),0.0) -> 0 | AF10: =IFERROR(__xludf.DUMMYFUNCTION("IFERROR(IF(Match(L10,IMPORTRANGE(""https://docs.google.com/spreadsheets/d/1UY0hI2S83Fmafa5P-C1LM9yqe4v4qIKTnVy_CzLzRPs/edit?resourcekey=&gid=1583835601#gid=1583835601"",""Form Responses 1!B2:B194""),0),1), 0)"),0.0) -> 0 | AG10: =IFERROR(__xludf.DUMMYFUNCTION("IFERROR(IF(Match(L10,IMPORTRANGE(""https://docs.google.com/spreadsheets/d/1hO4mQ22n6cudUygJ2ss_JeJdm2Ua_7hJl_79lWWEtic/edit?resourcekey=&gid=2087212010#gid=2087212010"",""Form Responses 1!B2:B104""),0),1), 0)"),0.0) -> 0 | AH10: =IFERROR(__xludf.DUMMYFUNCTION("IFERROR(IF(Match(L10,IMPORTRANGE(""https://docs.google.com/spreadsheets/d/1HbfCXhSXbtTODKKY1MOFwJccyhgDKD0J9sO1k5l_6lM/edit?resourcekey=&gid=1616384832#gid=1616384832"",""Form Responses 1!E2:E143""),0),1), 0)"),0.0) -> 0
A11: 45917.647 | B11: christine.choo@warriorlife.net | C11: Christine | D11: Choo | E11: G130 | F11: Novice (1st year or 2nd years who haven't placed top 10 (SCDC) or top 3 (SVCDC)) | G11: Riday | H11: Canva whiteboard is really useful for planning. | K11: Arkopriya Aich | L11: arkopriya.aich@warriorlife.net | M11: Alicia Tang | N11: N | O11: 2nd Year | P11: 2 | Q11: PSE | R11: 0.5 | S11: 0.5 | T11: =IF(COUNTIF(B$275:B$401,L11)=0,0,1) -> 1 | U11: =IFERROR(__xludf.DUMMYFUNCTION("IFERROR(IF(Match(L11,IMPORTRANGE(""https://docs.google.com/spreadsheets/d/1CAXKDiOnZb21bZOY_nacH9xI9AiD-nH8ZZQAwYKkVC0/edit?usp=drivesdk"",""Completed Exams!A1:A135""),0),1), 0)"),0.0) -> 0 | V11: =IF(COUNTIF(B$416:B$535,L11)=0,0,1) -> 1 | W11: =IF(COUNTIF(B$535:B$602,L11)=0,0,1) -> 0 | X11: =IF(COUNTIF(B$603:B$725,L11)=0,0,1) -> 1 | Y11: =IF(COUNTIF(B$725:B$844,L11)=0,0,1) -> 1 | Z11: =IF(COUNTIF(B$845:B$969,L11)=0,0,1) -> 1 | AA11: =IF(COUNTIF(B$971:B$1124,L11)=0,0,1) -> 1 | AB11: =IFERROR(__xludf.DUMMYFUNCTION("IFERROR(IF(Match(L11,IMPORTRANGE(""https://docs.google.com/spreadsheets/d/1n1sT_Q_W3mKmn2Yrd8qcNzuRD4zr4DB9gqARnjQ30B4/edit?gid=1918970062#gid=1918970062"",""Form Responses 1!B2:B49""),0),1), 0)"),0.0) -> 0 | AC11: =IF(COUNTIF(B$1145:B$1305,L11)=0,0,1) -> 1 | AD11: 0.5 | AE11: =IFERROR(__xludf.DUMMYFUNCTION("IFERROR(IF(Match(L11,IMPORTRANGE(""https://docs.google.com/spreadsheets/d/1hvckjcCpxEuDQDPrBMml_I1kBhYyjrgR8qBKC9QGVUc/edit?resourcekey=&gid=230793720#gid=230793720"",""Form Responses 1!B2:B199""),0),1), 0)"),0.0) -> 0 | AF11: =IFERROR(__xludf.DUMMYFUNCTION("IFERROR(IF(Match(L11,IMPORTRANGE(""https://docs.google.com/spreadsheets/d/1UY0hI2S83Fmafa5P-C1LM9yqe4v4qIKTnVy_CzLzRPs/edit?resourcekey=&gid=1583835601#gid=1583835601"",""Form Responses 1!B2:B194""),0),1), 0)"),0.0) -> 0 | AG11: =IFERROR(__xludf.DUMMYFUNCTION("IFERROR(IF(Match(L11,IMPORTRANGE(""https://docs.google.com/spreadsheets/d/1hO4mQ22n6cudUygJ2ss_JeJdm2Ua_7hJl_79lWWEtic/edit?resourcekey=&gid=2087212010#gid=2087212010"",""Form Responses 1!B2:B104""),0),1), 0)"),0.0) -> 0 | AH11: =IFERROR(__xludf.DUMMYFUNCTION("IFERROR(IF(Match(L11,IMPORTRANGE(""https://docs.google.com/spreadsheets/d/1HbfCXhSXbtTODKKY1MOFwJccyhgDKD0J9sO1k5l_6lM/edit?resourcekey=&gid=1616384832#gid=1616384832"",""Form Responses 1!E2:E143""),0),1), 0)"),0.0) -> 0
A12: 45917.647 | B12: lincolnjacob.tran@warriorlife.net | C12: Lincoln | D12: Tran | E12: G130 | F12: Novice (1st year or 2nd years who haven't placed top 10 (SCDC) or top 3 (SVCDC)) | G12: Xiaowei Zhang | H12: I learned to use the whiteboard on canva to see how we can scale our franchise business plan | K12: Cherrilyn Huynh | L12: t.huynh@warriorlife.net | M12: Arissa Cao | N12: N | O12: 2nd Year | P12: 3 | Q12: BMOR | R12: =IF(COUNTIF(B$2:B$149,L12)=0,0,1) -> 1 | S12: =IF(COUNTIF(B$150:B$274,L12)=0,0,1) -> 1 | T12: =IF(COUNTIF(B$275:B$401,L12)=0,0,1) -> 1 | U12: =IFERROR(__xludf.DUMMYFUNCTION("IFERROR(IF(Match(L12,IMPORTRANGE(""https://docs.google.com/spreadsheets/d/1CAXKDiOnZb21bZOY_nacH9xI9AiD-nH8ZZQAwYKkVC0/edit?usp=drivesdk"",""Completed Exams!A1:A135""),0),1), 0)"),0.0) -> 0 | V12: =IF(COUNTIF(B$416:B$535,L12)=0,0,1) -> 0 | W12: =IF(COUNTIF(B$535:B$602,L12)=0,0,1) -> 1 | X12: =IF(COUNTIF(B$603:B$725,L12)=0,0,1) -> 0 | Y12: =IF(COUNTIF(B$725:B$844,L12)=0,0,1) -> 0 | Z12: =IF(COUNTIF(B$845:B$969,L12)=0,0,1) -> 0 | AA12: =IF(COUNTIF(B$971:B$1124,L12)=0,0,1) -> 0 | AB12: =IFERROR(__xludf.DUMMYFUNCTION("IFERROR(IF(Match(L12,IMPORTRANGE(""https://docs.google.com/spreadsheets/d/1n1sT_Q_W3mKmn2Yrd8qcNzuRD4zr4DB9gqARnjQ30B4/edit?gid=1918970062#gid=1918970062"",""Form Responses 1!B2:B49""),0),1), 0)"),0.0) -> 0 | AC12: =IF(COUNTIF(B$1145:B$1305,L12)=0,0,1) -> 0 | AD12: 0 | AE12: =IFERROR(__xludf.DUMMYFUNCTION("IFERROR(IF(Match(L12,IMPORTRANGE(""https://docs.google.com/spreadsheets/d/1hvckjcCpxEuDQDPrBMml_I1kBhYyjrgR8qBKC9QGVUc/edit?resourcekey=&gid=230793720#gid=230793720"",""Form Responses 1!B2:B199""),0),1), 0)"),0.0) -> 0 | AF12: =IFERROR(__xludf.DUMMYFUNCTION("IFERROR(IF(Match(L12,IMPORTRANGE(""https://docs.google.com/spreadsheets/d/1UY0hI2S83Fmafa5P-C1LM9yqe4v4qIKTnVy_CzLzRPs/edit?resourcekey=&gid=1583835601#gid=1583835601"",""Form Responses 1!B2:B194""),0),1), 0)"),0.0) -> 0 | AG12: =IFERROR(__xludf.DUMMYFUNCTION("IFERROR(IF(Match(L12,IMPORTRANGE(""https://docs.google.com/spreadsheets/d/1hO4mQ22n6cudUygJ2ss_JeJdm2Ua_7hJl_79lWWEtic/edit?resourcekey=&gid=2087212010#gid=2087212010"",""Form Responses 1!B2:B104""),0),1), 0)"),0.0) -> 0 | AH12: =IFERROR(__xludf.DUMMYFUNCTION("IFERROR(IF(Match(L12,IMPORTRANGE(""https://docs.google.com/spreadsheets/d/1HbfCXhSXbtTODKKY1MOFwJccyhgDKD0J9sO1k5l_6lM/edit?resourcekey=&gid=1616384832#gid=1616384832"",""Form Responses 1!E2:E143""),0),1), 0)"),0.0) -> 0
A13: 45917.647 | B13: haochien.wang@warriorlife.net | C13: hao-chien | D13: wang | E13: G130 | F13: Novice (1st year or 2nd years who haven't placed top 10 (SCDC) or top 3 (SVCDC)) | G13: xiaowei zhang | H13: we learned about writttens and see how we can scale our franchise plan. | K13: Madi Nguyen | L13: ct.nguyen@warriorlife.net | M13: Arissa Cao | N13: N | O13: 1st Year | P13: 3 | Q13: BMOR | R13: =IF(COUNTIF(B$2:B$149,L13)=0,0,1) -> 1 | S13: =IF(COUNTIF(B$150:B$274,L13)=0,0,1) -> 1 | T13: =IF(COUNTIF(B$275:B$401,L13)=0,0,1) -> 1 | U13: =IFERROR(__xludf.DUMMYFUNCTION("IFERROR(IF(Match(L13,IMPORTRANGE(""https://docs.google.com/spreadsheets/d/1CAXKDiOnZb21bZOY_nacH9xI9AiD-nH8ZZQAwYKkVC0/edit?usp=drivesdk"",""Completed Exams!A1:A135""),0),1), 0)"),0.0) -> 0 | V13: =IF(COUNTIF(B$416:B$535,L13)=0,0,1) -> 0 | W13: =IF(COUNTIF(B$535:B$602,L13)=0,0,1) -> 1 | X13: =IF(COUNTIF(B$603:B$725,L13)=0,0,1) -> 1 | Y13: =IF(COUNTIF(B$725:B$844,L13)=0,0,1) -> 1 | Z13: =IF(COUNTIF(B$845:B$969,L13)=0,0,1) -> 1 | AA13: =IF(COUNTIF(B$971:B$1124,L13)=0,0,1) -> 1 | AB13: =IFERROR(__xludf.DUMMYFUNCTION("IFERROR(IF(Match(L13,IMPORTRANGE(""https://docs.google.com/spreadsheets/d/1n1sT_Q_W3mKmn2Yrd8qcNzuRD4zr4DB9gqARnjQ30B4/edit?gid=1918970062#gid=1918970062"",""Form Responses 1!B2:B49""),0),1), 0)"),0.0) -> 0 | AC13: =IF(COUNTIF(B$1145:B$1305,L13)=0,0,1) -> 1 | AD13: 0 | AE13: =IFERROR(__xludf.DUMMYFUNCTION("IFERROR(IF(Match(L13,IMPORTRANGE(""https://docs.google.com/spreadsheets/d/1hvckjcCpxEuDQDPrBMml_I1kBhYyjrgR8qBKC9QGVUc/edit?resourcekey=&gid=230793720#gid=230793720"",""Form Responses 1!B2:B199""),0),1), 0)"),0.0) -> 0 | AF13: =IFERROR(__xludf.DUMMYFUNCTION("IFERROR(IF(Match(L13,IMPORTRANGE(""https://docs.google.com/spreadsheets/d/1UY0hI2S83Fmafa5P-C1LM9yqe4v4qIKTnVy_CzLzRPs/edit?resourcekey=&gid=1583835601#gid=1583835601"",""Form Responses 1!B2:B194""),0),1), 0)"),0.0) -> 0 | AG13: 0.5 | AH13: 0.5
A14: 45917.647 | B14: viraaj.vatte@warriorlife.net | C14: Viraaj | D14: Vatte | E14: G130 | F14: Novice (1st year or 2nd years who haven't placed top 10 (SCDC) or top 3 (SVCDC)) | G14: Vivian | H14: we learned about writtens and how to make our slides better | K14: Keshav Satagopan | L14: sk.satagopan@warriorlife.net | M14: Arissa Cao | N14: E | O14: 2nd Year | P14: 3 | Q14: BMOR | R14: =IF(COUNTIF(B$2:B$149,L14)=0,0,1) -> 0 | S14: =IF(COUNTIF(B$150:B$274,L14)=0,0,1) -> 0 | T14: =IF(COUNTIF(B$275:B$401,L14)=0,0,1) -> 1 | U14: =IFERROR(__xludf.DUMMYFUNCTION("IFERROR(IF(Match(L14,IMPORTRANGE(""https://docs.google.com/spreadsheets/d/1CAXKDiOnZb21bZOY_nacH9xI9AiD-nH8ZZQAwYKkVC0/edit?usp=drivesdk"",""Completed Exams!A1:A135""),0),1), 0)"),0.0) -> 0 | V14: =IF(COUNTIF(B$416:B$535,L14)=0,0,1) -> 0 | W14: =IF(COUNTIF(B$535:B$602,L14)=0,0,1) -> 1 | X14: =IF(COUNTIF(B$603:B$725,L14)=0,0,1) -> 0 | Y14: =IF(COUNTIF(B$725:B$844,L14)=0,0,1) -> 0 | Z14: =IF(COUNTIF(B$845:B$969,L14)=0,0,1) -> 1 | AA14: 0.5 | AB14: =IFERROR(__xludf.DUMMYFUNCTION("IFERROR(IF(Match(L14,IMPORTRANGE(""https://docs.google.com/spreadsheets/d/1n1sT_Q_W3mKmn2Yrd8qcNzuRD4zr4DB9gqARnjQ30B4/edit?gid=1918970062#gid=1918970062"",""Form Responses 1!B2:B49""),0),1), 0)"),0.0) -> 0 | AC14: =IF(COUNTIF(B$1145:B$1305,L14)=0,0,1) -> 1 | AD14: 0 | AE14: =IFERROR(__xludf.DUMMYFUNCTION("IFERROR(IF(Match(L14,IMPORTRANGE(""https://docs.google.com/spreadsheets/d/1hvckjcCpxEuDQDPrBMml_I1kBhYyjrgR8qBKC9QGVUc/edit?resourcekey=&gid=230793720#gid=230793720"",""Form Responses 1!B2:B199""),0),1), 0)"),0.0) -> 0 | AF14: =IFERROR(__xludf.DUMMYFUNCTION("IFERROR(IF(Match(L14,IMPORTRANGE(""https://docs.google.com/spreadsheets/d/1UY0hI2S83Fmafa5P-C1LM9yqe4v4qIKTnVy_CzLzRPs/edit?resourcekey=&gid=1583835601#gid=1583835601"",""Form Responses 1!B2:B194""),0),1), 0)"),0.0) -> 0 | AG14: =IFERROR(__xludf.DUMMYFUNCTION("IFERROR(IF(Match(L14,IMPORTRANGE(""https://docs.google.com/spreadsheets/d/1hO4mQ22n6cudUygJ2ss_JeJdm2Ua_7hJl_79lWWEtic/edit?resourcekey=&gid=2087212010#gid=2087212010"",""Form Responses 1!B2:B104""),0),1), 0)"),0.0) -> 0 | AH14: =IFERROR(__xludf.DUMMYFUNCTION("IFERROR(IF(Match(L14,IMPORTRANGE(""https://docs.google.com/spreadsheets/d/1HbfCXhSXbtTODKKY1MOFwJccyhgDKD0J9sO1k5l_6lM/edit?resourcekey=&gid=1616384832#gid=1616384832"",""Form Responses 1!E2:E143""),0),1), 0)"),0.0) -> 0
A15: 45917.647 | B15: aman.kochar@warriorlife.net | C15: Aman | D15: Kochar | E15: G130 | F15: Novice (1st year or 2nd years who haven't placed top 10 (SCDC) or top 3 (SVCDC)) | G15: Revathi | H15: i learned that when making slides you should not use many icons. | K15: Jaden Park | L15: Jaden.park@warriorlife.net | M15: Arissa Cao | N15: E | O15: 3rd Year | P15: 3 | Q15: BMOR | R15: =IF(COUNTIF(B$2:B$149,L15)=0,0,1) -> 0 | S15: =IF(COUNTIF(B$150:B$274,L15)=0,0,1) -> 0 | T15: =IF(COUNTIF(B$275:B$401,L15)=0,0,1) -> 1 | U15: =IFERROR(__xludf.DUMMYFUNCTION("IFERROR(IF(Match(L15,IMPORTRANGE(""https://docs.google.com/spreadsheets/d/1CAXKDiOnZb21bZOY_nacH9xI9AiD-nH8ZZQAwYKkVC0/edit?usp=drivesdk"",""Completed Exams!A1:A135""),0),1), 0)"),0.0) -> 0 | V15: =IF(COUNTIF(B$416:B$535,L15)=0,0,1) -> 0 | W15: =IF(COUNTIF(B$535:B$602,L15)=0,0,1) -> 0 | X15: =IF(COUNTIF(B$603:B$725,L15)=0,0,1) -> 1 | Y15: =IF(COUNTIF(B$725:B$844,L15)=0,0,1) -> 0 | Z15: =IF(COUNTIF(B$845:B$969,L15)=0,0,1) -> 0 | AA15: =IF(COUNTIF(B$971:B$1124,L15)=0,0,1) -> 1 | AB15: =IFERROR(__xludf.DUMMYFUNCTION("IFERROR(IF(Match(L15,IMPORTRANGE(""https://docs.google.com/spreadsheets/d/1n1sT_Q_W3mKmn2Yrd8qcNzuRD4zr4DB9gqARnjQ30B4/edit?gid=1918970062#gid=1918970062"",""Form Responses 1!B2:B49""),0),1), 0)"),0.0) -> 0 | AC15: =IF(COUNTIF(B$1145:B$1305,L15)=0,0,1) -> 1 | AD15: 0 | AE15: =IFERROR(__xludf.DUMMYFUNCTION("IFERROR(IF(Match(L15,IMPORTRANGE(""https://docs.google.com/spreadsheets/d/1hvckjcCpxEuDQDPrBMml_I1kBhYyjrgR8qBKC9QGVUc/edit?resourcekey=&gid=230793720#gid=230793720"",""Form Responses 1!B2:B199""),0),1), 0)"),0.0) -> 0 | AF15: =IFERROR(__xludf.DUMMYFUNCTION("IFERROR(IF(Match(L15,IMPORTRANGE(""https://docs.google.com/spreadsheets/d/1UY0hI2S83Fmafa5P-C1LM9yqe4v4qIKTnVy_CzLzRPs/edit?resourcekey=&gid=1583835601#gid=1583835601"",""Form Responses 1!B2:B194""),0),1), 0)"),0.0) -> 0 | AG15: =IFERROR(__xludf.DUMMYFUNCTION("IFERROR(IF(Match(L15,IMPORTRANGE(""https://docs.google.com/spreadsheets/d/1hO4mQ22n6cudUygJ2ss_JeJdm2Ua_7hJl_79lWWEtic/edit?resourcekey=&gid=2087212010#gid=2087212010"",""Form Responses 1!B2:B104""),0),1), 0)"),0.0) -> 0 | AH15: =IFERROR(__xludf.DUMMYFUNCTION("IFERROR(IF(Match(L15,IMPORTRANGE(""https://docs.google.com/spreadsheets/d/1HbfCXhSXbtTODKKY1MOFwJccyhgDKD0J9sO1k5l_6lM/edit?resourcekey=&gid=1616384832#gid=1616384832"",""Form Responses 1!E2:E143""),0),1), 0)"),0.0) -> 0
A16: 45917.648 | B16: avaneesh.nangare@warriorlife.net | C16: Avaneesh | D16: Nangare | E16: G130 | F16: Experienced (2nd years who have placed top 10 (SCDC) or top 3 (SVCDC) or 3rd and 4th years) | G16: Rochelle(wrong event) | H16: I learned how to brainstorm canva and more | K16: Sradha Namala | L16: sradha.namala@warriorlife.net | M16: Arissa Cao | N16: N | O16: 1st Year | P16: 3 | Q16: BMOR | R16: =IF(COUNTIF(B$2:B$149,L16)=0,0,1) -> 1 | S16: =IF(COUNTIF(B$150:B$274,L16)=0,0,1) -> 1 | T16: =IF(COUNTIF(B$275:B$401,L16)=0,0,1) -> 0 | U16: =IFERROR(__xludf.DUMMYFUNCTION("IFERROR(IF(Match(L16,IMPORTRANGE(""https://docs.google.com/spreadsheets/d/1CAXKDiOnZb21bZOY_nacH9xI9AiD-nH8ZZQAwYKkVC0/edit?usp=drivesdk"",""Completed Exams!A1:A135""),0),1), 0)"),0.0) -> 0 | V16: =IF(COUNTIF(B$416:B$535,L16)=0,0,1) -> 0 | W16: =IF(COUNTIF(B$535:B$602,L16)=0,0,1) -> 1 | X16: =IF(COUNTIF(B$603:B$725,L16)=0,0,1) -> 1 | Y16: =IF(COUNTIF(B$725:B$844,L16)=0,0,1) -> 1 | Z16: =IF(COUNTIF(B$845:B$969,L16)=0,0,1) -> 1 | AA16: =IF(COUNTIF(B$971:B$1124,L16)=0,0,1) -> 1 | AB16: =IFERROR(__xludf.DUMMYFUNCTION("IFERROR(IF(Match(L16,IMPORTRANGE(""https://docs.google.com/spreadsheets/d/1n1sT_Q_W3mKmn2Yrd8qcNzuRD4zr4DB9gqARnjQ30B4/edit?gid=1918970062#gid=1918970062"",""Form Responses 1!B2:B49""),0),1), 0)"),0.0) -> 0 | AC16: =IF(COUNTIF(B$1145:B$1305,L16)=0,0,1) -> 1 | AD16: 0 | AE16: =IFERROR(__xludf.DUMMYFUNCTION("IFERROR(IF(Match(L16,IMPORTRANGE(""https://docs.google.com/spreadsheets/d/1hvckjcCpxEuDQDPrBMml_I1kBhYyjrgR8qBKC9QGVUc/edit?resourcekey=&gid=230793720#gid=230793720"",""Form Responses 1!B2:B199""),0),1), 0)"),0.0) -> 0 | AF16: 0.5 | AG16: 0.5 | AH16: =IFERROR(__xludf.DUMMYFUNCTION("IFERROR(IF(Match(L16,IMPORTRANGE(""https://docs.google.com/spreadsheets/d/1HbfCXhSXbtTODKKY1MOFwJccyhgDKD0J9sO1k5l_6lM/edit?resourcekey=&gid=1616384832#gid=1616384832"",""Form Responses 1!E2:E143""),0),1), 0)"),0.0) -> 0
A17: 45917.648 | B17: aditya.poduri@warriorlife.net | C17: Aditya | D17: Poduri | E17: G130 | F17: Novice (1st year or 2nd years who haven't placed top 10 (SCDC) or top 3 (SVCDC)) | G17: Elaine Wang | H17: Do not add too many icons when making your presentation, that can end up becoming redundant and repetitive. | K17: Franklin Dao | L17: franklin.dao@warriorlife.net | M17: Ayden Wang | N17: E | O17: 3rd Year | P17: 4 | Q17: HTOR | R17: =IF(COUNTIF(B$2:B$149,L17)=0,0,1) -> 1 | S17: =IF(COUNTIF(B$150:B$274,L17)=0,0,1) -> 0 | T17: =IF(COUNTIF(B$275:B$401,L17)=0,0,1) -> 0 | U17: =IFERROR(__xludf.DUMMYFUNCTION("IFERROR(IF(Match(L17,IMPORTRANGE(""https://docs.google.com/spreadsheets/d/1CAXKDiOnZb21bZOY_nacH9xI9AiD-nH8ZZQAwYKkVC0/edit?usp=drivesdk"",""Completed Exams!A1:A135""),0),1), 0)"),0.0) -> 0 | V17: =IF(COUNTIF(B$416:B$535,L17)=0,0,1) -> 0 | W17: =IF(COUNTIF(B$535:B$602,L17)=0,0,1) -> 0 | X17: =IF(COUNTIF(B$603:B$725,L17)=0,0,1) -> 1 | Y17: =IF(COUNTIF(B$725:B$844,L17)=0,0,1) -> 0 | Z17: =IF(COUNTIF(B$845:B$969,L17)=0,0,1) -> 0 | AA17: =IF(COUNTIF(B$971:B$1124,L17)=0,0,1) -> 1 | AB17: =IFERROR(__xludf.DUMMYFUNCTION("IFERROR(IF(Match(L17,IMPORTRANGE(""https://docs.google.com/spreadsheets/d/1n1sT_Q_W3mKmn2Yrd8qcNzuRD4zr4DB9gqARnjQ30B4/edit?gid=1918970062#gid=1918970062"",""Form Responses 1!B2:B49""),0),1), 0)"),0.0) -> 0 | AC17: =IF(COUNTIF(B$1145:B$1305,L17)=0,0,1) -> 1 | AD17: 1 | AE17: =IFERROR(__xludf.DUMMYFUNCTION("IFERROR(IF(Match(L17,IMPORTRANGE(""https://docs.google.com/spreadsheets/d/1hvckjcCpxEuDQDPrBMml_I1kBhYyjrgR8qBKC9QGVUc/edit?resourcekey=&gid=230793720#gid=230793720"",""Form Responses 1!B2:B199""),0),1), 0)"),0.0) -> 0 | AF17: =IFERROR(__xludf.DUMMYFUNCTION("IFERROR(IF(Match(L17,IMPORTRANGE(""https://docs.google.com/spreadsheets/d/1UY0hI2S83Fmafa5P-C1LM9yqe4v4qIKTnVy_CzLzRPs/edit?resourcekey=&gid=1583835601#gid=1583835601"",""Form Responses 1!B2:B194""),0),1), 0)"),0.0) -> 0 | AG17: =IFERROR(__xludf.DUMMYFUNCTION("IFERROR(IF(Match(L17,IMPORTRANGE(""https://docs.google.com/spreadsheets/d/1hO4mQ22n6cudUygJ2ss_JeJdm2Ua_7hJl_79lWWEtic/edit?resourcekey=&gid=2087212010#gid=2087212010"",""Form Responses 1!B2:B104""),0),1), 0)"),0.0) -> 0 | AH17: =IFERROR(__xludf.DUMMYFUNCTION("IFERROR(IF(Match(L17,IMPORTRANGE(""https://docs.google.com/spreadsheets/d/1HbfCXhSXbtTODKKY1MOFwJccyhgDKD0J9sO1k5l_6lM/edit?resourcekey=&gid=1616384832#gid=1616384832"",""Form Responses 1!E2:E143""),0),1), 0)"),0.0) -> 0
A18: 45917.648 | B18: sarah.xu@warriorlife.net | C18: Sarah | D18: Xu | E18: G130 | F18: Experienced (2nd years who have placed top 10 (SCDC) or top 3 (SVCDC) or 3rd and 4th years) | G18: Suneri Chinthalapati | H18: Don’t cram too much information on slides, and don’t use too many icons. | K18: Samuel Xiao | L18: samuel.xiao@warriorlife.net | M18: Ayden Wang | N18: E | O18: 3rd Year | P18: 4 | Q18: HTOR | R18: =IF(COUNTIF(B$2:B$149,L18)=0,0,1) -> 1 | S18: =IF(COUNTIF(B$150:B$274,L18)=0,0,1) -> 0 | T18: =IF(COUNTIF(B$275:B$401,L18)=0,0,1) -> 0 | U18: =IFERROR(__xludf.DUMMYFUNCTION("IFERROR(IF(Match(L18,IMPORTRANGE(""https://docs.google.com/spreadsheets/d/1CAXKDiOnZb21bZOY_nacH9xI9AiD-nH8ZZQAwYKkVC0/edit?usp=drivesdk"",""Completed Exams!A1:A135""),0),1), 0)"),0.0) -> 0 | V18: =IF(COUNTIF(B$416:B$535,L18)=0,0,1) -> 0 | W18: =IF(COUNTIF(B$535:B$602,L18)=0,0,1) -> 1 | X18: =IF(COUNTIF(B$603:B$725,L18)=0,0,1) -> 1 | Y18: =IF(COUNTIF(B$725:B$844,L18)=0,0,1) -> 0 | Z18: =IF(COUNTIF(B$845:B$969,L18)=0,0,1) -> 1 | AA18: =IF(COUNTIF(B$971:B$1124,L18)=0,0,1) -> 1 | AB18: 1 | AC18: =IF(COUNTIF(B$1145:B$1305,L18)=0,0,1) -> 1 | AD18: 1 | AE18: =IFERROR(__xludf.DUMMYFUNCTION("IFERROR(IF(Match(L18,IMPORTRANGE(""https://docs.google.com/spreadsheets/d/1hvckjcCpxEuDQDPrBMml_I1kBhYyjrgR8qBKC9QGVUc/edit?resourcekey=&gid=230793720#gid=230793720"",""Form Responses 1!B2:B199""),0),1), 0)"),0.0) -> 0 | AF18: =IFERROR(__xludf.DUMMYFUNCTION("IFERROR(IF(Match(L18,IMPORTRANGE(""https://docs.google.com/spreadsheets/d/1UY0hI2S83Fmafa5P-C1LM9yqe4v4qIKTnVy_CzLzRPs/edit?resourcekey=&gid=1583835601#gid=1583835601"",""Form Responses 1!B2:B194""),0),1), 0)"),0.0) -> 0 | AG18: =IFERROR(__xludf.DUMMYFUNCTION("IFERROR(IF(Match(L18,IMPORTRANGE(""https://docs.google.com/spreadsheets/d/1hO4mQ22n6cudUygJ2ss_JeJdm2Ua_7hJl_79lWWEtic/edit?resourcekey=&gid=2087212010#gid=2087212010"",""Form Responses 1!B2:B104""),0),1), 0)"),0.0) -> 0 | AH18: =IFERROR(__xludf.DUMMYFUNCTION("IFERROR(IF(Match(L18,IMPORTRANGE(""https://docs.google.com/spreadsheets/d/1HbfCXhSXbtTODKKY1MOFwJccyhgDKD0J9sO1k5l_6lM/edit?resourcekey=&gid=1616384832#gid=1616384832"",""Form Responses 1!E2:E143""),0),1), 0)"),0.0) -> 0
A19: 45917.65 | B19: jessica.ma@warriorlife.net | C19: Jessica | D19: Ma | E19: G130 | F19: Novice (1st year or 2nd years who haven't placed top 10 (SCDC) or top 3 (SVCDC)) | G19: Emily Tang | H19: I learned that I have to find a company that is good in all aspects except their social media branding. | K19: Aubrey Santos | L19: aubrey.santos@warriorlife.net | M19: Ayden Wang | N19: N | O19: 1st Year | P19: 4 | Q19: SEOR | R19: =IF(COUNTIF(B$2:B$149,L19)=0,0,1) -> 1 | S19: =IF(COUNTIF(B$150:B$274,L19)=0,0,1) -> 1 | T19: =IF(COUNTIF(B$275:B$401,L19)=0,0,1) -> 1 | U19: =IFERROR(__xludf.DUMMYFUNCTION("IFERROR(IF(Match(L19,IMPORTRANGE(""https://docs.google.com/spreadsheets/d/1CAXKDiOnZb21bZOY_nacH9xI9AiD-nH8ZZQAwYKkVC0/edit?usp=drivesdk"",""Completed Exams!A1:A135""),0),1), 0)"),0.0) -> 0 | V19: =IF(COUNTIF(B$416:B$535,L19)=0,0,1) -> 1 | W19: 1 | X19: =IF(COUNTIF(B$603:B$725,L19)=0,0,1) -> 1 | Y19: 0.5 | Z19: =IF(COUNTIF(B$845:B$969,L19)=0,0,1) -> 1 | AA19: =IF(COUNTIF(B$971:B$1124,L19)=0,0,1) -> 1 | AB19: =IFERROR(__xludf.DUMMYFUNCTION("IFERROR(IF(Match(L19,IMPORTRANGE(""https://docs.google.com/spreadsheets/d/1n1sT_Q_W3mKmn2Yrd8qcNzuRD4zr4DB9gqARnjQ30B4/edit?gid=1918970062#gid=1918970062"",""Form Responses 1!B2:B49""),0),1), 0)"),0.0) -> 0 | AC19: =IF(COUNTIF(B$1145:B$1305,L19)=0,0,1) -> 1 | AD19: 1 | AE19: =IFERROR(__xludf.DUMMYFUNCTION("IFERROR(IF(Match(L19,IMPORTRANGE(""https://docs.google.com/spreadsheets/d/1hvckjcCpxEuDQDPrBMml_I1kBhYyjrgR8qBKC9QGVUc/edit?resourcekey=&gid=230793720#gid=230793720"",""Form Responses 1!B2:B199""),0),1), 0)"),0.0) -> 0 | AF19: =IFERROR(__xludf.DUMMYFUNCTION("IFERROR(IF(Match(L19,IMPORTRANGE(""https://docs.google.com/spreadsheets/d/1UY0hI2S83Fmafa5P-C1LM9yqe4v4qIKTnVy_CzLzRPs/edit?resourcekey=&gid=1583835601#gid=1583835601"",""Form Responses 1!B2:B194""),0),1), 0)"),0.0) -> 0 | AG19: =IFERROR(__xludf.DUMMYFUNCTION("IFERROR(IF(Match(L19,IMPORTRANGE(""https://docs.google.com/spreadsheets/d/1hO4mQ22n6cudUygJ2ss_JeJdm2Ua_7hJl_79lWWEtic/edit?resourcekey=&gid=2087212010#gid=2087212010"",""Form Responses 1!B2:B104""),0),1), 0)"),0.0) -> 0 | AH19: =IFERROR(__xludf.DUMMYFUNCTION("IFERROR(IF(Match(L19,IMPORTRANGE(""https://docs.google.com/spreadsheets/d/1HbfCXhSXbtTODKKY1MOFwJccyhgDKD0J9sO1k5l_6lM/edit?resourcekey=&gid=1616384832#gid=1616384832"",""Form Responses 1!E2:E143""),0),1), 0)"),0.0) -> 0
A20: 45917.661 | B20: aidan.qi@warriorlife.net | C20: Aidan | D20: Qi | E20: G107 | F20: Experienced (2nd years who have placed top 10 (SCDC) or top 3 (SVCDC) or 3rd and 4th years) | G20: Saron | H20: Elaine and Evelyn | K20: Riyana Baldua | L20: riyana.baldua@warriorlife.net | M20: Ayden Wang | N20: N | O20: 2nd Year | P20: 4 | Q20: SEOR | R20: =IF(COUNTIF(B$2:B$149,L20)=0,0,1) -> 1 | S20: =IF(COUNTIF(B$150:B$274,L20)=0,0,1) -> 1 | T20: =IF(COUNTIF(B$275:B$401,L20)=0,0,1) -> 1 | U20: =IFERROR(__xludf.DUMMYFUNCTION("IFERROR(IF(Match(L20,IMPORTRANGE(""https://docs.google.com/spreadsheets/d/1CAXKDiOnZb21bZOY_nacH9xI9AiD-nH8ZZQAwYKkVC0/edit?usp=drivesdk"",""Completed Exams!A1:A135""),0),1), 0)"),0.0) -> 0 | V20: =IF(COUNTIF(B$416:B$535,L20)=0,0,1) -> 1 | W20: 1 | X20: =IF(COUNTIF(B$603:B$725,L20)=0,0,1) -> 1 | Y20: 1 | Z20: =IF(COUNTIF(B$845:B$969,L20)=0,0,1) -> 1 | AA20: =IF(COUNTIF(B$971:B$1124,L20)=0,0,1) -> 1 | AB20: =IFERROR(__xludf.DUMMYFUNCTION("IFERROR(IF(Match(L20,IMPORTRANGE(""https://docs.google.com/spreadsheets/d/1n1sT_Q_W3mKmn2Yrd8qcNzuRD4zr4DB9gqARnjQ30B4/edit?gid=1918970062#gid=1918970062"",""Form Responses 1!B2:B49""),0),1), 0)"),0.0) -> 0 | AC20: =IF(COUNTIF(B$1145:B$1305,L20)=0,0,1) -> 1 | AD20: 1 | AE20: =IFERROR(__xludf.DUMMYFUNCTION("IFERROR(IF(Match(L20,IMPORTRANGE(""https://docs.google.com/spreadsheets/d/1hvckjcCpxEuDQDPrBMml_I1kBhYyjrgR8qBKC9QGVUc/edit?resourcekey=&gid=230793720#gid=230793720"",""Form Responses 1!B2:B199""),0),1), 0)"),0.0) -> 0 | AF20: =IFERROR(__xludf.DUMMYFUNCTION("IFERROR(IF(Match(L20,IMPORTRANGE(""https://docs.google.com/spreadsheets/d/1UY0hI2S83Fmafa5P-C1LM9yqe4v4qIKTnVy_CzLzRPs/edit?resourcekey=&gid=1583835601#gid=1583835601"",""Form Responses 1!B2:B194""),0),1), 0)"),0.0) -> 0 | AG20: =IFERROR(__xludf.DUMMYFUNCTION("IFERROR(IF(Match(L20,IMPORTRANGE(""https://docs.google.com/spreadsheets/d/1hO4mQ22n6cudUygJ2ss_JeJdm2Ua_7hJl_79lWWEtic/edit?resourcekey=&gid=2087212010#gid=2087212010"",""Form Responses 1!B2:B104""),0),1), 0)"),0.0) -> 0 | AH20: 0.5
A21: 45917.662 | B21: jennaly.fangonilo@warriorlife.net | C21: JennaLy | D21: Fangonilo | E21: G107 | F21: Experienced (2nd years who have placed top 10 (SCDC) or top 3 (SVCDC) or 3rd and 4th years) | G21: Lizzy | H21: Elaine and Evelyn | K21: Maahir Satwani | L21: maahir.satwani@warriorlife.net | M21: Ayden Wang | N21: N | O21: 1st Year | P21: 4 | Q21: IMCS | R21: =IF(COUNTIF(B$2:B$149,L21)=0,0,1) -> 1 | S21: =IF(COUNTIF(B$150:B$274,L21)=0,0,1) -> 1 | T21: 0.5 | U21: =IFERROR(__xludf.DUMMYFUNCTION("IFERROR(IF(Match(L21,IMPORTRANGE(""https://docs.google.com/spreadsheets/d/1CAXKDiOnZb21bZOY_nacH9xI9AiD-nH8ZZQAwYKkVC0/edit?usp=drivesdk"",""Completed Exams!A1:A135""),0),1), 0)"),0.0) -> 0 | V21: 0.5 | W21: =IF(COUNTIF(B$535:B$602,L21)=0,0,1) -> 0 | X21: =IF(COUNTIF(B$603:B$725,L21)=0,0,1) -> 1 | Y21: =IF(COUNTIF(B$725:B$844,L21)=0,0,1) -> 1 | Z21: =IF(COUNTIF(B$845:B$969,L21)=0,0,1) -> 1 | AA21: =IF(COUNTIF(B$971:B$1124,L21)=0,0,1) -> 1 | AB21: 1 | AC21: =IF(COUNTIF(B$1145:B$1305,L21)=0,0,1) -> 1 | AD21: 1 | AE21: 0.5 | AF21: =IFERROR(__xludf.DUMMYFUNCTION("IFERROR(IF(Match(L21,IMPORTRANGE(""https://docs.google.com/spreadsheets/d/1UY0hI2S83Fmafa5P-C1LM9yqe4v4qIKTnVy_CzLzRPs/edit?resourcekey=&gid=1583835601#gid=1583835601"",""Form Responses 1!B2:B194""),0),1), 0)"),0.0) -> 0 | AG21: =IFERROR(__xludf.DUMMYFUNCTION("IFERROR(IF(Match(L21,IMPORTRANGE(""https://docs.google.com/spreadsheets/d/1hO4mQ22n6cudUygJ2ss_JeJdm2Ua_7hJl_79lWWEtic/edit?resourcekey=&gid=2087212010#gid=2087212010"",""Form Responses 1!B2:B104""),0),1), 0)"),0.0) -> 0 | AH21: =IFERROR(__xludf.DUMMYFUNCTION("IFERROR(IF(Match(L21,IMPORTRANGE(""https://docs.google.com/spreadsheets/d/1HbfCXhSXbtTODKKY1MOFwJccyhgDKD0J9sO1k5l_6lM/edit?resourcekey=&gid=1616384832#gid=1616384832"",""Form Responses 1!E2:E143""),0),1), 0)"),0.0) -> 0
A22: 45917.662 | B22: john.kirchenbauer@warriorlife.net | C22: John | D22: Kirchenbauer | E22: G107 | F22: Novice (1st year or 2nd years who haven't placed top 10 (SCDC) or top 3 (SVCDC)) | G22: Melody | H22: Elaine, Evelyn | K22: Suvir Maniktala | L22: suvir.maniktala@warriorlife.net | M22: Ayden Wang | N22: N | O22: 2nd Year | P22: 4 | Q22: IMCS | R22: =IF(COUNTIF(B$2:B$149,L22)=0,0,1) -> 1 | S22: =IF(COUNTIF(B$150:B$274,L22)=0,0,1) -> 1 | T22: =IF(COUNTIF(B$275:B$401,L22)=0,0,1) -> 1 | U22: =IFERROR(__xludf.DUMMYFUNCTION("IFERROR(IF(Match(L22,IMPORTRANGE(""https://docs.google.com/spreadsheets/d/1CAXKDiOnZb21bZOY_nacH9xI9AiD-nH8ZZQAwYKkVC0/edit?usp=drivesdk"",""Completed Exams!A1:A135""),0),1), 0)"),0.0) -> 0 | V22: =IF(COUNTIF(B$416:B$535,L22)=0,0,1) -> 1 | W22: =IF(COUNTIF(B$535:B$602,L22)=0,0,1) -> 0 | X22: =IF(COUNTIF(B$603:B$725,L22)=0,0,1) -> 1 | Y22: =IF(COUNTIF(B$725:B$844,L22)=0,0,1) -> 1 | Z22: =IF(COUNTIF(B$845:B$969,L22)=0,0,1) -> 1 | AA22: =IF(COUNTIF(B$971:B$1124,L22)=0,0,1) -> 1 | AB22: =IFERROR(__xludf.DUMMYFUNCTION("IFERROR(IF(Match(L22,IMPORTRANGE(""https://docs.google.com/spreadsheets/d/1n1sT_Q_W3mKmn2Yrd8qcNzuRD4zr4DB9gqARnjQ30B4/edit?gid=1918970062#gid=1918970062"",""Form Responses 1!B2:B49""),0),1), 0)"),0.0) -> 0 | AC22: =IF(COUNTIF(B$1145:B$1305,L22)=0,0,1) -> 1 | AD22: 1 | AE22: =IFERROR(__xludf.DUMMYFUNCTION("IFERROR(IF(Match(L22,IMPORTRANGE(""https://docs.google.com/spreadsheets/d/1hvckjcCpxEuDQDPrBMml_I1kBhYyjrgR8qBKC9QGVUc/edit?resourcekey=&gid=230793720#gid=230793720"",""Form Responses 1!B2:B199""),0),1), 0)"),0.0) -> 0 | AF22: =IFERROR(__xludf.DUMMYFUNCTION("IFERROR(IF(Match(L22,IMPORTRANGE(""https://docs.google.com/spreadsheets/d/1UY0hI2S83Fmafa5P-C1LM9yqe4v4qIKTnVy_CzLzRPs/edit?resourcekey=&gid=1583835601#gid=1583835601"",""Form Responses 1!B2:B194""),0),1), 0)"),0.0) -> 0 | AG22: =IFERROR(__xludf.DUMMYFUNCTION("IFERROR(IF(Match(L22,IMPORTRANGE(""https://docs.google.com/spreadsheets/d/1hO4mQ22n6cudUygJ2ss_JeJdm2Ua_7hJl_79lWWEtic/edit?resourcekey=&gid=2087212010#gid=2087212010"",""Form Responses 1!B2:B104""),0),1), 0)"),0.0) -> 0 | AH22: =IFERROR(__xludf.DUMMYFUNCTION("IFERROR(IF(Match(L22,IMPORTRANGE(""https://docs.google.com/spreadsheets/d/1HbfCXhSXbtTODKKY1MOFwJccyhgDKD0J9sO1k5l_6lM/edit?resourcekey=&gid=1616384832#gid=1616384832"",""Form Responses 1!E2:E143""),0),1), 0)"),0.0) -> 0
A23: 45917.662 | B23: crystal.chen@warriorlife.net | C23: Crystal | D23: Chen | E23: G107 | F23: Novice (1st year or 2nd years who haven't placed top 10 (SCDC) or top 3 (SVCDC)) | G23: Philina Chen | H23: Elaine and Evelyn | K23: Ethan Teh | L23: ethan.teh@warriorlife.net | M23: Chloe Ding | N23: N | O23: 2nd Year | P23: 5 | Q23: EIB | R23: =IF(COUNTIF(B$2:B$149,L23)=0,0,1) -> 1 | S23: =IF(COUNTIF(B$150:B$274,L23)=0,0,1) -> 0 | T23: =IF(COUNTIF(B$275:B$401,L23)=0,0,1) -> 1 | U23: =IFERROR(__xludf.DUMMYFUNCTION("IFERROR(IF(Match(L23,IMPORTRANGE(""https://docs.google.com/spreadsheets/d/1CAXKDiOnZb21bZOY_nacH9xI9AiD-nH8ZZQAwYKkVC0/edit?usp=drivesdk"",""Completed Exams!A1:A135""),0),1), 0)"),0.0) -> 0 | V23: =IF(COUNTIF(B$416:B$535,L23)=0,0,1) -> 1 | W23: =IF(COUNTIF(B$535:B$602,L23)=0,0,1) -> 0 | X23: =IF(COUNTIF(B$603:B$725,L23)=0,0,1) -> 1 | Y23: =IF(COUNTIF(B$725:B$844,L23)=0,0,1) -> 1 | Z23: =IF(COUNTIF(B$845:B$969,L23)=0,0,1) -> 1 | AA23: =IF(COUNTIF(B$971:B$1124,L23)=0,0,1) -> 1 | AB23: =IFERROR(__xludf.DUMMYFUNCTION("IFERROR(IF(Match(L23,IMPORTRANGE(""https://docs.google.com/spreadsheets/d/1n1sT_Q_W3mKmn2Yrd8qcNzuRD4zr4DB9gqARnjQ30B4/edit?gid=1918970062#gid=1918970062"",""Form Responses 1!B2:B49""),0),1), 0)"),0.0) -> 0 | AC23: =IF(COUNTIF(B$1145:B$1305,L23)=0,0,1) -> 1 | AD23: 0 | AE23: =IFERROR(__xludf.DUMMYFUNCTION("IFERROR(IF(Match(L23,IMPORTRANGE(""https://docs.google.com/spreadsheets/d/1hvckjcCpxEuDQDPrBMml_I1kBhYyjrgR8qBKC9QGVUc/edit?resourcekey=&gid=230793720#gid=230793720"",""Form Responses 1!B2:B199""),0),1), 0)"),0.0) -> 0 | AF23: =IFERROR(__xludf.DUMMYFUNCTION("IFERROR(IF(Match(L23,IMPORTRANGE(""https://docs.google.com/spreadsheets/d/1UY0hI2S83Fmafa5P-C1LM9yqe4v4qIKTnVy_CzLzRPs/edit?resourcekey=&gid=1583835601#gid=1583835601"",""Form Responses 1!B2:B194""),0),1), 0)"),0.0) -> 0 | AG23: =IFERROR(__xludf.DUMMYFUNCTION("IFERROR(IF(Match(L23,IMPORTRANGE(""https://docs.google.com/spreadsheets/d/1hO4mQ22n6cudUygJ2ss_JeJdm2Ua_7hJl_79lWWEtic/edit?resourcekey=&gid=2087212010#gid=2087212010"",""Form Responses 1!B2:B104""),0),1), 0)"),0.0) -> 0 | AH23: =IFERROR(__xludf.DUMMYFUNCTION("IFERROR(IF(Match(L23,IMPORTRANGE(""https://docs.google.com/spreadsheets/d/1HbfCXhSXbtTODKKY1MOFwJccyhgDKD0J9sO1k5l_6lM/edit?resourcekey=&gid=1616384832#gid=1616384832"",""Form Responses 1!E2:E143""),0),1), 0)"),0.0) -> 0
A24: 45917.662 | B24: woobin.jang@warriorlife.net | C24: Woobin | D24: Jang | E24: G107 | F24: Novice (1st year or 2nd years who haven't placed top 10 (SCDC) or top 3 (SVCDC)) | G24: Lizzie Huang | H24: Elaine, evelyn | K24: Jason Tang | L24: jason.tang@warriorlife.net | M24: Chloe Ding | N24: N | O24: 2nd Year | P24: 5 | Q24: EIB | R24: 0.5 | S24: =IF(COUNTIF(B$150:B$274,L24)=0,0,1) -> 0 | T24: =IF(COUNTIF(B$275:B$401,L24)=0,0,1) -> 1 | U24: =IFERROR(__xludf.DUMMYFUNCTION("IFERROR(IF(Match(L24,IMPORTRANGE(""https://docs.google.com/spreadsheets/d/1CAXKDiOnZb21bZOY_nacH9xI9AiD-nH8ZZQAwYKkVC0/edit?usp=drivesdk"",""Completed Exams!A1:A135""),0),1), 0)"),0.0) -> 0 | V24: =IF(COUNTIF(B$416:B$535,L24)=0,0,1) -> 1 | W24: =IF(COUNTIF(B$535:B$602,L24)=0,0,1) -> 1 | X24: =IF(COUNTIF(B$603:B$725,L24)=0,0,1) -> 1 | Y24: =IF(COUNTIF(B$725:B$844,L24)=0,0,1) -> 1 | Z24: =IF(COUNTIF(B$845:B$969,L24)=0,0,1) -> 1 | AA24: =IF(COUNTIF(B$971:B$1124,L24)=0,0,1) -> 1 | AB24: =IFERROR(__xludf.DUMMYFUNCTION("IFERROR(IF(Match(L24,IMPORTRANGE(""https://docs.google.com/spreadsheets/d/1n1sT_Q_W3mKmn2Yrd8qcNzuRD4zr4DB9gqARnjQ30B4/edit?gid=1918970062#gid=1918970062"",""Form Responses 1!B2:B49""),0),1), 0)"),0.0) -> 0 | AC24: =IF(COUNTIF(B$1145:B$1305,L24)=0,0,1) -> 1 | AD24: 0 | AE24: =IFERROR(__xludf.DUMMYFUNCTION("IFERROR(IF(Match(L24,IMPORTRANGE(""https://docs.google.com/spreadsheets/d/1hvckjcCpxEuDQDPrBMml_I1kBhYyjrgR8qBKC9QGVUc/edit?resourcekey=&gid=230793720#gid=230793720"",""Form Responses 1!B2:B199""),0),1), 0)"),0.0) -> 0 | AF24: =IFERROR(__xludf.DUMMYFUNCTION("IFERROR(IF(Match(L24,IMPORTRANGE(""https://docs.google.com/spreadsheets/d/1UY0hI2S83Fmafa5P-C1LM9yqe4v4qIKTnVy_CzLzRPs/edit?resourcekey=&gid=1583835601#gid=1583835601"",""Form Responses 1!B2:B194""),0),1), 0)"),0.0) -> 0 | AG24: =IFERROR(__xludf.DUMMYFUNCTION("IFERROR(IF(Match(L24,IMPORTRANGE(""https://docs.google.com/spreadsheets/d/1hO4mQ22n6cudUygJ2ss_JeJdm2Ua_7hJl_79lWWEtic/edit?resourcekey=&gid=2087212010#gid=2087212010"",""Form Responses 1!B2:B104""),0),1), 0)"),0.0) -> 0 | AH24: 0.5
A25: 45917.662 | B25: s.swaminathan@warriorlife.net | C25: Sidharth | D25: Swaminathan | E25: G107 | F25: Novice (1st year or 2nd years who haven't placed top 10 (SCDC) or top 3 (SVCDC)) | G25: Melody Leong | H25: Elaine and Evelyn | K25: Gordon Lee | L25: gordon.lee@warriorlife.net | M25: Chloe Ding | N25: N | O25: 1st Year | P25: 5 | Q25: ESB | R25: =IF(COUNTIF(B$2:B$149,L25)=0,0,1) -> 1 | S25: =IF(COUNTIF(B$150:B$274,L25)=0,0,1) -> 1 | T25: =IF(COUNTIF(B$275:B$401,L25)=0,0,1) -> 1 | U25: =IFERROR(__xludf.DUMMYFUNCTION("IFERROR(IF(Match(L25,IMPORTRANGE(""https://docs.google.com/spreadsheets/d/1CAXKDiOnZb21bZOY_nacH9xI9AiD-nH8ZZQAwYKkVC0/edit?usp=drivesdk"",""Completed Exams!A1:A135""),0),1), 0)"),0.0) -> 0 | V25: =IF(COUNTIF(B$416:B$535,L25)=0,0,1) -> 0 | W25: =IF(COUNTIF(B$535:B$602,L25)=0,0,1) -> 0 | X25: =IF(COUNTIF(B$603:B$725,L25)=0,0,1) -> 1 | Y25: 1 | Z25: =IF(COUNTIF(B$845:B$969,L25)=0,0,1) -> 1 | AA25: =IF(COUNTIF(B$971:B$1124,L25)=0,0,1) -> 1 | AB25: 1 | AC25: =IF(COUNTIF(B$1145:B$1305,L25)=0,0,1) -> 1 | AD25: 1 | AE25: =IFERROR(__xludf.DUMMYFUNCTION("IFERROR(IF(Match(L25,IMPORTRANGE(""https://docs.google.com/spreadsheets/d/1hvckjcCpxEuDQDPrBMml_I1kBhYyjrgR8qBKC9QGVUc/edit?resourcekey=&gid=230793720#gid=230793720"",""Form Responses 1!B2:B199""),0),1), 0)"),0.0) -> 0 | AF25: =IFERROR(__xludf.DUMMYFUNCTION("IFERROR(IF(Match(L25,IMPORTRANGE(""https://docs.google.com/spreadsheets/d/1UY0hI2S83Fmafa5P-C1LM9yqe4v4qIKTnVy_CzLzRPs/edit?resourcekey=&gid=1583835601#gid=1583835601"",""Form Responses 1!B2:B194""),0),1), 0)"),0.0) -> 0 | AG25: =IFERROR(__xludf.DUMMYFUNCTION("IFERROR(IF(Match(L25,IMPORTRANGE(""https://docs.google.com/spreadsheets/d/1hO4mQ22n6cudUygJ2ss_JeJdm2Ua_7hJl_79lWWEtic/edit?resourcekey=&gid=2087212010#gid=2087212010"",""Form Responses 1!B2:B104""),0),1), 0)"),0.0) -> 0 | AH25: =IFERROR(__xludf.DUMMYFUNCTION("IFERROR(IF(Match(L25,IMPORTRANGE(""https://docs.google.com/spreadsheets/d/1HbfCXhSXbtTODKKY1MOFwJccyhgDKD0J9sO1k5l_6lM/edit?resourcekey=&gid=1616384832#gid=1616384832"",""Form Responses 1!E2:E143""),0),1), 0)"),0.0) -> 0
A26: 45917.662 | B26: joey.zhu@warriorlife.net | C26: Joey | D26: Zhu | E26: G107 | F26: Novice (1st year or 2nd years who haven't placed top 10 (SCDC) or top 3 (SVCDC)) | G26: Lizzie Huang | H26: Evelyn Elaine | K26: Matthew Zhu | L26: matthew.zhu@warriorlife.net | M26: Chloe Ding | N26: N | O26: 2nd Year | P26: 5 | Q26: ESB | R26: =IF(COUNTIF(B$2:B$149,L26)=0,0,1) -> 1 | S26: =IF(COUNTIF(B$150:B$274,L26)=0,0,1) -> 1 | T26: =IF(COUNTIF(B$275:B$401,L26)=0,0,1) -> 1 | U26: =IFERROR(__xludf.DUMMYFUNCTION("IFERROR(IF(Match(L26,IMPORTRANGE(""https://docs.google.com/spreadsheets/d/1CAXKDiOnZb21bZOY_nacH9xI9AiD-nH8ZZQAwYKkVC0/edit?usp=drivesdk"",""Completed Exams!A1:A135""),0),1), 0)"),0.0) -> 0 | V26: =IF(COUNTIF(B$416:B$535,L26)=0,0,1) -> 0 | W26: =IF(COUNTIF(B$535:B$602,L26)=0,0,1) -> 1 | X26: =IF(COUNTIF(B$603:B$725,L26)=0,0,1) -> 1 | Y26: =IF(COUNTIF(B$725:B$844,L26)=0,0,1) -> 1 | Z26: =IF(COUNTIF(B$845:B$969,L26)=0,0,1) -> 1 | AA26: =IF(COUNTIF(B$971:B$1124,L26)=0,0,1) -> 1 | AB26: =IFERROR(__xludf.DUMMYFUNCTION("IFERROR(IF(Match(L26,IMPORTRANGE(""https://docs.google.com/spreadsheets/d/1n1sT_Q_W3mKmn2Yrd8qcNzuRD4zr4DB9gqARnjQ30B4/edit?gid=1918970062#gid=1918970062"",""Form Responses 1!B2:B49""),0),1), 0)"),0.0) -> 0 | AC26: =IF(COUNTIF(B$1145:B$1305,L26)=0,0,1) -> 1 | AD26: 0 | AE26: =IFERROR(__xludf.DUMMYFUNCTION("IFERROR(IF(Match(L26,IMPORTRANGE(""https://docs.google.com/spreadsheets/d/1hvckjcCpxEuDQDPrBMml_I1kBhYyjrgR8qBKC9QGVUc/edit?resourcekey=&gid=230793720#gid=230793720"",""Form Responses 1!B2:B199""),0),1), 0)"),0.0) -> 0 | AF26: =IFERROR(__xludf.DUMMYFUNCTION("IFERROR(IF(Match(L26,IMPORTRANGE(""https://docs.google.com/spreadsheets/d/1UY0hI2S83Fmafa5P-C1LM9yqe4v4qIKTnVy_CzLzRPs/edit?resourcekey=&gid=1583835601#gid=1583835601"",""Form Responses 1!B2:B194""),0),1), 0)"),0.0) -> 0 | AG26: =IFERROR(__xludf.DUMMYFUNCTION("IFERROR(IF(Match(L26,IMPORTRANGE(""https://docs.google.com/spreadsheets/d/1hO4mQ22n6cudUygJ2ss_JeJdm2Ua_7hJl_79lWWEtic/edit?resourcekey=&gid=2087212010#gid=2087212010"",""Form Responses 1!B2:B104""),0),1), 0)"),0.0) -> 0 | AH26: =IFERROR(__xludf.DUMMYFUNCTION("IFERROR(IF(Match(L26,IMPORTRANGE(""https://docs.google.com/spreadsheets/d/1HbfCXhSXbtTODKKY1MOFwJccyhgDKD0J9sO1k5l_6lM/edit?resourcekey=&gid=1616384832#gid=1616384832"",""Form Responses 1!E2:E143""),0),1), 0)"),0.0) -> 0
A27: 45917.662 | B27: neela.koneru@warriorlife.net | C27: Neela | D27: Koneru | E27: G107 | F27: Novice (1st year or 2nd years who haven't placed top 10 (SCDC) or top 3 (SVCDC)) | G27: Saron | H27: Evelyn, Elaine | K27: Isabella Su | L27: isabella.su@warriorlife.net | M27: Chloe Zhong | N27: N | O27: 1st Year | P27: 6 | Q27: EIP | R27: =IF(COUNTIF(B$2:B$149,L27)=0,0,1) -> 1 | S27: =IF(COUNTIF(B$150:B$274,L27)=0,0,1) -> 1 | T27: =IF(COUNTIF(B$275:B$401,L27)=0,0,1) -> 1 | U27: =IFERROR(__xludf.DUMMYFUNCTION("IFERROR(IF(Match(L27,IMPORTRANGE(""https://docs.google.com/spreadsheets/d/1CAXKDiOnZb21bZOY_nacH9xI9AiD-nH8ZZQAwYKkVC0/edit?usp=drivesdk"",""Completed Exams!A1:A135""),0),1), 0)"),0.0) -> 0 | V27: =IF(COUNTIF(B$416:B$535,L27)=0,0,1) -> 1 | W27: 1 | X27: =IF(COUNTIF(B$603:B$725,L27)=0,0,1) -> 1 | Y27: =IF(COUNTIF(B$725:B$844,L27)=0,0,1) -> 1 | Z27: =IF(COUNTIF(B$845:B$969,L27)=0,0,1) -> 0 | AA27: =IF(COUNTIF(B$971:B$1124,L27)=0,0,1) -> 1 | AB27: =IFERROR(__xludf.DUMMYFUNCTION("IFERROR(IF(Match(L27,IMPORTRANGE(""https://docs.google.com/spreadsheets/d/1n1sT_Q_W3mKmn2Yrd8qcNzuRD4zr4DB9gqARnjQ30B4/edit?gid=1918970062#gid=1918970062"",""Form Responses 1!B2:B49""),0),1), 0)"),0.0) -> 0 | AC27: =IF(COUNTIF(B$1145:B$1305,L27)=0,0,1) -> 1 | AD27: 0.5 | AE27: =IFERROR(__xludf.DUMMYFUNCTION("IFERROR(IF(Match(L27,IMPORTRANGE(""https://docs.google.com/spreadsheets/d/1hvckjcCpxEuDQDPrBMml_I1kBhYyjrgR8qBKC9QGVUc/edit?resourcekey=&gid=230793720#gid=230793720"",""Form Responses 1!B2:B199""),0),1), 0)"),0.0) -> 0 | AF27: =IFERROR(__xludf.DUMMYFUNCTION("IFERROR(IF(Match(L27,IMPORTRANGE(""https://docs.google.com/spreadsheets/d/1UY0hI2S83Fmafa5P-C1LM9yqe4v4qIKTnVy_CzLzRPs/edit?resourcekey=&gid=1583835601#gid=1583835601"",""Form Responses 1!B2:B194""),0),1), 0)"),0.0) -> 0 | AG27: =IFERROR(__xludf.DUMMYFUNCTION("IFERROR(IF(Match(L27,IMPORTRANGE(""https://docs.google.com/spreadsheets/d/1hO4mQ22n6cudUygJ2ss_JeJdm2Ua_7hJl_79lWWEtic/edit?resourcekey=&gid=2087212010#gid=2087212010"",""Form Responses 1!B2:B104""),0),1), 0)"),0.0) -> 0 | AH27: =IFERROR(__xludf.DUMMYFUNCTION("IFERROR(IF(Match(L27,IMPORTRANGE(""https://docs.google.com/spreadsheets/d/1HbfCXhSXbtTODKKY1MOFwJccyhgDKD0J9sO1k5l_6lM/edit?resourcekey=&gid=1616384832#gid=1616384832"",""Form Responses 1!E2:E143""),0),1), 0)"),0.0) -> 0
A28: 45917.662 | B28: hanna.handy@warriorlife.net | C28: Hanna | D28: Handy | E28: G106 | F28: Novice (1st year or 2nd years who haven't placed top 10 (SCDC) or top 3 (SVCDC)) | G28: Elizabeth Huang | H28: Evelyn and Elaine | K28: Ashley Park | L28: ashley.park@warriorlife.net | M28: Chloe Zhong | N28: E | O28: 3rd Year | P28: 6 | Q28: EIP | R28: =IF(COUNTIF(B$2:B$149,L28)=0,0,1) -> 1 | S28: =IF(COUNTIF(B$150:B$274,L28)=0,0,1) -> 0 | T28: =IF(COUNTIF(B$275:B$401,L28)=0,0,1) -> 0 | U28: =IFERROR(__xludf.DUMMYFUNCTION("IFERROR(IF(Match(L28,IMPORTRANGE(""https://docs.google.com/spreadsheets/d/1CAXKDiOnZb21bZOY_nacH9xI9AiD-nH8ZZQAwYKkVC0/edit?usp=drivesdk"",""Completed Exams!A1:A135""),0),1), 0)"),0.0) -> 0 | V28: =IF(COUNTIF(B$416:B$535,L28)=0,0,1) -> 1 | W28: =IF(COUNTIF(B$535:B$602,L28)=0,0,1) -> 0 | X28: =IF(COUNTIF(B$603:B$725,L28)=0,0,1) -> 1 | Y28: =IF(COUNTIF(B$725:B$844,L28)=0,0,1) -> 0 | Z28: =IF(COUNTIF(B$845:B$969,L28)=0,0,1) -> 0 | AA28: 0.5 | AB28: =IFERROR(__xludf.DUMMYFUNCTION("IFERROR(IF(Match(L28,IMPORTRANGE(""https://docs.google.com/spreadsheets/d/1n1sT_Q_W3mKmn2Yrd8qcNzuRD4zr4DB9gqARnjQ30B4/edit?gid=1918970062#gid=1918970062"",""Form Responses 1!B2:B49""),0),1), 0)"),0.0) -> 0 | AC28: =IF(COUNTIF(B$1145:B$1305,L28)=0,0,1) -> 1 | AD28: 0 | AE28: =IFERROR(__xludf.DUMMYFUNCTION("IFERROR(IF(Match(L28,IMPORTRANGE(""https://docs.google.com/spreadsheets/d/1hvckjcCpxEuDQDPrBMml_I1kBhYyjrgR8qBKC9QGVUc/edit?resourcekey=&gid=230793720#gid=230793720"",""Form Responses 1!B2:B199""),0),1), 0)"),0.0) -> 0 | AF28: =IFERROR(__xludf.DUMMYFUNCTION("IFERROR(IF(Match(L28,IMPORTRANGE(""https://docs.google.com/spreadsheets/d/1UY0hI2S83Fmafa5P-C1LM9yqe4v4qIKTnVy_CzLzRPs/edit?resourcekey=&gid=1583835601#gid=1583835601"",""Form Responses 1!B2:B194""),0),1), 0)"),0.0) -> 0 | AG28: =IFERROR(__xludf.DUMMYFUNCTION("IFERROR(IF(Match(L28,IMPORTRANGE(""https://docs.google.com/spreadsheets/d/1hO4mQ22n6cudUygJ2ss_JeJdm2Ua_7hJl_79lWWEtic/edit?resourcekey=&gid=2087212010#gid=2087212010"",""Form Responses 1!B2:B104""),0),1), 0)"),0.0) -> 0 | AH28: =IFERROR(__xludf.DUMMYFUNCTION("IFERROR(IF(Match(L28,IMPORTRANGE(""https://docs.google.com/spreadsheets/d/1HbfCXhSXbtTODKKY1MOFwJccyhgDKD0J9sO1k5l_6lM/edit?resourcekey=&gid=1616384832#gid=1616384832"",""Form Responses 1!E2:E143""),0),1), 0)"),0.0) -> 0
A29: 45917.662 | B29: gabriele.lynch@warriorlife.net | C29: Gabriele | D29: Lynch | E29: G107 | F29: Novice (1st year or 2nd years who haven't placed top 10 (SCDC) or top 3 (SVCDC)) | G29: Lizzie | H29: Evelyn and Elaine | K29: Jihoo Lee | L29: jihoo.lee@warriorlife.net | M29: Chloe Zhong | N29: E | O29: 3rd Year | P29: 6 | Q29: EIP | R29: =IF(COUNTIF(B$2:B$149,L29)=0,0,1) -> 1 | S29: =IF(COUNTIF(B$150:B$274,L29)=0,0,1) -> 0 | T29: =IF(COUNTIF(B$275:B$401,L29)=0,0,1) -> 0 | U29: 1 | V29: =IF(COUNTIF(B$416:B$535,L29)=0,0,1) -> 0 | W29: =IF(COUNTIF(B$535:B$602,L29)=0,0,1) -> 1 | X29: =IF(COUNTIF(B$603:B$725,L29)=0,0,1) -> 1 | Y29: =IF(COUNTIF(B$725:B$844,L29)=0,0,1) -> 1 | Z29: =IF(COUNTIF(B$845:B$969,L29)=0,0,1) -> 0 | AA29: =IF(COUNTIF(B$971:B$1124,L29)=0,0,1) -> 1 | AB29: =IFERROR(__xludf.DUMMYFUNCTION("IFERROR(IF(Match(L29,IMPORTRANGE(""https://docs.google.com/spreadsheets/d/1n1sT_Q_W3mKmn2Yrd8qcNzuRD4zr4DB9gqARnjQ30B4/edit?gid=1918970062#gid=1918970062"",""Form Responses 1!B2:B49""),0),1), 0)"),0.0) -> 0 | AC29: =IF(COUNTIF(B$1145:B$1305,L29)=0,0,1) -> 1 | AD29: 0.5 | AE29: =IFERROR(__xludf.DUMMYFUNCTION("IFERROR(IF(Match(L29,IMPORTRANGE(""https://docs.google.com/spreadsheets/d/1hvckjcCpxEuDQDPrBMml_I1kBhYyjrgR8qBKC9QGVUc/edit?resourcekey=&gid=230793720#gid=230793720"",""Form Responses 1!B2:B199""),0),1), 0)"),0.0) -> 0 | AF29: =IFERROR(__xludf.DUMMYFUNCTION("IFERROR(IF(Match(L29,IMPORTRANGE(""https://docs.google.com/spreadsheets/d/1UY0hI2S83Fmafa5P-C1LM9yqe4v4qIKTnVy_CzLzRPs/edit?resourcekey=&gid=1583835601#gid=1583835601"",""Form Responses 1!B2:B194""),0),1), 0)"),0.0) -> 0 | AG29: =IFERROR(__xludf.DUMMYFUNCTION("IFERROR(IF(Match(L29,IMPORTRANGE(""https://docs.google.com/spreadsheets/d/1hO4mQ22n6cudUygJ2ss_JeJdm2Ua_7hJl_79lWWEtic/edit?resourcekey=&gid=2087212010#gid=2087212010"",""Form Responses 1!B2:B104""),0),1), 0)"),0.0) -> 0 | AH29: =IFERROR(__xludf.DUMMYFUNCTION("IFERROR(IF(Match(L29,IMPORTRANGE(""https://docs.google.com/spreadsheets/d/1HbfCXhSXbtTODKKY1MOFwJccyhgDKD0J9sO1k5l_6lM/edit?resourcekey=&gid=1616384832#gid=1616384832"",""Form Responses 1!E2:E143""),0),1), 0)"),0.0) -> 0
A30: 45917.662 | B30: ava.shu@warriorlife.net | C30: Ava | D30: Shu | E30: G107 | F30: Novice (1st year or 2nd years who haven't placed top 10 (SCDC) or top 3 (SVCDC)) | G30: Isabella Yu | H30: Elaine and Evelyn | K30: Lucas Wang | L30: lucasj.wang@warriorlife.net | M30: Chloe Zhong | N30: E | O30: 3rd Year | P30: 6 | Q30: EIP | R30: =IF(COUNTIF(B$2:B$149,L30)=0,0,1) -> 1 | S30: =IF(COUNTIF(B$150:B$274,L30)=0,0,1) -> 0 | T30: =IF(COUNTIF(B$275:B$401,L30)=0,0,1) -> 1 | U30: 1 | V30: =IF(COUNTIF(B$416:B$535,L30)=0,0,1) -> 0 | W30: =IF(COUNTIF(B$535:B$602,L30)=0,0,1) -> 0 | X30: =IF(COUNTIF(B$603:B$725,L30)=0,0,1) -> 1 | Y30: =IF(COUNTIF(B$725:B$844,L30)=0,0,1) -> 1 | Z30: =IF(COUNTIF(B$845:B$969,L30)=0,0,1) -> 0 | AA30: =IF(COUNTIF(B$971:B$1124,L30)=0,0,1) -> 1 | AB30: =IFERROR(__xludf.DUMMYFUNCTION("IFERROR(IF(Match(L30,IMPORTRANGE(""https://docs.google.com/spreadsheets/d/1n1sT_Q_W3mKmn2Yrd8qcNzuRD4zr4DB9gqARnjQ30B4/edit?gid=1918970062#gid=1918970062"",""Form Responses 1!B2:B49""),0),1), 0)"),0.0) -> 0 | AC30: =IF(COUNTIF(B$1145:B$1305,L30)=0,0,1) -> 1 | AD30: 0 | AE30: =IFERROR(__xludf.DUMMYFUNCTION("IFERROR(IF(Match(L30,IMPORTRANGE(""https://docs.google.com/spreadsheets/d/1hvckjcCpxEuDQDPrBMml_I1kBhYyjrgR8qBKC9QGVUc/edit?resourcekey=&gid=230793720#gid=230793720"",""Form Responses 1!B2:B199""),0),1), 0)"),0.0) -> 0 | AF30: =IFERROR(__xludf.DUMMYFUNCTION("IFERROR(IF(Match(L30,IMPORTRANGE(""https://docs.google.com/spreadsheets/d/1UY0hI2S83Fmafa5P-C1LM9yqe4v4qIKTnVy_CzLzRPs/edit?resourcekey=&gid=1583835601#gid=1583835601"",""Form Responses 1!B2:B194""),0),1), 0)"),0.0) -> 0 | AG30: =IFERROR(__xludf.DUMMYFUNCTION("IFERROR(IF(Match(L30,IMPORTRANGE(""https://docs.google.com/spreadsheets/d/1hO4mQ22n6cudUygJ2ss_JeJdm2Ua_7hJl_79lWWEtic/edit?resourcekey=&gid=2087212010#gid=2087212010"",""Form Responses 1!B2:B104""),0),1), 0)"),0.0) -> 0 | AH30: =IFERROR(__xludf.DUMMYFUNCTION("IFERROR(IF(Match(L30,IMPORTRANGE(""https://docs.google.com/spreadsheets/d/1HbfCXhSXbtTODKKY1MOFwJccyhgDKD0J9sO1k5l_6lM/edit?resourcekey=&gid=1616384832#gid=1616384832"",""Form Responses 1!E2:E143""),0),1), 0)"),0.0) -> 0
A31: 45917.662 | B31: hailey.taylor@warriorlife.net | C31: hailey | D31: taylor | E31: G107 | F31: Novice (1st year or 2nd years who haven't placed top 10 (SCDC) or top 3 (SVCDC)) | G31: elaine wang | H31: elaine and evelyn | K31: Kayla Tan | L31: kayla.tan@warriorlife.net | M31: Chloe Zhong | N31: E | O31: 2nd Year | P31: 6 | Q31: PMCG | R31: =IF(COUNTIF(B$2:B$149,L31)=0,0,1) -> 1 | S31: =IF(COUNTIF(B$150:B$274,L31)=0,0,1) -> 0 | T31: =IF(COUNTIF(B$275:B$401,L31)=0,0,1) -> 0 | U31: =IFERROR(__xludf.DUMMYFUNCTION("IFERROR(IF(Match(L31,IMPORTRANGE(""https://docs.google.com/spreadsheets/d/1CAXKDiOnZb21bZOY_nacH9xI9AiD-nH8ZZQAwYKkVC0/edit?usp=drivesdk"",""Completed Exams!A1:A135""),0),1), 0)"),0.0) -> 0 | V31: =IF(COUNTIF(B$416:B$535,L31)=0,0,1) -> 0 | W31: 1 | X31: =IF(COUNTIF(B$603:B$725,L31)=0,0,1) -> 0 | Y31: =IF(COUNTIF(B$725:B$844,L31)=0,0,1) -> 0 | Z31: =IF(COUNTIF(B$845:B$969,L31)=0,0,1) -> 0 | AA31: =IF(COUNTIF(B$971:B$1124,L31)=0,0,1) -> 1 | AB31: =IFERROR(__xludf.DUMMYFUNCTION("IFERROR(IF(Match(L31,IMPORTRANGE(""https://docs.google.com/spreadsheets/d/1n1sT_Q_W3mKmn2Yrd8qcNzuRD4zr4DB9gqARnjQ30B4/edit?gid=1918970062#gid=1918970062"",""Form Responses 1!B2:B49""),0),1), 0)"),0.0) -> 0 | AC31: =IF(COUNTIF(B$1145:B$1305,L31)=0,0,1) -> 1 | AD31: 0 | AE31: =IFERROR(__xludf.DUMMYFUNCTION("IFERROR(IF(Match(L31,IMPORTRANGE(""https://docs.google.com/spreadsheets/d/1hvckjcCpxEuDQDPrBMml_I1kBhYyjrgR8qBKC9QGVUc/edit?resourcekey=&gid=230793720#gid=230793720"",""Form Responses 1!B2:B199""),0),1), 0)"),0.0) -> 0 | AF31: =IFERROR(__xludf.DUMMYFUNCTION("IFERROR(IF(Match(L31,IMPORTRANGE(""https://docs.google.com/spreadsheets/d/1UY0hI2S83Fmafa5P-C1LM9yqe4v4qIKTnVy_CzLzRPs/edit?resourcekey=&gid=1583835601#gid=1583835601"",""Form Responses 1!B2:B194""),0),1), 0)"),0.0) -> 0 | AG31: =IFERROR(__xludf.DUMMYFUNCTION("IFERROR(IF(Match(L31,IMPORTRANGE(""https://docs.google.com/spreadsheets/d/1hO4mQ22n6cudUygJ2ss_JeJdm2Ua_7hJl_79lWWEtic/edit?resourcekey=&gid=2087212010#gid=2087212010"",""Form Responses 1!B2:B104""),0),1), 0)"),0.0) -> 0 | AH31: =IFERROR(__xludf.DUMMYFUNCTION("IFERROR(IF(Match(L31,IMPORTRANGE(""https://docs.google.com/spreadsheets/d/1HbfCXhSXbtTODKKY1MOFwJccyhgDKD0J9sO1k5l_6lM/edit?resourcekey=&gid=1616384832#gid=1616384832"",""Form Responses 1!E2:E143""),0),1), 0)"),0.0) -> 0
A32: 45917.662 | B32: aubrey.santos@warriorlife.net | C32: Aubrey | D32: Santos | E32: G107 | F32: Novice (1st year or 2nd years who haven't placed top 10 (SCDC) or top 3 (SVCDC)) | G32: Ayden | H32: Elaine, Evelyn | K32: Sofia Choo | L32: sofia.choo@warriorlife.net | M32: Chloe Zhong | N32: N | O32: 2nd Year | P32: 6 | Q32: IBP | R32: =IF(COUNTIF(B$2:B$149,L32)=0,0,1) -> 1 | S32: =IF(COUNTIF(B$150:B$274,L32)=0,0,1) -> 1 | T32: =IF(COUNTIF(B$275:B$401,L32)=0,0,1) -> 1 | U32: =IFERROR(__xludf.DUMMYFUNCTION("IFERROR(IF(Match(L32,IMPORTRANGE(""https://docs.google.com/spreadsheets/d/1CAXKDiOnZb21bZOY_nacH9xI9AiD-nH8ZZQAwYKkVC0/edit?usp=drivesdk"",""Completed Exams!A1:A135""),0),1), 0)"),0.0) -> 0 | V32: =IF(COUNTIF(B$416:B$535,L32)=0,0,1) -> 1 | W32: =IF(COUNTIF(B$535:B$602,L32)=0,0,1) -> 1 | X32: =IF(COUNTIF(B$603:B$725,L32)=0,0,1) -> 1 | Y32: =IF(COUNTIF(B$725:B$844,L32)=0,0,1) -> 0 | Z32: =IF(COUNTIF(B$845:B$969,L32)=0,0,1) -> 0 | AA32: =IF(COUNTIF(B$971:B$1124,L32)=0,0,1) -> 1 | AB32: =IFERROR(__xludf.DUMMYFUNCTION("IFERROR(IF(Match(L32,IMPORTRANGE(""https://docs.google.com/spreadsheets/d/1n1sT_Q_W3mKmn2Yrd8qcNzuRD4zr4DB9gqARnjQ30B4/edit?gid=1918970062#gid=1918970062"",""Form Responses 1!B2:B49""),0),1), 0)"),0.0) -> 0 | AC32: =IF(COUNTIF(B$1145:B$1305,L32)=0,0,1) -> 0 | AD32: 0 | AE32: =IFERROR(__xludf.DUMMYFUNCTION("IFERROR(IF(Match(L32,IMPORTRANGE(""https://docs.google.com/spreadsheets/d/1hvckjcCpxEuDQDPrBMml_I1kBhYyjrgR8qBKC9QGVUc/edit?resourcekey=&gid=230793720#gid=230793720"",""Form Responses 1!B2:B199""),0),1), 0)"),0.0) -> 0 | AF32: =IFERROR(__xludf.DUMMYFUNCTION("IFERROR(IF(Match(L32,IMPORTRANGE(""https://docs.google.com/spreadsheets/d/1UY0hI2S83Fmafa5P-C1LM9yqe4v4qIKTnVy_CzLzRPs/edit?resourcekey=&gid=1583835601#gid=1583835601"",""Form Responses 1!B2:B194""),0),1), 0)"),0.0) -> 0 | AG32: =IFERROR(__xludf.DUMMYFUNCTION("IFERROR(IF(Match(L32,IMPORTRANGE(""https://docs.google.com/spreadsheets/d/1hO4mQ22n6cudUygJ2ss_JeJdm2Ua_7hJl_79lWWEtic/edit?resourcekey=&gid=2087212010#gid=2087212010"",""Form Responses 1!B2:B104""),0),1), 0)"),0.0) -> 0 | AH32: =IFERROR(__xludf.DUMMYFUNCTION("IFERROR(IF(Match(L32,IMPORTRANGE(""https://docs.google.com/spreadsheets/d/1HbfCXhSXbtTODKKY1MOFwJccyhgDKD0J9sO1k5l_6lM/edit?resourcekey=&gid=1616384832#gid=1616384832"",""Form Responses 1!E2:E143""),0),1), 0)"),0.0) -> 0
A33: 45917.662 | B33: elaine.choi@warriorlife.net | C33: Elaine | D33: Choi | E33: G107 | F33: Novice (1st year or 2nd years who haven't placed top 10 (SCDC) or top 3 (SVCDC)) | G33: Isabella Yun | H33: Elaine and Evelyn | K33: Grace Frieder | L33: grace.frieder@warriorlife.net | M33: Elaine Wang | N33: N | O33: 1st Year | P33: 7 | Q33: IMCP | R33: =IF(COUNTIF(B$2:B$149,L33)=0,0,1) -> 1 | S33: 0.5 | T33: =IF(COUNTIF(B$275:B$401,L33)=0,0,1) -> 1 | U33: =IFERROR(__xludf.DUMMYFUNCTION("IFERROR(IF(Match(L33,IMPORTRANGE(""https://docs.google.com/spreadsheets/d/1CAXKDiOnZb21bZOY_nacH9xI9AiD-nH8ZZQAwYKkVC0/edit?usp=drivesdk"",""Completed Exams!A1:A135""),0),1), 0)"),0.0) -> 0 | V33: 0.5 | W33: 1 | X33: 0.5 | Y33: 1 | Z33: 1 | AA33: =IF(COUNTIF(B$971:B$1124,L33)=0,0,1) -> 1 | AB33: =IFERROR(__xludf.DUMMYFUNCTION("IFERROR(IF(Match(L33,IMPORTRANGE(""https://docs.google.com/spreadsheets/d/1n1sT_Q_W3mKmn2Yrd8qcNzuRD4zr4DB9gqARnjQ30B4/edit?gid=1918970062#gid=1918970062"",""Form Responses 1!B2:B49""),0),1), 0)"),0.0) -> 0 | AC33: =IF(COUNTIF(B$1145:B$1305,L33)=0,0,1) -> 1 | AD33: 0 | AE33: =IFERROR(__xludf.DUMMYFUNCTION("IFERROR(IF(Match(L33,IMPORTRANGE(""https://docs.google.com/spreadsheets/d/1hvckjcCpxEuDQDPrBMml_I1kBhYyjrgR8qBKC9QGVUc/edit?resourcekey=&gid=230793720#gid=230793720"",""Form Responses 1!B2:B199""),0),1), 0)"),0.0) -> 0 | AF33: =IFERROR(__xludf.DUMMYFUNCTION("IFERROR(IF(Match(L33,IMPORTRANGE(""https://docs.google.com/spreadsheets/d/1UY0hI2S83Fmafa5P-C1LM9yqe4v4qIKTnVy_CzLzRPs/edit?resourcekey=&gid=1583835601#gid=1583835601"",""Form Responses 1!B2:B194""),0),1), 0)"),0.0) -> 0 | AG33: =IFERROR(__xludf.DUMMYFUNCTION("IFERROR(IF(Match(L33,IMPORTRANGE(""https://docs.google.com/spreadsheets/d/1hO4mQ22n6cudUygJ2ss_JeJdm2Ua_7hJl_79lWWEtic/edit?resourcekey=&gid=2087212010#gid=2087212010"",""Form Responses 1!B2:B104""),0),1), 0)"),0.0) -> 0 | AH33: =IFERROR(__xludf.DUMMYFUNCTION("IFERROR(IF(Match(L33,IMPORTRANGE(""https://docs.google.com/spreadsheets/d/1HbfCXhSXbtTODKKY1MOFwJccyhgDKD0J9sO1k5l_6lM/edit?resourcekey=&gid=1616384832#gid=1616384832"",""Form Responses 1!E2:E143""),0),1), 0)"),0.0) -> 0
A34: 45917.662 | B34: thatcher.kim@warriorlife.net | C34: Thatcher | D34: Kim | E34: G107 | F34: Novice (1st year or 2nd years who haven't placed top 10 (SCDC) or top 3 (SVCDC)) | G34: Saron | H34: Evelyn, Elaine | K34: Hailey Taylor | L34: hailey.taylor@warriorlife.net | M34: Elaine Wang | N34: N | O34: 1st Year | P34: 7 | Q34: IMCP | R34: =IF(COUNTIF(B$2:B$149,L34)=0,0,1) -> 1 | S34: 1 | T34: 0.5 | U34: 0.5 | V34: =IF(COUNTIF(B$416:B$535,L34)=0,0,1) -> 0 | W34: 1 | X34: 1 | Y34: =IF(COUNTIF(B$725:B$844,L34)=0,0,1) -> 0 | Z34: =IF(COUNTIF(B$845:B$969,L34)=0,0,1) -> 1 | AA34: =IF(COUNTIF(B$971:B$1124,L34)=0,0,1) -> 1 | AB34: 1 | AC34: =IF(COUNTIF(B$1145:B$1305,L34)=0,0,1) -> 1 | AD34: 0 | AE34: =IFERROR(__xludf.DUMMYFUNCTION("IFERROR(IF(Match(L34,IMPORTRANGE(""https://docs.google.com/spreadsheets/d/1hvckjcCpxEuDQDPrBMml_I1kBhYyjrgR8qBKC9QGVUc/edit?resourcekey=&gid=230793720#gid=230793720"",""Form Responses 1!B2:B199""),0),1), 0)"),0.0) -> 0 | AF34: =IFERROR(__xludf.DUMMYFUNCTION("IFERROR(IF(Match(L34,IMPORTRANGE(""https://docs.google.com/spreadsheets/d/1UY0hI2S83Fmafa5P-C1LM9yqe4v4qIKTnVy_CzLzRPs/edit?resourcekey=&gid=1583835601#gid=1583835601"",""Form Responses 1!B2:B194""),0),1), 0)"),0.0) -> 0 | AG34: =IFERROR(__xludf.DUMMYFUNCTION("IFERROR(IF(Match(L34,IMPORTRANGE(""https://docs.google.com/spreadsheets/d/1hO4mQ22n6cudUygJ2ss_JeJdm2Ua_7hJl_79lWWEtic/edit?resourcekey=&gid=2087212010#gid=2087212010"",""Form Responses 1!B2:B104""),0),1), 0)"),0.0) -> 0 | AH34: =IFERROR(__xludf.DUMMYFUNCTION("IFERROR(IF(Match(L34,IMPORTRANGE(""https://docs.google.com/spreadsheets/d/1HbfCXhSXbtTODKKY1MOFwJccyhgDKD0J9sO1k5l_6lM/edit?resourcekey=&gid=1616384832#gid=1616384832"",""Form Responses 1!E2:E143""),0),1), 0)"),0.0) -> 0
A35: 45917.662 | B35: shalom.kommu@warriorlife.net | C35: Shalom | D35: Kommu | E35: G107 | F35: Novice (1st year or 2nd years who haven't placed top 10 (SCDC) or top 3 (SVCDC)) | G35: Isabella Yu | H35: Elaine and Evelyn | K35: Kate Borba | L35: kate.borba@warriorlife.net | M35: Elaine Wang | N35: N | O35: 1st Year | P35: 7 | Q35: IMCP | R35: =IF(COUNTIF(B$2:B$149,L35)=0,0,1) -> 1 | S35: 0.5 | T35: =IF(COUNTIF(B$275:B$401,L35)=0,0,1) -> 1 | U35: =IFERROR(__xludf.DUMMYFUNCTION("IFERROR(IF(Match(L35,IMPORTRANGE(""https://docs.google.com/spreadsheets/d/1CAXKDiOnZb21bZOY_nacH9xI9AiD-nH8ZZQAwYKkVC0/edit?usp=drivesdk"",""Completed Exams!A1:A135""),0),1), 0)"),0.0) -> 0 | V35: =IF(COUNTIF(B$416:B$535,L35)=0,0,1) -> 0 | W35: 1 | X35: =IF(COUNTIF(B$603:B$725,L35)=0,0,1) -> 1 | Y35: 0.5 | Z35: =IF(COUNTIF(B$845:B$969,L35)=0,0,1) -> 1 | AA35: =IF(COUNTIF(B$971:B$1124,L35)=0,0,1) -> 1 | AB35: =IFERROR(__xludf.DUMMYFUNCTION("IFERROR(IF(Match(L35,IMPORTRANGE(""https://docs.google.com/spreadsheets/d/1n1sT_Q_W3mKmn2Yrd8qcNzuRD4zr4DB9gqARnjQ30B4/edit?gid=1918970062#gid=1918970062"",""Form Responses 1!B2:B49""),0),1), 0)"),0.0) -> 0 | AC35: =IF(COUNTIF(B$1145:B$1305,L35)=0,0,1) -> 1 | AD35: 0 | AE35: 0.5 | AF35: =IFERROR(__xludf.DUMMYFUNCTION("IFERROR(IF(Match(L35,IMPORTRANGE(""https://docs.google.com/spreadsheets/d/1UY0hI2S83Fmafa5P-C1LM9yqe4v4qIKTnVy_CzLzRPs/edit?resourcekey=&gid=1583835601#gid=1583835601"",""Form Responses 1!B2:B194""),0),1), 0)"),0.0) -> 0 | AG35: 0.5 | AH35: =IFERROR(__xludf.DUMMYFUNCTION("IFERROR(IF(Match(L35,IMPORTRANGE(""https://docs.google.com/spreadsheets/d/1HbfCXhSXbtTODKKY1MOFwJccyhgDKD0J9sO1k5l_6lM/edit?resourcekey=&gid=1616384832#gid=1616384832"",""Form Responses 1!E2:E143""),0),1), 0)"),0.0) -> 0
A36: 45917.662 | B36: suvir.maniktala@warriorlife.net | C36: Suvir | D36: Maniktala | E36: G107 | F36: Novice (1st year or 2nd years who haven't placed top 10 (SCDC) or top 3 (SVCDC)) | G36: Ayden Wang | H36: Elaine and Evelyn | K36: Aditya Poduri | L36: aditya.poduri@warriorlife.net | M36: Elaine Wang | N36: N | O36: 2nd Year | P36: 7 | Q36: PSE | R36: =IF(COUNTIF(B$2:B$149,L36)=0,0,1) -> 1 | S36: =IF(COUNTIF(B$150:B$274,L36)=0,0,1) -> 1 | T36: 0.5 | U36: =IFERROR(__xludf.DUMMYFUNCTION("IFERROR(IF(Match(L36,IMPORTRANGE(""https://docs.google.com/spreadsheets/d/1CAXKDiOnZb21bZOY_nacH9xI9AiD-nH8ZZQAwYKkVC0/edit?usp=drivesdk"",""Completed Exams!A1:A135""),0),1), 0)"),0.0) -> 0 | V36: =IF(COUNTIF(B$416:B$535,L36)=0,0,1) -> 1 | W36: 1 | X36: =IF(COUNTIF(B$603:B$725,L36)=0,0,1) -> 1 | Y36: =IF(COUNTIF(B$725:B$844,L36)=0,0,1) -> 0 | Z36: 0.5 | AA36: =IF(COUNTIF(B$971:B$1124,L36)=0,0,1) -> 1 | AB36: 1 | AC36: =IF(COUNTIF(B$1145:B$1305,L36)=0,0,1) -> 1 | AD36: 0 | AE36: =IFERROR(__xludf.DUMMYFUNCTION("IFERROR(IF(Match(L36,IMPORTRANGE(""https://docs.google.com/spreadsheets/d/1hvckjcCpxEuDQDPrBMml_I1kBhYyjrgR8qBKC9QGVUc/edit?resourcekey=&gid=230793720#gid=230793720"",""Form Responses 1!B2:B199""),0),1), 0)"),0.0) -> 0 | AF36: =IFERROR(__xludf.DUMMYFUNCTION("IFERROR(IF(Match(L36,IMPORTRANGE(""https://docs.google.com/spreadsheets/d/1UY0hI2S83Fmafa5P-C1LM9yqe4v4qIKTnVy_CzLzRPs/edit?resourcekey=&gid=1583835601#gid=1583835601"",""Form Responses 1!B2:B194""),0),1), 0)"),0.0) -> 0 | AG36: =IFERROR(__xludf.DUMMYFUNCTION("IFERROR(IF(Match(L36,IMPORTRANGE(""https://docs.google.com/spreadsheets/d/1hO4mQ22n6cudUygJ2ss_JeJdm2Ua_7hJl_79lWWEtic/edit?resourcekey=&gid=2087212010#gid=2087212010"",""Form Responses 1!B2:B104""),0),1), 0)"),0.0) -> 0 | AH36: =IFERROR(__xludf.DUMMYFUNCTION("IFERROR(IF(Match(L36,IMPORTRANGE(""https://docs.google.com/spreadsheets/d/1HbfCXhSXbtTODKKY1MOFwJccyhgDKD0J9sO1k5l_6lM/edit?resourcekey=&gid=1616384832#gid=1616384832"",""Form Responses 1!E2:E143""),0),1), 0)"),0.0) -> 0
A37: 45917.662 | B37: braden.fong@warriorlife.net | C37: Braden | D37: Fong | E37: G107 | F37: Novice (1st year or 2nd years who haven't placed top 10 (SCDC) or top 3 (SVCDC)) | G37: Melody | H37: Elaine and Evelin | K37: Jonathan Cheng | L37: jonathan.cheng@warriorlife.net | M37: Elaine Wang | N37: E | O37: 4th Year | P37: 7 | Q37: PSE | R37: =IF(COUNTIF(B$2:B$149,L37)=0,0,1) -> 0 | S37: =IF(COUNTIF(B$150:B$274,L37)=0,0,1) -> 1 | T37: =IF(COUNTIF(B$275:B$401,L37)=0,0,1) -> 0 | U37: =IFERROR(__xludf.DUMMYFUNCTION("IFERROR(IF(Match(L37,IMPORTRANGE(""https://docs.google.com/spreadsheets/d/1CAXKDiOnZb21bZOY_nacH9xI9AiD-nH8ZZQAwYKkVC0/edit?usp=drivesdk"",""Completed Exams!A1:A135""),0),1), 0)"),0.0) -> 0 | V37: =IF(COUNTIF(B$416:B$535,L37)=0,0,1) -> 0 | W37: =IF(COUNTIF(B$535:B$602,L37)=0,0,1) -> 0 | X37: =IF(COUNTIF(B$603:B$725,L37)=0,0,1) -> 0 | Y37: =IF(COUNTIF(B$725:B$844,L37)=0,0,1) -> 1 | Z37: =IF(COUNTIF(B$845:B$969,L37)=0,0,1) -> 0 | AA37: 0.5 | AB37: =IFERROR(__xludf.DUMMYFUNCTION("IFERROR(IF(Match(L37,IMPORTRANGE(""https://docs.google.com/spreadsheets/d/1n1sT_Q_W3mKmn2Yrd8qcNzuRD4zr4DB9gqARnjQ30B4/edit?gid=1918970062#gid=1918970062"",""Form Responses 1!B2:B49""),0),1), 0)"),0.0) -> 0 | AC37: =IF(COUNTIF(B$1145:B$1305,L37)=0,0,1) -> 0 | AD37: 1 | AE37: =IFERROR(__xludf.DUMMYFUNCTION("IFERROR(IF(Match(L37,IMPORTRANGE(""https://docs.google.com/spreadsheets/d/1hvckjcCpxEuDQDPrBMml_I1kBhYyjrgR8qBKC9QGVUc/edit?resourcekey=&gid=230793720#gid=230793720"",""Form Responses 1!B2:B199""),0),1), 0)"),0.0) -> 0 | AF37: =IFERROR(__xludf.DUMMYFUNCTION("IFERROR(IF(Match(L37,IMPORTRANGE(""https://docs.google.com/spreadsheets/d/1UY0hI2S83Fmafa5P-C1LM9yqe4v4qIKTnVy_CzLzRPs/edit?resourcekey=&gid=1583835601#gid=1583835601"",""Form Responses 1!B2:B194""),0),1), 0)"),0.0) -> 0 | AG37: =IFERROR(__xludf.DUMMYFUNCTION("IFERROR(IF(Match(L37,IMPORTRANGE(""https://docs.google.com/spreadsheets/d/1hO4mQ22n6cudUygJ2ss_JeJdm2Ua_7hJl_79lWWEtic/edit?resourcekey=&gid=2087212010#gid=2087212010"",""Form Responses 1!B2:B104""),0),1), 0)"),0.0) -> 0 | AH37: =IFERROR(__xludf.DUMMYFUNCTION("IFERROR(IF(Match(L37,IMPORTRANGE(""https://docs.google.com/spreadsheets/d/1HbfCXhSXbtTODKKY1MOFwJccyhgDKD0J9sO1k5l_6lM/edit?resourcekey=&gid=1616384832#gid=1616384832"",""Form Responses 1!E2:E143""),0),1), 0)"),0.0) -> 0
K38: Michael Deng | L38: michael.deng@warriorlife.net | M38: Elaine Wang | N38: E | O38: 4th Year | P38: 7 | Q38: PSE | R38: =IF(COUNTIF(B$2:B$149,L38)=0,0,1) -> 0 | S38: =IF(COUNTIF(B$150:B$274,L38)=0,0,1) -> 1 | T38: =IF(COUNTIF(B$275:B$401,L38)=0,0,1) -> 0 | U38: =IFERROR(__xludf.DUMMYFUNCTION("IFERROR(IF(Match(L38,IMPORTRANGE(""https://docs.google.com/spreadsheets/d/1CAXKDiOnZb21bZOY_nacH9xI9AiD-nH8ZZQAwYKkVC0/edit?usp=drivesdk"",""Completed Exams!A1:A135""),0),1), 0)"),0.0) -> 0 | V38: =IF(COUNTIF(B$416:B$535,L38)=0,0,1) -> 0 | W38: =IF(COUNTIF(B$535:B$602,L38)=0,0,1) -> 0 | X38: =IF(COUNTIF(B$603:B$725,L38)=0,0,1) -> 0 | Y38: =IF(COUNTIF(B$725:B$844,L38)=0,0,1) -> 1 | Z38: =IF(COUNTIF(B$845:B$969,L38)=0,0,1) -> 0 | AA38: 0.5 | AB38: =IFERROR(__xludf.DUMMYFUNCTION("IFERROR(IF(Match(L38,IMPORTRANGE(""https://docs.google.com/spreadsheets/d/1n1sT_Q_W3mKmn2Yrd8qcNzuRD4zr4DB9gqARnjQ30B4/edit?gid=1918970062#gid=1918970062"",""Form Responses 1!B2:B49""),0),1), 0)"),0.0) -> 0 | AC38: =IF(COUNTIF(B$1145:B$1305,L38)=0,0,1) -> 1 | AD38: 1 | AE38: =IFERROR(__xludf.DUMMYFUNCTION("IFERROR(IF(Match(L38,IMPORTRANGE(""https://docs.google.com/spreadsheets/d/1hvckjcCpxEuDQDPrBMml_I1kBhYyjrgR8qBKC9QGVUc/edit?resourcekey=&gid=230793720#gid=230793720"",""Form Responses 1!B2:B199""),0),1), 0)"),0.0) -> 0 | AF38: =IFERROR(__xludf.DUMMYFUNCTION("IFERROR(IF(Match(L38,IMPORTRANGE(""https://docs.google.com/spreadsheets/d/1UY0hI2S83Fmafa5P-C1LM9yqe4v4qIKTnVy_CzLzRPs/edit?resourcekey=&gid=1583835601#gid=1583835601"",""Form Responses 1!B2:B194""),0),1), 0)"),0.0) -> 0 | AG38: =IFERROR(__xludf.DUMMYFUNCTION("IFERROR(IF(Match(L38,IMPORTRANGE(""https://docs.google.com/spreadsheets/d/1hO4mQ22n6cudUygJ2ss_JeJdm2Ua_7hJl_79lWWEtic/edit?resourcekey=&gid=2087212010#gid=2087212010"",""Form Responses 1!B2:B104""),0),1), 0)"),0.0) -> 0 | AH38: =IFERROR(__xludf.DUMMYFUNCTION("IFERROR(IF(Match(L38,IMPORTRANGE(""https://docs.google.com/spreadsheets/d/1HbfCXhSXbtTODKKY1MOFwJccyhgDKD0J9sO1k5l_6lM/edit?resourcekey=&gid=1616384832#gid=1616384832"",""Form Responses 1!E2:E143""),0),1), 0)"),0.0) -> 0
A39: 45917.662 | B39: maahir.satwani@warriorlife.net | C39: Maahir | D39: Satwani | E39: G107 | F39: Novice (1st year or 2nd years who haven't placed top 10 (SCDC) or top 3 (SVCDC)) | G39: Ayden Wang | H39: Evelyn, Elaine | K39: Julia Li | L39: julia.li@warriorlife.net | M39: Elizabeth Huang | N39: E | O39: 2nd Year | P39: 8 | Q39: SEOR | R39: =IF(COUNTIF(B$2:B$149,L39)=0,0,1) -> 1 | S39: =IF(COUNTIF(B$150:B$274,L39)=0,0,1) -> 1 | T39: =IF(COUNTIF(B$275:B$401,L39)=0,0,1) -> 0 | U39: 1 | V39: =IF(COUNTIF(B$416:B$535,L39)=0,0,1) -> 1 | W39: =IF(COUNTIF(B$535:B$602,L39)=0,0,1) -> 1 | X39: =IF(COUNTIF(B$603:B$725,L39)=0,0,1) -> 0 | Y39: =IF(COUNTIF(B$725:B$844,L39)=0,0,1) -> 0 | Z39: 0.5 | AA39: =IF(COUNTIF(B$971:B$1124,L39)=0,0,1) -> 1 | AB39: =IFERROR(__xludf.DUMMYFUNCTION("IFERROR(IF(Match(L39,IMPORTRANGE(""https://docs.google.com/spreadsheets/d/1n1sT_Q_W3mKmn2Yrd8qcNzuRD4zr4DB9gqARnjQ30B4/edit?gid=1918970062#gid=1918970062"",""Form Responses 1!B2:B49""),0),1), 0)"),0.0) -> 0 | AC39: =IF(COUNTIF(B$1145:B$1305,L39)=0,0,1) -> 1 | AD39: 0 | AE39: =IFERROR(__xludf.DUMMYFUNCTION("IFERROR(IF(Match(L39,IMPORTRANGE(""https://docs.google.com/spreadsheets/d/1hvckjcCpxEuDQDPrBMml_I1kBhYyjrgR8qBKC9QGVUc/edit?resourcekey=&gid=230793720#gid=230793720"",""Form Responses 1!B2:B199""),0),1), 0)"),0.0) -> 0 | AF39: =IFERROR(__xludf.DUMMYFUNCTION("IFERROR(IF(Match(L39,IMPORTRANGE(""https://docs.google.com/spreadsheets/d/1UY0hI2S83Fmafa5P-C1LM9yqe4v4qIKTnVy_CzLzRPs/edit?resourcekey=&gid=1583835601#gid=1583835601"",""Form Responses 1!B2:B194""),0),1), 0)"),0.0) -> 0 | AG39: =IFERROR(__xludf.DUMMYFUNCTION("IFERROR(IF(Match(L39,IMPORTRANGE(""https://docs.google.com/spreadsheets/d/1hO4mQ22n6cudUygJ2ss_JeJdm2Ua_7hJl_79lWWEtic/edit?resourcekey=&gid=2087212010#gid=2087212010"",""Form Responses 1!B2:B104""),0),1), 0)"),0.0) -> 0 | AH39: =IFERROR(__xludf.DUMMYFUNCTION("IFERROR(IF(Match(L39,IMPORTRANGE(""https://docs.google.com/spreadsheets/d/1HbfCXhSXbtTODKKY1MOFwJccyhgDKD0J9sO1k5l_6lM/edit?resourcekey=&gid=1616384832#gid=1616384832"",""Form Responses 1!E2:E143""),0),1), 0)"),0.0) -> 0
A40: 45917.662 | B40: milla.lim@warriorlife.net | C40: Milla | D40: Lim | E40: G107 | F40: Novice (1st year or 2nd years who haven't placed top 10 (SCDC) or top 3 (SVCDC)) | G40: Saron | H40: Evelyn, Elaine | K40: Tiffany Zhang | L40: tiffany.zhang@warriorlife.net | M40: Elizabeth Huang | N40: E | O40: 2nd Year | P40: 8 | Q40: SEOR | R40: =IF(COUNTIF(B$2:B$149,L40)=0,0,1) -> 0 | S40: =IF(COUNTIF(B$150:B$274,L40)=0,0,1) -> 0 | T40: =IF(COUNTIF(B$275:B$401,L40)=0,0,1) -> 0 | U40: 1 | V40: =IF(COUNTIF(B$416:B$535,L40)=0,0,1) -> 1 | W40: =IF(COUNTIF(B$535:B$602,L40)=0,0,1) -> 1 | X40: =IF(COUNTIF(B$603:B$725,L40)=0,0,1) -> 0 | Y40: =IF(COUNTIF(B$725:B$844,L40)=0,0,1) -> 0 | Z40: =IF(COUNTIF(B$845:B$969,L40)=0,0,1) -> 0 | AA40: =IF(COUNTIF(B$971:B$1124,L40)=0,0,1) -> 1 | AB40: =IFERROR(__xludf.DUMMYFUNCTION("IFERROR(IF(Match(L40,IMPORTRANGE(""https://docs.google.com/spreadsheets/d/1n1sT_Q_W3mKmn2Yrd8qcNzuRD4zr4DB9gqARnjQ30B4/edit?gid=1918970062#gid=1918970062"",""Form Responses 1!B2:B49""),0),1), 0)"),0.0) -> 0 | AC40: =IF(COUNTIF(B$1145:B$1305,L40)=0,0,1) -> 1 | AD40: 0 | AE40: =IFERROR(__xludf.DUMMYFUNCTION("IFERROR(IF(Match(L40,IMPORTRANGE(""https://docs.google.com/spreadsheets/d/1hvckjcCpxEuDQDPrBMml_I1kBhYyjrgR8qBKC9QGVUc/edit?resourcekey=&gid=230793720#gid=230793720"",""Form Responses 1!B2:B199""),0),1), 0)"),0.0) -> 0 | AF40: =IFERROR(__xludf.DUMMYFUNCTION("IFERROR(IF(Match(L40,IMPORTRANGE(""https://docs.google.com/spreadsheets/d/1UY0hI2S83Fmafa5P-C1LM9yqe4v4qIKTnVy_CzLzRPs/edit?resourcekey=&gid=1583835601#gid=1583835601"",""Form Responses 1!B2:B194""),0),1), 0)"),0.0) -> 0 | AG40: =IFERROR(__xludf.DUMMYFUNCTION("IFERROR(IF(Match(L40,IMPORTRANGE(""https://docs.google.com/spreadsheets/d/1hO4mQ22n6cudUygJ2ss_JeJdm2Ua_7hJl_79lWWEtic/edit?resourcekey=&gid=2087212010#gid=2087212010"",""Form Responses 1!B2:B104""),0),1), 0)"),0.0) -> 0 | AH40: =IFERROR(__xludf.DUMMYFUNCTION("IFERROR(IF(Match(L40,IMPORTRANGE(""https://docs.google.com/spreadsheets/d/1HbfCXhSXbtTODKKY1MOFwJccyhgDKD0J9sO1k5l_6lM/edit?resourcekey=&gid=1616384832#gid=1616384832"",""Form Responses 1!E2:E143""),0),1), 0)"),0.0) -> 0
A41: 45917.662 | B41: ashley.lai@warriorlife.net | C41: Ashley | D41: Lai | E41: G107 | F41: Novice (1st year or 2nd years who haven't placed top 10 (SCDC) or top 3 (SVCDC)) | G41: Grace Xu | H41: Evelyn, Elaine | K41: Jamie Jang | L41: woobin.jang@warriorlife.net | M41: Elizabeth Huang | N41: N | O41: 2nd Year | P41: 8 | Q41: IMCP | R41: =IF(COUNTIF(B$2:B$149,L41)=0,0,1) -> 1 | S41: =IF(COUNTIF(B$150:B$274,L41)=0,0,1) -> 1 | T41: =IF(COUNTIF(B$275:B$401,L41)=0,0,1) -> 1 | U41: =IFERROR(__xludf.DUMMYFUNCTION("IFERROR(IF(Match(L41,IMPORTRANGE(""https://docs.google.com/spreadsheets/d/1CAXKDiOnZb21bZOY_nacH9xI9AiD-nH8ZZQAwYKkVC0/edit?usp=drivesdk"",""Completed Exams!A1:A135""),0),1), 0)"),0.0) -> 0 | V41: =IF(COUNTIF(B$416:B$535,L41)=0,0,1) -> 1 | W41: =IF(COUNTIF(B$535:B$602,L41)=0,0,1) -> 1 | X41: =IF(COUNTIF(B$603:B$725,L41)=0,0,1) -> 1 | Y41: =IF(COUNTIF(B$725:B$844,L41)=0,0,1) -> 0 | Z41: =IF(COUNTIF(B$845:B$969,L41)=0,0,1) -> 1 | AA41: =IF(COUNTIF(B$971:B$1124,L41)=0,0,1) -> 1 | AB41: 1 | AC41: =IF(COUNTIF(B$1145:B$1305,L41)=0,0,1) -> 1 | AD41: 0 | AE41: =IFERROR(__xludf.DUMMYFUNCTION("IFERROR(IF(Match(L41,IMPORTRANGE(""https://docs.google.com/spreadsheets/d/1hvckjcCpxEuDQDPrBMml_I1kBhYyjrgR8qBKC9QGVUc/edit?resourcekey=&gid=230793720#gid=230793720"",""Form Responses 1!B2:B199""),0),1), 0)"),0.0) -> 0 | AF41: =IFERROR(__xludf.DUMMYFUNCTION("IFERROR(IF(Match(L41,IMPORTRANGE(""https://docs.google.com/spreadsheets/d/1UY0hI2S83Fmafa5P-C1LM9yqe4v4qIKTnVy_CzLzRPs/edit?resourcekey=&gid=1583835601#gid=1583835601"",""Form Responses 1!B2:B194""),0),1), 0)"),0.0) -> 0 | AG41: =IFERROR(__xludf.DUMMYFUNCTION("IFERROR(IF(Match(L41,IMPORTRANGE(""https://docs.google.com/spreadsheets/d/1hO4mQ22n6cudUygJ2ss_JeJdm2Ua_7hJl_79lWWEtic/edit?resourcekey=&gid=2087212010#gid=2087212010"",""Form Responses 1!B2:B104""),0),1), 0)"),0.0) -> 0 | AH41: =IFERROR(__xludf.DUMMYFUNCTION("IFERROR(IF(Match(L41,IMPORTRANGE(""https://docs.google.com/spreadsheets/d/1HbfCXhSXbtTODKKY1MOFwJccyhgDKD0J9sO1k5l_6lM/edit?resourcekey=&gid=1616384832#gid=1616384832"",""Form Responses 1!E2:E143""),0),1), 0)"),0.0) -> 0
A42: 45917.662 | B42: grace.frieder@warriorlife.net | C42: Grace | D42: Frieder | E42: G107 | F42: Novice (1st year or 2nd years who haven't placed top 10 (SCDC) or top 3 (SVCDC)) | G42: Elaine Wang | H42: Elaine and Evelyn | K42: Hanna Handy | L42: hanna.handy@warriorlife.net | M42: Elizabeth Huang | N42: N | O42: 1st Year | P42: 8 | Q42: IMCP | R42: =IF(COUNTIF(B$2:B$149,L42)=0,0,1) -> 1 | S42: =IF(COUNTIF(B$150:B$274,L42)=0,0,1) -> 1 | T42: =IF(COUNTIF(B$275:B$401,L42)=0,0,1) -> 1 | U42: =IFERROR(__xludf.DUMMYFUNCTION("IFERROR(IF(Match(L42,IMPORTRANGE(""https://docs.google.com/spreadsheets/d/1CAXKDiOnZb21bZOY_nacH9xI9AiD-nH8ZZQAwYKkVC0/edit?usp=drivesdk"",""Completed Exams!A1:A135""),0),1), 0)"),0.0) -> 0 | V42: =IF(COUNTIF(B$416:B$535,L42)=0,0,1) -> 1 | W42: =IF(COUNTIF(B$535:B$602,L42)=0,0,1) -> 1 | X42: =IF(COUNTIF(B$603:B$725,L42)=0,0,1) -> 1 | Y42: =IF(COUNTIF(B$725:B$844,L42)=0,0,1) -> 1 | Z42: =IF(COUNTIF(B$845:B$969,L42)=0,0,1) -> 1 | AA42: =IF(COUNTIF(B$971:B$1124,L42)=0,0,1) -> 1 | AB42: =IFERROR(__xludf.DUMMYFUNCTION("IFERROR(IF(Match(L42,IMPORTRANGE(""https://docs.google.com/spreadsheets/d/1n1sT_Q_W3mKmn2Yrd8qcNzuRD4zr4DB9gqARnjQ30B4/edit?gid=1918970062#gid=1918970062"",""Form Responses 1!B2:B49""),0),1), 0)"),0.0) -> 0 | AC42: =IF(COUNTIF(B$1145:B$1305,L42)=0,0,1) -> 1 | AD42: 1 | AE42: =IFERROR(__xludf.DUMMYFUNCTION("IFERROR(IF(Match(L42,IMPORTRANGE(""https://docs.google.com/spreadsheets/d/1hvckjcCpxEuDQDPrBMml_I1kBhYyjrgR8qBKC9QGVUc/edit?resourcekey=&gid=230793720#gid=230793720"",""Form Responses 1!B2:B199""),0),1), 0)"),0.0) -> 0 | AF42: =IFERROR(__xludf.DUMMYFUNCTION("IFERROR(IF(Match(L42,IMPORTRANGE(""https://docs.google.com/spreadsheets/d/1UY0hI2S83Fmafa5P-C1LM9yqe4v4qIKTnVy_CzLzRPs/edit?resourcekey=&gid=1583835601#gid=1583835601"",""Form Responses 1!B2:B194""),0),1), 0)"),0.0) -> 0 | AG42: =IFERROR(__xludf.DUMMYFUNCTION("IFERROR(IF(Match(L42,IMPORTRANGE(""https://docs.google.com/spreadsheets/d/1hO4mQ22n6cudUygJ2ss_JeJdm2Ua_7hJl_79lWWEtic/edit?resourcekey=&gid=2087212010#gid=2087212010"",""Form Responses 1!B2:B104""),0),1), 0)"),0.0) -> 0 | AH42: =IFERROR(__xludf.DUMMYFUNCTION("IFERROR(IF(Match(L42,IMPORTRANGE(""https://docs.google.com/spreadsheets/d/1HbfCXhSXbtTODKKY1MOFwJccyhgDKD0J9sO1k5l_6lM/edit?resourcekey=&gid=1616384832#gid=1616384832"",""Form Responses 1!E2:E143""),0),1), 0)"),0.0) -> 0
A43: 45917.662 | B43: nathan.pham@warriorlife.net | C43: Nathan | D43: Pham | E43: G107 | F43: Experienced (2nd years who have placed top 10 (SCDC) or top 3 (SVCDC) or 3rd and 4th years) | G43: Melody | H43: Elaine and Evelyn | K43: Jennaly Fangonilo | L43: jennaly.fangonilo@warriorlife.net | M43: Elizabeth Huang | N43: E | O43: 3rd Year | P43: 8 | Q43: IMCP | R43: =IF(COUNTIF(B$2:B$149,L43)=0,0,1) -> 1 | S43: =IF(COUNTIF(B$150:B$274,L43)=0,0,1) -> 1 | T43: =IF(COUNTIF(B$275:B$401,L43)=0,0,1) -> 0 | U43: 1 | V43: =IF(COUNTIF(B$416:B$535,L43)=0,0,1) -> 1 | W43: =IF(COUNTIF(B$535:B$602,L43)=0,0,1) -> 0 | X43: =IF(COUNTIF(B$603:B$725,L43)=0,0,1) -> 1 | Y43: =IF(COUNTIF(B$725:B$844,L43)=0,0,1) -> 1 | Z43: =IF(COUNTIF(B$845:B$969,L43)=0,0,1) -> 0 | AA43: 0.5 | AB43: =IFERROR(__xludf.DUMMYFUNCTION("IFERROR(IF(Match(L43,IMPORTRANGE(""https://docs.google.com/spreadsheets/d/1n1sT_Q_W3mKmn2Yrd8qcNzuRD4zr4DB9gqARnjQ30B4/edit?gid=1918970062#gid=1918970062"",""Form Responses 1!B2:B49""),0),1), 0)"),0.0) -> 0 | AC43: =IF(COUNTIF(B$1145:B$1305,L43)=0,0,1) -> 1 | AD43: 0 | AE43: =IFERROR(__xludf.DUMMYFUNCTION("IFERROR(IF(Match(L43,IMPORTRANGE(""https://docs.google.com/spreadsheets/d/1hvckjcCpxEuDQDPrBMml_I1kBhYyjrgR8qBKC9QGVUc/edit?resourcekey=&gid=230793720#gid=230793720"",""Form Responses 1!B2:B199""),0),1), 0)"),0.0) -> 0 | AF43: =IFERROR(__xludf.DUMMYFUNCTION("IFERROR(IF(Match(L43,IMPORTRANGE(""https://docs.google.com/spreadsheets/d/1UY0hI2S83Fmafa5P-C1LM9yqe4v4qIKTnVy_CzLzRPs/edit?resourcekey=&gid=1583835601#gid=1583835601"",""Form Responses 1!B2:B194""),0),1), 0)"),0.0) -> 0 | AG43: =IFERROR(__xludf.DUMMYFUNCTION("IFERROR(IF(Match(L43,IMPORTRANGE(""https://docs.google.com/spreadsheets/d/1hO4mQ22n6cudUygJ2ss_JeJdm2Ua_7hJl_79lWWEtic/edit?resourcekey=&gid=2087212010#gid=2087212010"",""Form Responses 1!B2:B104""),0),1), 0)"),0.0) -> 0 | AH43: =IFERROR(__xludf.DUMMYFUNCTION("IFERROR(IF(Match(L43,IMPORTRANGE(""https://docs.google.com/spreadsheets/d/1HbfCXhSXbtTODKKY1MOFwJccyhgDKD0J9sO1k5l_6lM/edit?resourcekey=&gid=1616384832#gid=1616384832"",""Form Responses 1!E2:E143""),0),1), 0)"),0.0) -> 0
A44: 45917.662 | B44: riyana.baldua@warriorlife.net | C44: Riyana | D44: Baldua | E44: G106 | F44: Novice (1st year or 2nd years who haven't placed top 10 (SCDC) or top 3 (SVCDC)) | G44: Ayden | H44: Elaine and Evebly | K44: Gabby Lynch | L44: gabriele.lynch@warriorlife.net | M44: Elizabeth Huang | N44: N | O44: 1st Year | P44: 8 | Q44: IMCP | R44: =IF(COUNTIF(B$2:B$149,L44)=0,0,1) -> 1 | S44: =IF(COUNTIF(B$150:B$274,L44)=0,0,1) -> 1 | T44: =IF(COUNTIF(B$275:B$401,L44)=0,0,1) -> 1 | U44: =IFERROR(__xludf.DUMMYFUNCTION("IFERROR(IF(Match(L44,IMPORTRANGE(""https://docs.google.com/spreadsheets/d/1CAXKDiOnZb21bZOY_nacH9xI9AiD-nH8ZZQAwYKkVC0/edit?usp=drivesdk"",""Completed Exams!A1:A135""),0),1), 0)"),0.0) -> 0 | V44: =IF(COUNTIF(B$416:B$535,L44)=0,0,1) -> 0 | W44: =IF(COUNTIF(B$535:B$602,L44)=0,0,1) -> 0 | X44: =IF(COUNTIF(B$603:B$725,L44)=0,0,1) -> 1 | Y44: =IF(COUNTIF(B$725:B$844,L44)=0,0,1) -> 0 | Z44: =IF(COUNTIF(B$845:B$969,L44)=0,0,1) -> 1 | AA44: =IF(COUNTIF(B$971:B$1124,L44)=0,0,1) -> 1 | AB44: 1 | AC44: =IF(COUNTIF(B$1145:B$1305,L44)=0,0,1) -> 1 | AD44: 1 | AE44: =IFERROR(__xludf.DUMMYFUNCTION("IFERROR(IF(Match(L44,IMPORTRANGE(""https://docs.google.com/spreadsheets/d/1hvckjcCpxEuDQDPrBMml_I1kBhYyjrgR8qBKC9QGVUc/edit?resourcekey=&gid=230793720#gid=230793720"",""Form Responses 1!B2:B199""),0),1), 0)"),0.0) -> 0 | AF44: =IFERROR(__xludf.DUMMYFUNCTION("IFERROR(IF(Match(L44,IMPORTRANGE(""https://docs.google.com/spreadsheets/d/1UY0hI2S83Fmafa5P-C1LM9yqe4v4qIKTnVy_CzLzRPs/edit?resourcekey=&gid=1583835601#gid=1583835601"",""Form Responses 1!B2:B194""),0),1), 0)"),0.0) -> 0 | AG44: =IFERROR(__xludf.DUMMYFUNCTION("IFERROR(IF(Match(L44,IMPORTRANGE(""https://docs.google.com/spreadsheets/d/1hO4mQ22n6cudUygJ2ss_JeJdm2Ua_7hJl_79lWWEtic/edit?resourcekey=&gid=2087212010#gid=2087212010"",""Form Responses 1!B2:B104""),0),1), 0)"),0.0) -> 0 | AH44: =IFERROR(__xludf.DUMMYFUNCTION("IFERROR(IF(Match(L44,IMPORTRANGE(""https://docs.google.com/spreadsheets/d/1HbfCXhSXbtTODKKY1MOFwJccyhgDKD0J9sO1k5l_6lM/edit?resourcekey=&gid=1616384832#gid=1616384832"",""Form Responses 1!E2:E143""),0),1), 0)"),0.0) -> 0
A45: 45917.662 | B45: olivia.kang@warriorlife.net | C45: Olivia | D45: Kang | E45: G107 | F45: Novice (1st year or 2nd years who haven't placed top 10 (SCDC) or top 3 (SVCDC)) | G45: Hannah??? | H45: Evelyn | K45: Joey Zhu | L45: joey.zhu@warriorlife.net | M45: Elizabeth Huang | N45: N | O45: 1st Year | P45: 8 | Q45: IMCP | R45: =IF(COUNTIF(B$2:B$149,L45)=0,0,1) -> 1 | S45: =IF(COUNTIF(B$150:B$274,L45)=0,0,1) -> 1 | T45: =IF(COUNTIF(B$275:B$401,L45)=0,0,1) -> 1 | U45: =IFERROR(__xludf.DUMMYFUNCTION("IFERROR(IF(Match(L45,IMPORTRANGE(""https://docs.google.com/spreadsheets/d/1CAXKDiOnZb21bZOY_nacH9xI9AiD-nH8ZZQAwYKkVC0/edit?usp=drivesdk"",""Completed Exams!A1:A135""),0),1), 0)"),0.0) -> 0 | V45: =IF(COUNTIF(B$416:B$535,L45)=0,0,1) -> 0 | W45: 1 | X45: =IF(COUNTIF(B$603:B$725,L45)=0,0,1) -> 1 | Y45: =IF(COUNTIF(B$725:B$844,L45)=0,0,1) -> 1 | Z45: =IF(COUNTIF(B$845:B$969,L45)=0,0,1) -> 0 | AA45: =IF(COUNTIF(B$971:B$1124,L45)=0,0,1) -> 1 | AB45: =IFERROR(__xludf.DUMMYFUNCTION("IFERROR(IF(Match(L45,IMPORTRANGE(""https://docs.google.com/spreadsheets/d/1n1sT_Q_W3mKmn2Yrd8qcNzuRD4zr4DB9gqARnjQ30B4/edit?gid=1918970062#gid=1918970062"",""Form Responses 1!B2:B49""),0),1), 0)"),0.0) -> 0 | AC45: =IF(COUNTIF(B$1145:B$1305,L45)=0,0,1) -> 1 | AD45: 0 | AE45: =IFERROR(__xludf.DUMMYFUNCTION("IFERROR(IF(Match(L45,IMPORTRANGE(""https://docs.google.com/spreadsheets/d/1hvckjcCpxEuDQDPrBMml_I1kBhYyjrgR8qBKC9QGVUc/edit?resourcekey=&gid=230793720#gid=230793720"",""Form Responses 1!B2:B199""),0),1), 0)"),0.0) -> 0 | AF45: =IFERROR(__xludf.DUMMYFUNCTION("IFERROR(IF(Match(L45,IMPORTRANGE(""https://docs.google.com/spreadsheets/d/1UY0hI2S83Fmafa5P-C1LM9yqe4v4qIKTnVy_CzLzRPs/edit?resourcekey=&gid=1583835601#gid=1583835601"",""Form Responses 1!B2:B194""),0),1), 0)"),0.0) -> 0 | AG45: =IFERROR(__xludf.DUMMYFUNCTION("IFERROR(IF(Match(L45,IMPORTRANGE(""https://docs.google.com/spreadsheets/d/1hO4mQ22n6cudUygJ2ss_JeJdm2Ua_7hJl_79lWWEtic/edit?resourcekey=&gid=2087212010#gid=2087212010"",""Form Responses 1!B2:B104""),0),1), 0)"),0.0) -> 0 | AH45: =IFERROR(__xludf.DUMMYFUNCTION("IFERROR(IF(Match(L45,IMPORTRANGE(""https://docs.google.com/spreadsheets/d/1HbfCXhSXbtTODKKY1MOFwJccyhgDKD0J9sO1k5l_6lM/edit?resourcekey=&gid=1616384832#gid=1616384832"",""Form Responses 1!E2:E143""),0),1), 0)"),0.0) -> 0
A46: 45917.662 | B46: sofia.choo@warriorlife.net | C46: Sofia | D46: Choo | E46: G107 | F46: Novice (1st year or 2nd years who haven't placed top 10 (SCDC) or top 3 (SVCDC)) | G46: saron | H46: Evelyn and Elaine | K46: Nathaniel Kommu | L46: nathaniel.kommu@warriorlife.net | M46: Emily Tang | N46: N | O46: 2nd Year | P46: 9 | Q46: FCE | R46: =IF(COUNTIF(B$2:B$149,L46)=0,0,1) -> 1 | S46: =IF(COUNTIF(B$150:B$274,L46)=0,0,1) -> 0 | T46: =IF(COUNTIF(B$275:B$401,L46)=0,0,1) -> 1 | U46: =IFERROR(__xludf.DUMMYFUNCTION("IFERROR(IF(Match(L46,IMPORTRANGE(""https://docs.google.com/spreadsheets/d/1CAXKDiOnZb21bZOY_nacH9xI9AiD-nH8ZZQAwYKkVC0/edit?usp=drivesdk"",""Completed Exams!A1:A135""),0),1), 0)"),0.0) -> 0 | V46: =IF(COUNTIF(B$416:B$535,L46)=0,0,1) -> 1 | W46: 1 | X46: =IF(COUNTIF(B$603:B$725,L46)=0,0,1) -> 0 | Y46: =IF(COUNTIF(B$725:B$844,L46)=0,0,1) -> 1 | Z46: =IF(COUNTIF(B$845:B$969,L46)=0,0,1) -> 1 | AA46: =IF(COUNTIF(B$971:B$1124,L46)=0,0,1) -> 1 | AB46: =IFERROR(__xludf.DUMMYFUNCTION("IFERROR(IF(Match(L46,IMPORTRANGE(""https://docs.google.com/spreadsheets/d/1n1sT_Q_W3mKmn2Yrd8qcNzuRD4zr4DB9gqARnjQ30B4/edit?gid=1918970062#gid=1918970062"",""Form Responses 1!B2:B49""),0),1), 0)"),0.0) -> 0 | AC46: =IF(COUNTIF(B$1145:B$1305,L46)=0,0,1) -> 1 | AD46: 1 | AE46: =IFERROR(__xludf.DUMMYFUNCTION("IFERROR(IF(Match(L46,IMPORTRANGE(""https://docs.google.com/spreadsheets/d/1hvckjcCpxEuDQDPrBMml_I1kBhYyjrgR8qBKC9QGVUc/edit?resourcekey=&gid=230793720#gid=230793720"",""Form Responses 1!B2:B199""),0),1), 0)"),0.0) -> 0 | AF46: =IFERROR(__xludf.DUMMYFUNCTION("IFERROR(IF(Match(L46,IMPORTRANGE(""https://docs.google.com/spreadsheets/d/1UY0hI2S83Fmafa5P-C1LM9yqe4v4qIKTnVy_CzLzRPs/edit?resourcekey=&gid=1583835601#gid=1583835601"",""Form Responses 1!B2:B194""),0),1), 0)"),0.0) -> 0 | AG46: =IFERROR(__xludf.DUMMYFUNCTION("IFERROR(IF(Match(L46,IMPORTRANGE(""https://docs.google.com/spreadsheets/d/1hO4mQ22n6cudUygJ2ss_JeJdm2Ua_7hJl_79lWWEtic/edit?resourcekey=&gid=2087212010#gid=2087212010"",""Form Responses 1!B2:B104""),0),1), 0)"),0.0) -> 0 | AH46: =IFERROR(__xludf.DUMMYFUNCTION("IFERROR(IF(Match(L46,IMPORTRANGE(""https://docs.google.com/spreadsheets/d/1HbfCXhSXbtTODKKY1MOFwJccyhgDKD0J9sO1k5l_6lM/edit?resourcekey=&gid=1616384832#gid=1616384832"",""Form Responses 1!E2:E143""),0),1), 0)"),0.0) -> 0
A47: 45917.663 | B47: samuel.xiao@warriorlife.net | C47: Samuel | D47: Xiao | E47: G107 | F47: Experienced (2nd years who have placed top 10 (SCDC) or top 3 (SVCDC) or 3rd and 4th years) | G47: ayden wang | H47: elaine and evelyn | K47: Jessica Ma | L47: jessica.ma@warriorlife.net | M47: Emily Tang | N47: N | O47: 2nd Year | P47: 9 | Q47: HTPS | R47: =IF(COUNTIF(B$2:B$149,L47)=0,0,1) -> 1 | S47: =IF(COUNTIF(B$150:B$274,L47)=0,0,1) -> 1 | T47: =IF(COUNTIF(B$275:B$401,L47)=0,0,1) -> 1 | U47: =IFERROR(__xludf.DUMMYFUNCTION("IFERROR(IF(Match(L47,IMPORTRANGE(""https://docs.google.com/spreadsheets/d/1CAXKDiOnZb21bZOY_nacH9xI9AiD-nH8ZZQAwYKkVC0/edit?usp=drivesdk"",""Completed Exams!A1:A135""),0),1), 0)"),0.0) -> 0 | V47: =IF(COUNTIF(B$416:B$535,L47)=0,0,1) -> 1 | W47: =IF(COUNTIF(B$535:B$602,L47)=0,0,1) -> 1 | X47: =IF(COUNTIF(B$603:B$725,L47)=0,0,1) -> 1 | Y47: =IF(COUNTIF(B$725:B$844,L47)=0,0,1) -> 1 | Z47: =IF(COUNTIF(B$845:B$969,L47)=0,0,1) -> 1 | AA47: =IF(COUNTIF(B$971:B$1124,L47)=0,0,1) -> 1 | AB47: =IFERROR(__xludf.DUMMYFUNCTION("IFERROR(IF(Match(L47,IMPORTRANGE(""https://docs.google.com/spreadsheets/d/1n1sT_Q_W3mKmn2Yrd8qcNzuRD4zr4DB9gqARnjQ30B4/edit?gid=1918970062#gid=1918970062"",""Form Responses 1!B2:B49""),0),1), 0)"),0.0) -> 0 | AC47: =IF(COUNTIF(B$1145:B$1305,L47)=0,0,1) -> 1 | AD47: 1 | AE47: =IFERROR(__xludf.DUMMYFUNCTION("IFERROR(IF(Match(L47,IMPORTRANGE(""https://docs.google.com/spreadsheets/d/1hvckjcCpxEuDQDPrBMml_I1kBhYyjrgR8qBKC9QGVUc/edit?resourcekey=&gid=230793720#gid=230793720"",""Form Responses 1!B2:B199""),0),1), 0)"),0.0) -> 0 | AF47: =IFERROR(__xludf.DUMMYFUNCTION("IFERROR(IF(Match(L47,IMPORTRANGE(""https://docs.google.com/spreadsheets/d/1UY0hI2S83Fmafa5P-C1LM9yqe4v4qIKTnVy_CzLzRPs/edit?resourcekey=&gid=1583835601#gid=1583835601"",""Form Responses 1!B2:B194""),0),1), 0)"),0.0) -> 0 | AG47: =IFERROR(__xludf.DUMMYFUNCTION("IFERROR(IF(Match(L47,IMPORTRANGE(""https://docs.google.com/spreadsheets/d/1hO4mQ22n6cudUygJ2ss_JeJdm2Ua_7hJl_79lWWEtic/edit?resourcekey=&gid=2087212010#gid=2087212010"",""Form Responses 1!B2:B104""),0),1), 0)"),0.0) -> 0 | AH47: =IFERROR(__xludf.DUMMYFUNCTION("IFERROR(IF(Match(L47,IMPORTRANGE(""https://docs.google.com/spreadsheets/d/1HbfCXhSXbtTODKKY1MOFwJccyhgDKD0J9sO1k5l_6lM/edit?resourcekey=&gid=1616384832#gid=1616384832"",""Form Responses 1!E2:E143""),0),1), 0)"),0.0) -> 0
A48: 45917.665 | B48: ambery.chang@warriorlife.net | C48: Amber | D48: Chang | E48: G105 | F48: Novice (1st year or 2nd years who haven't placed top 10 (SCDC) or top 3 (SVCDC)) | G48: Aaron Vu | H48: Give one example of a CSR intiative | K48: Kevin Ou | L48: kevin.ou@warriorlife.net | M48: Emily Tang | N48: N | O48: 1st Year | P48: 9 | Q48: IBP | R48: =IF(COUNTIF(B$2:B$149,L48)=0,0,1) -> 1 | S48: =IF(COUNTIF(B$150:B$274,L48)=0,0,1) -> 1 | T48: =IF(COUNTIF(B$275:B$401,L48)=0,0,1) -> 1 | U48: =IFERROR(__xludf.DUMMYFUNCTION("IFERROR(IF(Match(L48,IMPORTRANGE(""https://docs.google.com/spreadsheets/d/1CAXKDiOnZb21bZOY_nacH9xI9AiD-nH8ZZQAwYKkVC0/edit?usp=drivesdk"",""Completed Exams!A1:A135""),0),1), 0)"),0.0) -> 0 | V48: =IF(COUNTIF(B$416:B$535,L48)=0,0,1) -> 1 | W48: =IF(COUNTIF(B$535:B$602,L48)=0,0,1) -> 1 | X48: =IF(COUNTIF(B$603:B$725,L48)=0,0,1) -> 1 | Y48: 0.5 | Z48: =IF(COUNTIF(B$845:B$969,L48)=0,0,1) -> 1 | AA48: =IF(COUNTIF(B$971:B$1124,L48)=0,0,1) -> 1 | AB48: =IFERROR(__xludf.DUMMYFUNCTION("IFERROR(IF(Match(L48,IMPORTRANGE(""https://docs.google.com/spreadsheets/d/1n1sT_Q_W3mKmn2Yrd8qcNzuRD4zr4DB9gqARnjQ30B4/edit?gid=1918970062#gid=1918970062"",""Form Responses 1!B2:B49""),0),1), 0)"),0.0) -> 0 | AC48: =IF(COUNTIF(B$1145:B$1305,L48)=0,0,1) -> 1 | AD48: 1 | AE48: =IFERROR(__xludf.DUMMYFUNCTION("IFERROR(IF(Match(L48,IMPORTRANGE(""https://docs.google.com/spreadsheets/d/1hvckjcCpxEuDQDPrBMml_I1kBhYyjrgR8qBKC9QGVUc/edit?resourcekey=&gid=230793720#gid=230793720"",""Form Responses 1!B2:B199""),0),1), 0)"),0.0) -> 0 | AF48: =IFERROR(__xludf.DUMMYFUNCTION("IFERROR(IF(Match(L48,IMPORTRANGE(""https://docs.google.com/spreadsheets/d/1UY0hI2S83Fmafa5P-C1LM9yqe4v4qIKTnVy_CzLzRPs/edit?resourcekey=&gid=1583835601#gid=1583835601"",""Form Responses 1!B2:B194""),0),1), 0)"),0.0) -> 0 | AG48: =IFERROR(__xludf.DUMMYFUNCTION("IFERROR(IF(Match(L48,IMPORTRANGE(""https://docs.google.com/spreadsheets/d/1hO4mQ22n6cudUygJ2ss_JeJdm2Ua_7hJl_79lWWEtic/edit?resourcekey=&gid=2087212010#gid=2087212010"",""Form Responses 1!B2:B104""),0),1), 0)"),0.0) -> 0 | AH48: =IFERROR(__xludf.DUMMYFUNCTION("IFERROR(IF(Match(L48,IMPORTRANGE(""https://docs.google.com/spreadsheets/d/1HbfCXhSXbtTODKKY1MOFwJccyhgDKD0J9sO1k5l_6lM/edit?resourcekey=&gid=1616384832#gid=1616384832"",""Form Responses 1!E2:E143""),0),1), 0)"),0.0) -> 0
A49: 45917.665 | B49: julia.li@warriorlife.net | C49: Julia | D49: Li | E49: G105 | F49: Experienced (2nd years who have placed top 10 (SCDC) or top 3 (SVCDC) or 3rd and 4th years) | G49: Elizabeth Huang | H49: Sustainable sourcing | K49: Michael Qi | L49: michael.qi@warriorlife.net | M49: Emily Tang | N49: N | O49: 1st Year | P49: 9 | Q49: IBP | R49: =IF(COUNTIF(B$2:B$149,L49)=0,0,1) -> 1 | S49: 0.5 | T49: =IF(COUNTIF(B$275:B$401,L49)=0,0,1) -> 1 | U49: =IFERROR(__xludf.DUMMYFUNCTION("IFERROR(IF(Match(L49,IMPORTRANGE(""https://docs.google.com/spreadsheets/d/1CAXKDiOnZb21bZOY_nacH9xI9AiD-nH8ZZQAwYKkVC0/edit?usp=drivesdk"",""Completed Exams!A1:A135""),0),1), 0)"),0.0) -> 0 | V49: =IF(COUNTIF(B$416:B$535,L49)=0,0,1) -> 0 | W49: =IF(COUNTIF(B$535:B$602,L49)=0,0,1) -> 1 | X49: =IF(COUNTIF(B$603:B$725,L49)=0,0,1) -> 1 | Y49: =IF(COUNTIF(B$725:B$844,L49)=0,0,1) -> 1 | Z49: =IF(COUNTIF(B$845:B$969,L49)=0,0,1) -> 0 | AA49: =IF(COUNTIF(B$971:B$1124,L49)=0,0,1) -> 1 | AB49: =IFERROR(__xludf.DUMMYFUNCTION("IFERROR(IF(Match(L49,IMPORTRANGE(""https://docs.google.com/spreadsheets/d/1n1sT_Q_W3mKmn2Yrd8qcNzuRD4zr4DB9gqARnjQ30B4/edit?gid=1918970062#gid=1918970062"",""Form Responses 1!B2:B49""),0),1), 0)"),0.0) -> 0 | AC49: =IF(COUNTIF(B$1145:B$1305,L49)=0,0,1) -> 1 | AD49: 1 | AE49: =IFERROR(__xludf.DUMMYFUNCTION("IFERROR(IF(Match(L49,IMPORTRANGE(""https://docs.google.com/spreadsheets/d/1hvckjcCpxEuDQDPrBMml_I1kBhYyjrgR8qBKC9QGVUc/edit?resourcekey=&gid=230793720#gid=230793720"",""Form Responses 1!B2:B199""),0),1), 0)"),0.0) -> 0 | AF49: =IFERROR(__xludf.DUMMYFUNCTION("IFERROR(IF(Match(L49,IMPORTRANGE(""https://docs.google.com/spreadsheets/d/1UY0hI2S83Fmafa5P-C1LM9yqe4v4qIKTnVy_CzLzRPs/edit?resourcekey=&gid=1583835601#gid=1583835601"",""Form Responses 1!B2:B194""),0),1), 0)"),0.0) -> 0 | AG49: =IFERROR(__xludf.DUMMYFUNCTION("IFERROR(IF(Match(L49,IMPORTRANGE(""https://docs.google.com/spreadsheets/d/1hO4mQ22n6cudUygJ2ss_JeJdm2Ua_7hJl_79lWWEtic/edit?resourcekey=&gid=2087212010#gid=2087212010"",""Form Responses 1!B2:B104""),0),1), 0)"),0.0) -> 0 | AH49: =IFERROR(__xludf.DUMMYFUNCTION("IFERROR(IF(Match(L49,IMPORTRANGE(""https://docs.google.com/spreadsheets/d/1HbfCXhSXbtTODKKY1MOFwJccyhgDKD0J9sO1k5l_6lM/edit?resourcekey=&gid=1616384832#gid=1616384832"",""Form Responses 1!E2:E143""),0),1), 0)"),0.0) -> 0
A50: 45917.665 | B50: litian.gu@warriorlife.net | C50: Litian | D50: Gu | E50: G106 | F50: Experienced (2nd years who have placed top 10 (SCDC) or top 3 (SVCDC) or 3rd and 4th years) | G50: Evelyn Bai | H50: Community service | K50: Shawn Wang | L50: zixuan.wang@warriorlife.net | M50: Emily Tang | N50: N | O50: 1st Year | P50: 9 | Q50: IBP | R50: =IF(COUNTIF(B$2:B$149,L50)=0,0,1) -> 1 | S50: =IF(COUNTIF(B$150:B$274,L50)=0,0,1) -> 1 | T50: =IF(COUNTIF(B$275:B$401,L50)=0,0,1) -> 1 | U50: =IFERROR(__xludf.DUMMYFUNCTION("IFERROR(IF(Match(L50,IMPORTRANGE(""https://docs.google.com/spreadsheets/d/1CAXKDiOnZb21bZOY_nacH9xI9AiD-nH8ZZQAwYKkVC0/edit?usp=drivesdk"",""Completed Exams!A1:A135""),0),1), 0)"),0.0) -> 0 | V50: =IF(COUNTIF(B$416:B$535,L50)=0,0,1) -> 1 | W50: =IF(COUNTIF(B$535:B$602,L50)=0,0,1) -> 1 | X50: =IF(COUNTIF(B$603:B$725,L50)=0,0,1) -> 1 | Y50: =IF(COUNTIF(B$725:B$844,L50)=0,0,1) -> 1 | Z50: =IF(COUNTIF(B$845:B$969,L50)=0,0,1) -> 1 | AA50: =IF(COUNTIF(B$971:B$1124,L50)=0,0,1) -> 1 | AB50: =IFERROR(__xludf.DUMMYFUNCTION("IFERROR(IF(Match(L50,IMPORTRANGE(""https://docs.google.com/spreadsheets/d/1n1sT_Q_W3mKmn2Yrd8qcNzuRD4zr4DB9gqARnjQ30B4/edit?gid=1918970062#gid=1918970062"",""Form Responses 1!B2:B49""),0),1), 0)"),0.0) -> 0 | AC50: =IF(COUNTIF(B$1145:B$1305,L50)=0,0,1) -> 0 | AD50: 1 | AE50: =IFERROR(__xludf.DUMMYFUNCTION("IFERROR(IF(Match(L50,IMPORTRANGE(""https://docs.google.com/spreadsheets/d/1hvckjcCpxEuDQDPrBMml_I1kBhYyjrgR8qBKC9QGVUc/edit?resourcekey=&gid=230793720#gid=230793720"",""Form Responses 1!B2:B199""),0),1), 0)"),0.0) -> 0 | AF50: =IFERROR(__xludf.DUMMYFUNCTION("IFERROR(IF(Match(L50,IMPORTRANGE(""https://docs.google.com/spreadsheets/d/1UY0hI2S83Fmafa5P-C1LM9yqe4v4qIKTnVy_CzLzRPs/edit?resourcekey=&gid=1583835601#gid=1583835601"",""Form Responses 1!B2:B194""),0),1), 0)"),0.0) -> 0 | AG50: =IFERROR(__xludf.DUMMYFUNCTION("IFERROR(IF(Match(L50,IMPORTRANGE(""https://docs.google.com/spreadsheets/d/1hO4mQ22n6cudUygJ2ss_JeJdm2Ua_7hJl_79lWWEtic/edit?resourcekey=&gid=2087212010#gid=2087212010"",""Form Responses 1!B2:B104""),0),1), 0)"),0.0) -> 0 | AH50: =IFERROR(__xludf.DUMMYFUNCTION("IFERROR(IF(Match(L50,IMPORTRANGE(""https://docs.google.com/spreadsheets/d/1HbfCXhSXbtTODKKY1MOFwJccyhgDKD0J9sO1k5l_6lM/edit?resourcekey=&gid=1616384832#gid=1616384832"",""Form Responses 1!E2:E143""),0),1), 0)"),0.0) -> 0
A51: 45917.665 | B51: james.yu@warriorlife.net | C51: James | D51: Yu | E51: G106 | F51: Novice (1st year or 2nd years who haven't placed top 10 (SCDC) or top 3 (SVCDC)) | G51: Hannah Li | H51: ethical work place | K51: Amanda Lam | L51: yuettung.lam@warriorlife.net | M51: Grace Xu | N51: N | O51: 1st Year | P51: 10 | Q51: EIP | R51: =IF(COUNTIF(B$2:B$149,L51)=0,0,1) -> 1 | S51: =IF(COUNTIF(B$150:B$274,L51)=0,0,1) -> 1 | T51: =IF(COUNTIF(B$275:B$401,L51)=0,0,1) -> 1 | U51: =IFERROR(__xludf.DUMMYFUNCTION("IFERROR(IF(Match(L51,IMPORTRANGE(""https://docs.google.com/spreadsheets/d/1CAXKDiOnZb21bZOY_nacH9xI9AiD-nH8ZZQAwYKkVC0/edit?usp=drivesdk"",""Completed Exams!A1:A135""),0),1), 0)"),0.0) -> 0 | V51: =IF(COUNTIF(B$416:B$535,L51)=0,0,1) -> 1 | W51: 1 | X51: =IF(COUNTIF(B$603:B$725,L51)=0,0,1) -> 1 | Y51: =IF(COUNTIF(B$725:B$844,L51)=0,0,1) -> 1 | Z51: =IF(COUNTIF(B$845:B$969,L51)=0,0,1) -> 1 | AA51: =IF(COUNTIF(B$971:B$1124,L51)=0,0,1) -> 1 | AB51: =IFERROR(__xludf.DUMMYFUNCTION("IFERROR(IF(Match(L51,IMPORTRANGE(""https://docs.google.com/spreadsheets/d/1n1sT_Q_W3mKmn2Yrd8qcNzuRD4zr4DB9gqARnjQ30B4/edit?gid=1918970062#gid=1918970062"",""Form Responses 1!B2:B49""),0),1), 0)"),0.0) -> 0 | AC51: =IF(COUNTIF(B$1145:B$1305,L51)=0,0,1) -> 1 | AD51: 1 | AE51: =IFERROR(__xludf.DUMMYFUNCTION("IFERROR(IF(Match(L51,IMPORTRANGE(""https://docs.google.com/spreadsheets/d/1hvckjcCpxEuDQDPrBMml_I1kBhYyjrgR8qBKC9QGVUc/edit?resourcekey=&gid=230793720#gid=230793720"",""Form Responses 1!B2:B199""),0),1), 0)"),0.0) -> 0 | AF51: =IFERROR(__xludf.DUMMYFUNCTION("IFERROR(IF(Match(L51,IMPORTRANGE(""https://docs.google.com/spreadsheets/d/1UY0hI2S83Fmafa5P-C1LM9yqe4v4qIKTnVy_CzLzRPs/edit?resourcekey=&gid=1583835601#gid=1583835601"",""Form Responses 1!B2:B194""),0),1), 0)"),0.0) -> 0 | AG51: =IFERROR(__xludf.DUMMYFUNCTION("IFERROR(IF(Match(L51,IMPORTRANGE(""https://docs.google.com/spreadsheets/d/1hO4mQ22n6cudUygJ2ss_JeJdm2Ua_7hJl_79lWWEtic/edit?resourcekey=&gid=2087212010#gid=2087212010"",""Form Responses 1!B2:B104""),0),1), 0)"),0.0) -> 0 | AH51: =IFERROR(__xludf.DUMMYFUNCTION("IFERROR(IF(Match(L51,IMPORTRANGE(""https://docs.google.com/spreadsheets/d/1HbfCXhSXbtTODKKY1MOFwJccyhgDKD0J9sO1k5l_6lM/edit?resourcekey=&gid=1616384832#gid=1616384832"",""Form Responses 1!E2:E143""),0),1), 0)"),0.0) -> 0
A52: 45917.665 | B52: ellie.mui@warriorlife.net | C52: Ellie | D52: Mui | E52: G105 | F52: Novice (1st year or 2nd years who haven't placed top 10 (SCDC) or top 3 (SVCDC)) | G52: Chloe Zhong | H52: Setting a minimum age requirement (no child labor!) | K52: Kissa Hsieh | L52: yicheng.hsieh@warriorlife.net | M52: Grace Xu | N52: N | O52: 1st Year | P52: 10 | Q52: EIP | R52: 0.5 | S52: =IF(COUNTIF(B$150:B$274,L52)=0,0,1) -> 0 | T52: =IF(COUNTIF(B$275:B$401,L52)=0,0,1) -> 1 | U52: =IFERROR(__xludf.DUMMYFUNCTION("IFERROR(IF(Match(L52,IMPORTRANGE(""https://docs.google.com/spreadsheets/d/1CAXKDiOnZb21bZOY_nacH9xI9AiD-nH8ZZQAwYKkVC0/edit?usp=drivesdk"",""Completed Exams!A1:A135""),0),1), 0)"),0.0) -> 0 | V52: =IF(COUNTIF(B$416:B$535,L52)=0,0,1) -> 1 | W52: 1 | X52: =IF(COUNTIF(B$603:B$725,L52)=0,0,1) -> 1 | Y52: =IF(COUNTIF(B$725:B$844,L52)=0,0,1) -> 1 | Z52: =IF(COUNTIF(B$845:B$969,L52)=0,0,1) -> 0 | AA52: =IF(COUNTIF(B$971:B$1124,L52)=0,0,1) -> 1 | AB52: 0.5 | AC52: =IF(COUNTIF(B$1145:B$1305,L52)=0,0,1) -> 1 | AD52: 1 | AE52: =IFERROR(__xludf.DUMMYFUNCTION("IFERROR(IF(Match(L52,IMPORTRANGE(""https://docs.google.com/spreadsheets/d/1hvckjcCpxEuDQDPrBMml_I1kBhYyjrgR8qBKC9QGVUc/edit?resourcekey=&gid=230793720#gid=230793720"",""Form Responses 1!B2:B199""),0),1), 0)"),0.0) -> 0 | AF52: =IFERROR(__xludf.DUMMYFUNCTION("IFERROR(IF(Match(L52,IMPORTRANGE(""https://docs.google.com/spreadsheets/d/1UY0hI2S83Fmafa5P-C1LM9yqe4v4qIKTnVy_CzLzRPs/edit?resourcekey=&gid=1583835601#gid=1583835601"",""Form Responses 1!B2:B194""),0),1), 0)"),0.0) -> 0 | AG52: =IFERROR(__xludf.DUMMYFUNCTION("IFERROR(IF(Match(L52,IMPORTRANGE(""https://docs.google.com/spreadsheets/d/1hO4mQ22n6cudUygJ2ss_JeJdm2Ua_7hJl_79lWWEtic/edit?resourcekey=&gid=2087212010#gid=2087212010"",""Form Responses 1!B2:B104""),0),1), 0)"),0.0) -> 0 | AH52: =IFERROR(__xludf.DUMMYFUNCTION("IFERROR(IF(Match(L52,IMPORTRANGE(""https://docs.google.com/spreadsheets/d/1HbfCXhSXbtTODKKY1MOFwJccyhgDKD0J9sO1k5l_6lM/edit?resourcekey=&gid=1616384832#gid=1616384832"",""Form Responses 1!E2:E143""),0),1), 0)"),0.0) -> 0
A53: 45917.665 | B53: sophie.ji@warriorlife.net | C53: Sophie | D53: Ji | E53: G105 | F53: Novice (1st year or 2nd years who haven't placed top 10 (SCDC) or top 3 (SVCDC)) | G53: Evelyn | H53: Donating to a non profit | K53: Nathan Cung | L53: nathan.cung@warriorlife.net | M53: Grace Xu | N53: N | O53: 1st Year | P53: 10 | Q53: EIP | R53: =IF(COUNTIF(B$2:B$149,L53)=0,0,1) -> 1 | S53: =IF(COUNTIF(B$150:B$274,L53)=0,0,1) -> 1 | T53: =IF(COUNTIF(B$275:B$401,L53)=0,0,1) -> 1 | U53: =IFERROR(__xludf.DUMMYFUNCTION("IFERROR(IF(Match(L53,IMPORTRANGE(""https://docs.google.com/spreadsheets/d/1CAXKDiOnZb21bZOY_nacH9xI9AiD-nH8ZZQAwYKkVC0/edit?usp=drivesdk"",""Completed Exams!A1:A135""),0),1), 0)"),0.0) -> 0 | V53: =IF(COUNTIF(B$416:B$535,L53)=0,0,1) -> 1 | W53: 1 | X53: =IF(COUNTIF(B$603:B$725,L53)=0,0,1) -> 1 | Y53: =IF(COUNTIF(B$725:B$844,L53)=0,0,1) -> 1 | Z53: =IF(COUNTIF(B$845:B$969,L53)=0,0,1) -> 1 | AA53: =IF(COUNTIF(B$971:B$1124,L53)=0,0,1) -> 1 | AB53: =IFERROR(__xludf.DUMMYFUNCTION("IFERROR(IF(Match(L53,IMPORTRANGE(""https://docs.google.com/spreadsheets/d/1n1sT_Q_W3mKmn2Yrd8qcNzuRD4zr4DB9gqARnjQ30B4/edit?gid=1918970062#gid=1918970062"",""Form Responses 1!B2:B49""),0),1), 0)"),0.0) -> 0 | AC53: =IF(COUNTIF(B$1145:B$1305,L53)=0,0,1) -> 1 | AD53: 1 | AE53: =IFERROR(__xludf.DUMMYFUNCTION("IFERROR(IF(Match(L53,IMPORTRANGE(""https://docs.google.com/spreadsheets/d/1hvckjcCpxEuDQDPrBMml_I1kBhYyjrgR8qBKC9QGVUc/edit?resourcekey=&gid=230793720#gid=230793720"",""Form Responses 1!B2:B199""),0),1), 0)"),0.0) -> 0 | AF53: =IFERROR(__xludf.DUMMYFUNCTION("IFERROR(IF(Match(L53,IMPORTRANGE(""https://docs.google.com/spreadsheets/d/1UY0hI2S83Fmafa5P-C1LM9yqe4v4qIKTnVy_CzLzRPs/edit?resourcekey=&gid=1583835601#gid=1583835601"",""Form Responses 1!B2:B194""),0),1), 0)"),0.0) -> 0 | AG53: =IFERROR(__xludf.DUMMYFUNCTION("IFERROR(IF(Match(L53,IMPORTRANGE(""https://docs.google.com/spreadsheets/d/1hO4mQ22n6cudUygJ2ss_JeJdm2Ua_7hJl_79lWWEtic/edit?resourcekey=&gid=2087212010#gid=2087212010"",""Form Responses 1!B2:B104""),0),1), 0)"),0.0) -> 0 | AH53: =IFERROR(__xludf.DUMMYFUNCTION("IFERROR(IF(Match(L53,IMPORTRANGE(""https://docs.google.com/spreadsheets/d/1HbfCXhSXbtTODKKY1MOFwJccyhgDKD0J9sO1k5l_6lM/edit?resourcekey=&gid=1616384832#gid=1616384832"",""Form Responses 1!E2:E143""),0),1), 0)"),0.0) -> 0
A54: 45917.665 | B54: shuhan.zhang@warriorlife.net | C54: Shuhan | D54: Zhang | E54: G109 | F54: Experienced (2nd years who have placed top 10 (SCDC) or top 3 (SVCDC) or 3rd and 4th years) | G54: Alicia Tang | H54: Opportunity | K54: Ashley Lai | L54: ashley.lai@warriorlife.net | M54: Grace Xu | N54: N | O54: 1st Year | P54: 10 | Q54: EIP | R54: =IF(COUNTIF(B$2:B$149,L54)=0,0,1) -> 1 | S54: =IF(COUNTIF(B$150:B$274,L54)=0,0,1) -> 1 | T54: =IF(COUNTIF(B$275:B$401,L54)=0,0,1) -> 1 | U54: =IFERROR(__xludf.DUMMYFUNCTION("IFERROR(IF(Match(L54,IMPORTRANGE(""https://docs.google.com/spreadsheets/d/1CAXKDiOnZb21bZOY_nacH9xI9AiD-nH8ZZQAwYKkVC0/edit?usp=drivesdk"",""Completed Exams!A1:A135""),0),1), 0)"),0.0) -> 0 | V54: =IF(COUNTIF(B$416:B$535,L54)=0,0,1) -> 1 | W54: =IF(COUNTIF(B$535:B$602,L54)=0,0,1) -> 1 | X54: =IF(COUNTIF(B$603:B$725,L54)=0,0,1) -> 1 | Y54: =IF(COUNTIF(B$725:B$844,L54)=0,0,1) -> 1 | Z54: =IF(COUNTIF(B$845:B$969,L54)=0,0,1) -> 1 | AA54: =IF(COUNTIF(B$971:B$1124,L54)=0,0,1) -> 1 | AB54: =IFERROR(__xludf.DUMMYFUNCTION("IFERROR(IF(Match(L54,IMPORTRANGE(""https://docs.google.com/spreadsheets/d/1n1sT_Q_W3mKmn2Yrd8qcNzuRD4zr4DB9gqARnjQ30B4/edit?gid=1918970062#gid=1918970062"",""Form Responses 1!B2:B49""),0),1), 0)"),0.0) -> 0 | AC54: =IF(COUNTIF(B$1145:B$1305,L54)=0,0,1) -> 1 | AD54: 0 | AE54: =IFERROR(__xludf.DUMMYFUNCTION("IFERROR(IF(Match(L54,IMPORTRANGE(""https://docs.google.com/spreadsheets/d/1hvckjcCpxEuDQDPrBMml_I1kBhYyjrgR8qBKC9QGVUc/edit?resourcekey=&gid=230793720#gid=230793720"",""Form Responses 1!B2:B199""),0),1), 0)"),0.0) -> 0 | AF54: =IFERROR(__xludf.DUMMYFUNCTION("IFERROR(IF(Match(L54,IMPORTRANGE(""https://docs.google.com/spreadsheets/d/1UY0hI2S83Fmafa5P-C1LM9yqe4v4qIKTnVy_CzLzRPs/edit?resourcekey=&gid=1583835601#gid=1583835601"",""Form Responses 1!B2:B194""),0),1), 0)"),0.0) -> 0 | AG54: =IFERROR(__xludf.DUMMYFUNCTION("IFERROR(IF(Match(L54,IMPORTRANGE(""https://docs.google.com/spreadsheets/d/1hO4mQ22n6cudUygJ2ss_JeJdm2Ua_7hJl_79lWWEtic/edit?resourcekey=&gid=2087212010#gid=2087212010"",""Form Responses 1!B2:B104""),0),1), 0)"),0.0) -> 0 | AH54: =IFERROR(__xludf.DUMMYFUNCTION("IFERROR(IF(Match(L54,IMPORTRANGE(""https://docs.google.com/spreadsheets/d/1HbfCXhSXbtTODKKY1MOFwJccyhgDKD0J9sO1k5l_6lM/edit?resourcekey=&gid=1616384832#gid=1616384832"",""Form Responses 1!E2:E143""),0),1), 0)"),0.0) -> 0 | AI54: 1
A55: 45917.665 | B55: dana.sun@warriorlife.net | C55: Dana | D55: Sun | E55: G106 | F55: Novice (1st year or 2nd years who haven't placed top 10 (SCDC) or top 3 (SVCDC)) | G55: Jayden Peterson | H55: Being eco-friendly | K55: Audrey Truong | L55: audrey.truong@warriorlife.net | M55: Grace Xu | N55: N | O55: 1st Year | P55: 10 | Q55: ESB | R55: =IF(COUNTIF(B$2:B$149,L55)=0,0,1) -> 1 | S55: =IF(COUNTIF(B$150:B$274,L55)=0,0,1) -> 1 | T55: =IF(COUNTIF(B$275:B$401,L55)=0,0,1) -> 1 | U55: =IFERROR(__xludf.DUMMYFUNCTION("IFERROR(IF(Match(L55,IMPORTRANGE(""https://docs.google.com/spreadsheets/d/1CAXKDiOnZb21bZOY_nacH9xI9AiD-nH8ZZQAwYKkVC0/edit?usp=drivesdk"",""Completed Exams!A1:A135""),0),1), 0)"),0.0) -> 0 | V55: =IF(COUNTIF(B$416:B$535,L55)=0,0,1) -> 1 | W55: =IF(COUNTIF(B$535:B$602,L55)=0,0,1) -> 0 | X55: =IF(COUNTIF(B$603:B$725,L55)=0,0,1) -> 1 | Y55: =IF(COUNTIF(B$725:B$844,L55)=0,0,1) -> 1 | Z55: =IF(COUNTIF(B$845:B$969,L55)=0,0,1) -> 1 | AA55: =IF(COUNTIF(B$971:B$1124,L55)=0,0,1) -> 1 | AB55: =IFERROR(__xludf.DUMMYFUNCTION("IFERROR(IF(Match(L55,IMPORTRANGE(""https://docs.google.com/spreadsheets/d/1n1sT_Q_W3mKmn2Yrd8qcNzuRD4zr4DB9gqARnjQ30B4/edit?gid=1918970062#gid=1918970062"",""Form Responses 1!B2:B49""),0),1), 0)"),0.0) -> 0 | AC55: =IF(COUNTIF(B$1145:B$1305,L55)=0,0,1) -> 1 | AD55: 1 | AE55: =IFERROR(__xludf.DUMMYFUNCTION("IFERROR(IF(Match(L55,IMPORTRANGE(""https://docs.google.com/spreadsheets/d/1hvckjcCpxEuDQDPrBMml_I1kBhYyjrgR8qBKC9QGVUc/edit?resourcekey=&gid=230793720#gid=230793720"",""Form Responses 1!B2:B199""),0),1), 0)"),0.0) -> 0 | AF55: 0.5 | AG55: =IFERROR(__xludf.DUMMYFUNCTION("IFERROR(IF(Match(L55,IMPORTRANGE(""https://docs.google.com/spreadsheets/d/1hO4mQ22n6cudUygJ2ss_JeJdm2Ua_7hJl_79lWWEtic/edit?resourcekey=&gid=2087212010#gid=2087212010"",""Form Responses 1!B2:B104""),0),1), 0)"),0.0) -> 0 | AH55: =IFERROR(__xludf.DUMMYFUNCTION("IFERROR(IF(Match(L55,IMPORTRANGE(""https://docs.google.com/spreadsheets/d/1HbfCXhSXbtTODKKY1MOFwJccyhgDKD0J9sO1k5l_6lM/edit?resourcekey=&gid=1616384832#gid=1616384832"",""Form Responses 1!E2:E143""),0),1), 0)"),0.0) -> 0
A56: 45917.665 | B56: purvi.muriki@warriorlife.net | C56: Purvi | D56: Muriki | E56: G109 | F56: Novice (1st year or 2nd years who haven't placed top 10 (SCDC) or top 3 (SVCDC)) | G56: Ranjani | H56: strengths | K56: Brooke Harvey | L56: brooke.harvey@warriorlife.net | M56: Grace Xu | N56: N | O56: 1st Year | P56: 10 | Q56: ESB | R56: =IF(COUNTIF(B$2:B$149,L56)=0,0,1) -> 1 | S56: =IF(COUNTIF(B$150:B$274,L56)=0,0,1) -> 1 | T56: =IF(COUNTIF(B$275:B$401,L56)=0,0,1) -> 1 | U56: =IFERROR(__xludf.DUMMYFUNCTION("IFERROR(IF(Match(L56,IMPORTRANGE(""https://docs.google.com/spreadsheets/d/1CAXKDiOnZb21bZOY_nacH9xI9AiD-nH8ZZQAwYKkVC0/edit?usp=drivesdk"",""Completed Exams!A1:A135""),0),1), 0)"),0.0) -> 0 | V56: =IF(COUNTIF(B$416:B$535,L56)=0,0,1) -> 0 | W56: 1 | X56: =IF(COUNTIF(B$603:B$725,L56)=0,0,1) -> 1 | Y56: =IF(COUNTIF(B$725:B$844,L56)=0,0,1) -> 1 | Z56: =IF(COUNTIF(B$845:B$969,L56)=0,0,1) -> 1 | AA56: =IF(COUNTIF(B$971:B$1124,L56)=0,0,1) -> 1 | AB56: 1 | AC56: =IF(COUNTIF(B$1145:B$1305,L56)=0,0,1) -> 1 | AD56: 1 | AE56: =IFERROR(__xludf.DUMMYFUNCTION("IFERROR(IF(Match(L56,IMPORTRANGE(""https://docs.google.com/spreadsheets/d/1hvckjcCpxEuDQDPrBMml_I1kBhYyjrgR8qBKC9QGVUc/edit?resourcekey=&gid=230793720#gid=230793720"",""Form Responses 1!B2:B199""),0),1), 0)"),0.0) -> 0 | AF56: =IFERROR(__xludf.DUMMYFUNCTION("IFERROR(IF(Match(L56,IMPORTRANGE(""https://docs.google.com/spreadsheets/d/1UY0hI2S83Fmafa5P-C1LM9yqe4v4qIKTnVy_CzLzRPs/edit?resourcekey=&gid=1583835601#gid=1583835601"",""Form Responses 1!B2:B194""),0),1), 0)"),0.0) -> 0 | AG56: =IFERROR(__xludf.DUMMYFUNCTION("IFERROR(IF(Match(L56,IMPORTRANGE(""https://docs.google.com/spreadsheets/d/1hO4mQ22n6cudUygJ2ss_JeJdm2Ua_7hJl_79lWWEtic/edit?resourcekey=&gid=2087212010#gid=2087212010"",""Form Responses 1!B2:B104""),0),1), 0)"),0.0) -> 0 | AH56: =IFERROR(__xludf.DUMMYFUNCTION("IFERROR(IF(Match(L56,IMPORTRANGE(""https://docs.google.com/spreadsheets/d/1HbfCXhSXbtTODKKY1MOFwJccyhgDKD0J9sO1k5l_6lM/edit?resourcekey=&gid=1616384832#gid=1616384832"",""Form Responses 1!E2:E143""),0),1), 0)"),0.0) -> 0
A57: 45917.665 | B57: benjamin.nie@warriorlife.net | C57: Benjamin | D57: Nie | E57: G109 | F57: Experienced (2nd years who have placed top 10 (SCDC) or top 3 (SVCDC) or 3rd and 4th years) | G57: Vivian Zhang | H57: Opportunity | K57: James Yu | L57: james.yu@warriorlife.net | M57: Hannah Li | N57: N | O57: 1st Year | P57: 11 | Q57: BOR | R57: =IF(COUNTIF(B$2:B$149,L57)=0,0,1) -> 1 | S57: =IF(COUNTIF(B$150:B$274,L57)=0,0,1) -> 1 | T57: =IF(COUNTIF(B$275:B$401,L57)=0,0,1) -> 1 | U57: =IFERROR(__xludf.DUMMYFUNCTION("IFERROR(IF(Match(L57,IMPORTRANGE(""https://docs.google.com/spreadsheets/d/1CAXKDiOnZb21bZOY_nacH9xI9AiD-nH8ZZQAwYKkVC0/edit?usp=drivesdk"",""Completed Exams!A1:A135""),0),1), 0)"),0.0) -> 0 | V57: =IF(COUNTIF(B$416:B$535,L57)=0,0,1) -> 0 | W57: =IF(COUNTIF(B$535:B$602,L57)=0,0,1) -> 0 | X57: =IF(COUNTIF(B$603:B$725,L57)=0,0,1) -> 0 | Y57: =IF(COUNTIF(B$725:B$844,L57)=0,0,1) -> 1 | Z57: =IF(COUNTIF(B$845:B$969,L57)=0,0,1) -> 1 | AA57: =IF(COUNTIF(B$971:B$1124,L57)=0,0,1) -> 1 | AB57: =IFERROR(__xludf.DUMMYFUNCTION("IFERROR(IF(Match(L57,IMPORTRANGE(""https://docs.google.com/spreadsheets/d/1n1sT_Q_W3mKmn2Yrd8qcNzuRD4zr4DB9gqARnjQ30B4/edit?gid=1918970062#gid=1918970062"",""Form Responses 1!B2:B49""),0),1), 0)"),0.0) -> 0 | AC57: =IF(COUNTIF(B$1145:B$1305,L57)=0,0,1) -> 0 | AD57: 0 | AE57: =IFERROR(__xludf.DUMMYFUNCTION("IFERROR(IF(Match(L57,IMPORTRANGE(""https://docs.google.com/spreadsheets/d/1hvckjcCpxEuDQDPrBMml_I1kBhYyjrgR8qBKC9QGVUc/edit?resourcekey=&gid=230793720#gid=230793720"",""Form Responses 1!B2:B199""),0),1), 0)"),0.0) -> 0 | AF57: =IFERROR(__xludf.DUMMYFUNCTION("IFERROR(IF(Match(L57,IMPORTRANGE(""https://docs.google.com/spreadsheets/d/1UY0hI2S83Fmafa5P-C1LM9yqe4v4qIKTnVy_CzLzRPs/edit?resourcekey=&gid=1583835601#gid=1583835601"",""Form Responses 1!B2:B194""),0),1), 0)"),0.0) -> 0 | AG57: =IFERROR(__xludf.DUMMYFUNCTION("IFERROR(IF(Match(L57,IMPORTRANGE(""https://docs.google.com/spreadsheets/d/1hO4mQ22n6cudUygJ2ss_JeJdm2Ua_7hJl_79lWWEtic/edit?resourcekey=&gid=2087212010#gid=2087212010"",""Form Responses 1!B2:B104""),0),1), 0)"),0.0) -> 0 | AH57: =IFERROR(__xludf.DUMMYFUNCTION("IFERROR(IF(Match(L57,IMPORTRANGE(""https://docs.google.com/spreadsheets/d/1HbfCXhSXbtTODKKY1MOFwJccyhgDKD0J9sO1k5l_6lM/edit?resourcekey=&gid=1616384832#gid=1616384832"",""Form Responses 1!E2:E143""),0),1), 0)"),0.0) -> 0
A58: 45917.665 | B58: saira.bhatia@warriorlife.net | C58: Saira | D58: Bhatia | E58: G105 | F58: Novice (1st year or 2nd years who haven't placed top 10 (SCDC) or top 3 (SVCDC)) | G58: Kyle Chen | H58: Community Engagement | K58: Anay Kalchuri | L58: anay.kalchuri@warriorlife.net | M58: Hannah Li | N58: E | O58: 2nd Year | P58: 11 | Q58: EFB | R58: =IF(COUNTIF(B$2:B$149,L58)=0,0,1) -> 0 | S58: =IF(COUNTIF(B$150:B$274,L58)=0,0,1) -> 0 | T58: =IF(COUNTIF(B$275:B$401,L58)=0,0,1) -> 0 | U58: 1 | V58: =IF(COUNTIF(B$416:B$535,L58)=0,0,1) -> 0 | W58: =IF(COUNTIF(B$535:B$602,L58)=0,0,1) -> 1 | X58: =IF(COUNTIF(B$603:B$725,L58)=0,0,1) -> 0 | Y58: =IF(COUNTIF(B$725:B$844,L58)=0,0,1) -> 0 | Z58: =IF(COUNTIF(B$845:B$969,L58)=0,0,1) -> 0 | AA58: =IF(COUNTIF(B$971:B$1124,L58)=0,0,1) -> 0 | AB58: 1 | AC58: =IF(COUNTIF(B$1145:B$1305,L58)=0,0,1) -> 1 | AD58: 1 | AE58: =IFERROR(__xludf.DUMMYFUNCTION("IFERROR(IF(Match(L58,IMPORTRANGE(""https://docs.google.com/spreadsheets/d/1hvckjcCpxEuDQDPrBMml_I1kBhYyjrgR8qBKC9QGVUc/edit?resourcekey=&gid=230793720#gid=230793720"",""Form Responses 1!B2:B199""),0),1), 0)"),0.0) -> 0 | AF58: =IFERROR(__xludf.DUMMYFUNCTION("IFERROR(IF(Match(L58,IMPORTRANGE(""https://docs.google.com/spreadsheets/d/1UY0hI2S83Fmafa5P-C1LM9yqe4v4qIKTnVy_CzLzRPs/edit?resourcekey=&gid=1583835601#gid=1583835601"",""Form Responses 1!B2:B194""),0),1), 0)"),0.0) -> 0 | AG58: =IFERROR(__xludf.DUMMYFUNCTION("IFERROR(IF(Match(L58,IMPORTRANGE(""https://docs.google.com/spreadsheets/d/1hO4mQ22n6cudUygJ2ss_JeJdm2Ua_7hJl_79lWWEtic/edit?resourcekey=&gid=2087212010#gid=2087212010"",""Form Responses 1!B2:B104""),0),1), 0)"),0.0) -> 0 | AH58: =IFERROR(__xludf.DUMMYFUNCTION("IFERROR(IF(Match(L58,IMPORTRANGE(""https://docs.google.com/spreadsheets/d/1HbfCXhSXbtTODKKY1MOFwJccyhgDKD0J9sO1k5l_6lM/edit?resourcekey=&gid=1616384832#gid=1616384832"",""Form Responses 1!E2:E143""),0),1), 0)"),0.0) -> 0
A59: 45917.665 | B59: zihan.liu@warriorlife.net | C59: Zihan | D59: Liu | E59: G105 | F59: Novice (1st year or 2nd years who haven't placed top 10 (SCDC) or top 3 (SVCDC)) | G59: Om | H59: Rounding up a dollar and giving funds to local charities | K59: Yamilet Quintana | L59: yamilet.quintana@warriorlife.net | M59: Hannah Li | N59: N | O59: 1st Year | P59: 11 | Q59: FOR | R59: =IF(COUNTIF(B$2:B$149,L59)=0,0,1) -> 1 | S59: =IF(COUNTIF(B$150:B$274,L59)=0,0,1) -> 1 | T59: =IF(COUNTIF(B$275:B$401,L59)=0,0,1) -> 1 | U59: =IFERROR(__xludf.DUMMYFUNCTION("IFERROR(IF(Match(L59,IMPORTRANGE(""https://docs.google.com/spreadsheets/d/1CAXKDiOnZb21bZOY_nacH9xI9AiD-nH8ZZQAwYKkVC0/edit?usp=drivesdk"",""Completed Exams!A1:A135""),0),1), 0)"),0.0) -> 0 | V59: =IF(COUNTIF(B$416:B$535,L59)=0,0,1) -> 1 | W59: 1 | X59: =IF(COUNTIF(B$603:B$725,L59)=0,0,1) -> 1 | Y59: =IF(COUNTIF(B$725:B$844,L59)=0,0,1) -> 1 | Z59: =IF(COUNTIF(B$845:B$969,L59)=0,0,1) -> 1 | AA59: =IF(COUNTIF(B$971:B$1124,L59)=0,0,1) -> 1 | AB59: =IFERROR(__xludf.DUMMYFUNCTION("IFERROR(IF(Match(L59,IMPORTRANGE(""https://docs.google.com/spreadsheets/d/1n1sT_Q_W3mKmn2Yrd8qcNzuRD4zr4DB9gqARnjQ30B4/edit?gid=1918970062#gid=1918970062"",""Form Responses 1!B2:B49""),0),1), 0)"),0.0) -> 0 | AC59: =IF(COUNTIF(B$1145:B$1305,L59)=0,0,1) -> 1 | AD59: 1 | AE59: =IFERROR(__xludf.DUMMYFUNCTION("IFERROR(IF(Match(L59,IMPORTRANGE(""https://docs.google.com/spreadsheets/d/1hvckjcCpxEuDQDPrBMml_I1kBhYyjrgR8qBKC9QGVUc/edit?resourcekey=&gid=230793720#gid=230793720"",""Form Responses 1!B2:B199""),0),1), 0)"),0.0) -> 0 | AF59: =IFERROR(__xludf.DUMMYFUNCTION("IFERROR(IF(Match(L59,IMPORTRANGE(""https://docs.google.com/spreadsheets/d/1UY0hI2S83Fmafa5P-C1LM9yqe4v4qIKTnVy_CzLzRPs/edit?resourcekey=&gid=1583835601#gid=1583835601"",""Form Responses 1!B2:B194""),0),1), 0)"),0.0) -> 0 | AG59: =IFERROR(__xludf.DUMMYFUNCTION("IFERROR(IF(Match(L59,IMPORTRANGE(""https://docs.google.com/spreadsheets/d/1hO4mQ22n6cudUygJ2ss_JeJdm2Ua_7hJl_79lWWEtic/edit?resourcekey=&gid=2087212010#gid=2087212010"",""Form Responses 1!B2:B104""),0),1), 0)"),0.0) -> 0 | AH59: =IFERROR(__xludf.DUMMYFUNCTION("IFERROR(IF(Match(L59,IMPORTRANGE(""https://docs.google.com/spreadsheets/d/1HbfCXhSXbtTODKKY1MOFwJccyhgDKD0J9sO1k5l_6lM/edit?resourcekey=&gid=1616384832#gid=1616384832"",""Form Responses 1!E2:E143""),0),1), 0)"),0.0) -> 0 | AI59: 1
A60: 45917.665 | B60: ivy.guo@warriorlife.net | C60: Ivy | D60: Guo | E60: G105 | F60: Novice (1st year or 2nd years who haven't placed top 10 (SCDC) or top 3 (SVCDC)) | G60: Mia tran | H60: Less child labor and repurposing. | K60: Eric Jia | L60: eric.jia@warriorlife.net | M60: Hannah Li | N60: E | O60: 3rd Year | P60: 11 | Q60: HTOR | R60: =IF(COUNTIF(B$2:B$149,L60)=0,0,1) -> 0 | S60: =IF(COUNTIF(B$150:B$274,L60)=0,0,1) -> 0 | T60: =IF(COUNTIF(B$275:B$401,L60)=0,0,1) -> 0 | U60: =IFERROR(__xludf.DUMMYFUNCTION("IFERROR(IF(Match(L60,IMPORTRANGE(""https://docs.google.com/spreadsheets/d/1CAXKDiOnZb21bZOY_nacH9xI9AiD-nH8ZZQAwYKkVC0/edit?usp=drivesdk"",""Completed Exams!A1:A135""),0),1), 0)"),0.0) -> 0 | V60: =IF(COUNTIF(B$416:B$535,L60)=0,0,1) -> 0 | W60: 1 | X60: =IF(COUNTIF(B$603:B$725,L60)=0,0,1) -> 1 | Y60: =IF(COUNTIF(B$725:B$844,L60)=0,0,1) -> 0 | Z60: =IF(COUNTIF(B$845:B$969,L60)=0,0,1) -> 1 | AA60: =IF(COUNTIF(B$971:B$1124,L60)=0,0,1) -> 0 | AB60: 1 | AC60: =IF(COUNTIF(B$1145:B$1305,L60)=0,0,1) -> 1 | AD60: 1 | AE60: =IFERROR(__xludf.DUMMYFUNCTION("IFERROR(IF(Match(L60,IMPORTRANGE(""https://docs.google.com/spreadsheets/d/1hvckjcCpxEuDQDPrBMml_I1kBhYyjrgR8qBKC9QGVUc/edit?resourcekey=&gid=230793720#gid=230793720"",""Form Responses 1!B2:B199""),0),1), 0)"),0.0) -> 0 | AF60: =IFERROR(__xludf.DUMMYFUNCTION("IFERROR(IF(Match(L60,IMPORTRANGE(""https://docs.google.com/spreadsheets/d/1UY0hI2S83Fmafa5P-C1LM9yqe4v4qIKTnVy_CzLzRPs/edit?resourcekey=&gid=1583835601#gid=1583835601"",""Form Responses 1!B2:B194""),0),1), 0)"),0.0) -> 0 | AG60: =IFERROR(__xludf.DUMMYFUNCTION("IFERROR(IF(Match(L60,IMPORTRANGE(""https://docs.google.com/spreadsheets/d/1hO4mQ22n6cudUygJ2ss_JeJdm2Ua_7hJl_79lWWEtic/edit?resourcekey=&gid=2087212010#gid=2087212010"",""Form Responses 1!B2:B104""),0),1), 0)"),0.0) -> 0 | AH60: =IFERROR(__xludf.DUMMYFUNCTION("IFERROR(IF(Match(L60,IMPORTRANGE(""https://docs.google.com/spreadsheets/d/1HbfCXhSXbtTODKKY1MOFwJccyhgDKD0J9sO1k5l_6lM/edit?resourcekey=&gid=1616384832#gid=1616384832"",""Form Responses 1!E2:E143""),0),1), 0)"),0.0) -> 0 | AI60: 1
A61: 45917.665 | B61: isobel.kwong@warriorlife.net | C61: Isobel | D61: Kwong | E61: G109 | F61: Novice (1st year or 2nd years who haven't placed top 10 (SCDC) or top 3 (SVCDC)) | G61: Ranjani | H61: Making sure the idea is plausible/feasible | K61: Jordan Kim | L61: jordan.kim@warriorlife.net | M61: Hannah Li | N61: N | O61: 2nd Year | P61: 11 | Q61: EFB | R61: =IF(COUNTIF(B$2:B$149,L61)=0,0,1) -> 1 | S61: =IF(COUNTIF(B$150:B$274,L61)=0,0,1) -> 1 | T61: =IF(COUNTIF(B$275:B$401,L61)=0,0,1) -> 1 | U61: =IFERROR(__xludf.DUMMYFUNCTION("IFERROR(IF(Match(L61,IMPORTRANGE(""https://docs.google.com/spreadsheets/d/1CAXKDiOnZb21bZOY_nacH9xI9AiD-nH8ZZQAwYKkVC0/edit?usp=drivesdk"",""Completed Exams!A1:A135""),0),1), 0)"),0.0) -> 0 | V61: =IF(COUNTIF(B$416:B$535,L61)=0,0,1) -> 1 | W61: =IF(COUNTIF(B$535:B$602,L61)=0,0,1) -> 1 | X61: =IF(COUNTIF(B$603:B$725,L61)=0,0,1) -> 1 | Y61: =IF(COUNTIF(B$725:B$844,L61)=0,0,1) -> 1 | Z61: =IF(COUNTIF(B$845:B$969,L61)=0,0,1) -> 0 | AA61: =IF(COUNTIF(B$971:B$1124,L61)=0,0,1) -> 1 | AB61: 1 | AC61: =IF(COUNTIF(B$1145:B$1305,L61)=0,0,1) -> 1 | AD61: 1 | AE61: =IFERROR(__xludf.DUMMYFUNCTION("IFERROR(IF(Match(L61,IMPORTRANGE(""https://docs.google.com/spreadsheets/d/1hvckjcCpxEuDQDPrBMml_I1kBhYyjrgR8qBKC9QGVUc/edit?resourcekey=&gid=230793720#gid=230793720"",""Form Responses 1!B2:B199""),0),1), 0)"),0.0) -> 0 | AF61: =IFERROR(__xludf.DUMMYFUNCTION("IFERROR(IF(Match(L61,IMPORTRANGE(""https://docs.google.com/spreadsheets/d/1UY0hI2S83Fmafa5P-C1LM9yqe4v4qIKTnVy_CzLzRPs/edit?resourcekey=&gid=1583835601#gid=1583835601"",""Form Responses 1!B2:B194""),0),1), 0)"),0.0) -> 0 | AG61: =IFERROR(__xludf.DUMMYFUNCTION("IFERROR(IF(Match(L61,IMPORTRANGE(""https://docs.google.com/spreadsheets/d/1hO4mQ22n6cudUygJ2ss_JeJdm2Ua_7hJl_79lWWEtic/edit?resourcekey=&gid=2087212010#gid=2087212010"",""Form Responses 1!B2:B104""),0),1), 0)"),0.0) -> 0 | AH61: =IFERROR(__xludf.DUMMYFUNCTION("IFERROR(IF(Match(L61,IMPORTRANGE(""https://docs.google.com/spreadsheets/d/1HbfCXhSXbtTODKKY1MOFwJccyhgDKD0J9sO1k5l_6lM/edit?resourcekey=&gid=1616384832#gid=1616384832"",""Form Responses 1!E2:E143""),0),1), 0)"),0.0) -> 0
A62: 45917.665 | B62: riya.khattri@warriorlife.net | C62: Riya | D62: Khattri | E62: G109 | F62: Novice (1st year or 2nd years who haven't placed top 10 (SCDC) or top 3 (SVCDC)) | G62: Sophia White | H62: feasibility | K62: Joshwyn Hong | L62: joshwyn.hong@warriorlife.net | M62: Isabella Yu | N62: N | O62: 1st Year | P62: 12 | Q62: EIP | R62: =IF(COUNTIF(B$2:B$149,L62)=0,0,1) -> 1 | S62: =IF(COUNTIF(B$150:B$274,L62)=0,0,1) -> 0 | T62: =IF(COUNTIF(B$275:B$401,L62)=0,0,1) -> 1 | U62: =IFERROR(__xludf.DUMMYFUNCTION("IFERROR(IF(Match(L62,IMPORTRANGE(""https://docs.google.com/spreadsheets/d/1CAXKDiOnZb21bZOY_nacH9xI9AiD-nH8ZZQAwYKkVC0/edit?usp=drivesdk"",""Completed Exams!A1:A135""),0),1), 0)"),0.0) -> 0 | V62: =IF(COUNTIF(B$416:B$535,L62)=0,0,1) -> 1 | W62: =IF(COUNTIF(B$535:B$602,L62)=0,0,1) -> 0 | X62: =IF(COUNTIF(B$603:B$725,L62)=0,0,1) -> 1 | Y62: =IF(COUNTIF(B$725:B$844,L62)=0,0,1) -> 1 | Z62: =IF(COUNTIF(B$845:B$969,L62)=0,0,1) -> 0 | AA62: =IF(COUNTIF(B$971:B$1124,L62)=0,0,1) -> 1 | AB62: =IFERROR(__xludf.DUMMYFUNCTION("IFERROR(IF(Match(L62,IMPORTRANGE(""https://docs.google.com/spreadsheets/d/1n1sT_Q_W3mKmn2Yrd8qcNzuRD4zr4DB9gqARnjQ30B4/edit?gid=1918970062#gid=1918970062"",""Form Responses 1!B2:B49""),0),1), 0)"),0.0) -> 0 | AC62: =IF(COUNTIF(B$1145:B$1305,L62)=0,0,1) -> 0 | AD62: 1 | AE62: =IFERROR(__xludf.DUMMYFUNCTION("IFERROR(IF(Match(L62,IMPORTRANGE(""https://docs.google.com/spreadsheets/d/1hvckjcCpxEuDQDPrBMml_I1kBhYyjrgR8qBKC9QGVUc/edit?resourcekey=&gid=230793720#gid=230793720"",""Form Responses 1!B2:B199""),0),1), 0)"),0.0) -> 0 | AF62: =IFERROR(__xludf.DUMMYFUNCTION("IFERROR(IF(Match(L62,IMPORTRANGE(""https://docs.google.com/spreadsheets/d/1UY0hI2S83Fmafa5P-C1LM9yqe4v4qIKTnVy_CzLzRPs/edit?resourcekey=&gid=1583835601#gid=1583835601"",""Form Responses 1!B2:B194""),0),1), 0)"),0.0) -> 0 | AG62: =IFERROR(__xludf.DUMMYFUNCTION("IFERROR(IF(Match(L62,IMPORTRANGE(""https://docs.google.com/spreadsheets/d/1hO4mQ22n6cudUygJ2ss_JeJdm2Ua_7hJl_79lWWEtic/edit?resourcekey=&gid=2087212010#gid=2087212010"",""Form Responses 1!B2:B104""),0),1), 0)"),0.0) -> 0 | AH62: =IFERROR(__xludf.DUMMYFUNCTION("IFERROR(IF(Match(L62,IMPORTRANGE(""https://docs.google.com/spreadsheets/d/1HbfCXhSXbtTODKKY1MOFwJccyhgDKD0J9sO1k5l_6lM/edit?resourcekey=&gid=1616384832#gid=1616384832"",""Form Responses 1!E2:E143""),0),1), 0)"),0.0) -> 0
A63: 45917.665 | B63: chunka.yu@warriorlife.net | C63: Chun Ka (Sophie) | D63: Yu | E63: G105 | F63: Novice (1st year or 2nd years who haven't placed top 10 (SCDC) or top 3 (SVCDC)) | G63: Mia Tran | H63: Fair wages and fair working hours | K63: Kinshuk Pandey | L63: kinshuk.pandey@warriorlife.net | M63: Isabella Yu | N63: N | O63: 1st Year | P63: 12 | Q63: EIP | R63: =IF(COUNTIF(B$2:B$149,L63)=0,0,1) -> 1 | S63: =IF(COUNTIF(B$150:B$274,L63)=0,0,1) -> 1 | T63: =IF(COUNTIF(B$275:B$401,L63)=0,0,1) -> 0 | U63: =IFERROR(__xludf.DUMMYFUNCTION("IFERROR(IF(Match(L63,IMPORTRANGE(""https://docs.google.com/spreadsheets/d/1CAXKDiOnZb21bZOY_nacH9xI9AiD-nH8ZZQAwYKkVC0/edit?usp=drivesdk"",""Completed Exams!A1:A135""),0),1), 0)"),0.0) -> 0 | V63: =IF(COUNTIF(B$416:B$535,L63)=0,0,1) -> 1 | W63: =IF(COUNTIF(B$535:B$602,L63)=0,0,1) -> 0 | X63: 0.5 | Y63: 0.5 | Z63: =IF(COUNTIF(B$845:B$969,L63)=0,0,1) -> 0 | AA63: =IF(COUNTIF(B$971:B$1124,L63)=0,0,1) -> 1 | AB63: =IFERROR(__xludf.DUMMYFUNCTION("IFERROR(IF(Match(L63,IMPORTRANGE(""https://docs.google.com/spreadsheets/d/1n1sT_Q_W3mKmn2Yrd8qcNzuRD4zr4DB9gqARnjQ30B4/edit?gid=1918970062#gid=1918970062"",""Form Responses 1!B2:B49""),0),1), 0)"),0.0) -> 0 | AC63: =IF(COUNTIF(B$1145:B$1305,L63)=0,0,1) -> 1 | AD63: 1 | AE63: =IFERROR(__xludf.DUMMYFUNCTION("IFERROR(IF(Match(L63,IMPORTRANGE(""https://docs.google.com/spreadsheets/d/1hvckjcCpxEuDQDPrBMml_I1kBhYyjrgR8qBKC9QGVUc/edit?resourcekey=&gid=230793720#gid=230793720"",""Form Responses 1!B2:B199""),0),1), 0)"),0.0) -> 0 | AF63: =IFERROR(__xludf.DUMMYFUNCTION("IFERROR(IF(Match(L63,IMPORTRANGE(""https://docs.google.com/spreadsheets/d/1UY0hI2S83Fmafa5P-C1LM9yqe4v4qIKTnVy_CzLzRPs/edit?resourcekey=&gid=1583835601#gid=1583835601"",""Form Responses 1!B2:B194""),0),1), 0)"),0.0) -> 0 | AG63: =IFERROR(__xludf.DUMMYFUNCTION("IFERROR(IF(Match(L63,IMPORTRANGE(""https://docs.google.com/spreadsheets/d/1hO4mQ22n6cudUygJ2ss_JeJdm2Ua_7hJl_79lWWEtic/edit?resourcekey=&gid=2087212010#gid=2087212010"",""Form Responses 1!B2:B104""),0),1), 0)"),0.0) -> 0 | AH63: =IFERROR(__xludf.DUMMYFUNCTION("IFERROR(IF(Match(L63,IMPORTRANGE(""https://docs.google.com/spreadsheets/d/1HbfCXhSXbtTODKKY1MOFwJccyhgDKD0J9sO1k5l_6lM/edit?resourcekey=&gid=1616384832#gid=1616384832"",""Form Responses 1!E2:E143""),0),1), 0)"),0.0) -> 0
A64: 45917.665 | B64: alyssa.ho@warriorlife.net | C64: Alyssa | D64: Ho | E64: G105 | F64: Novice (1st year or 2nd years who haven't placed top 10 (SCDC) or top 3 (SVCDC)) | G64: Mia Tran | H64: Sustainable sourcing and affordable pricing and donation | K64: Lukshman Senthil | L64: lukshman.senthil@warriorlife.net | M64: Isabella Yu | N64: N | O64: 1st Year | P64: 12 | Q64: EIP | R64: =IF(COUNTIF(B$2:B$149,L64)=0,0,1) -> 1 | S64: =IF(COUNTIF(B$150:B$274,L64)=0,0,1) -> 1 | T64: =IF(COUNTIF(B$275:B$401,L64)=0,0,1) -> 1 | U64: =IFERROR(__xludf.DUMMYFUNCTION("IFERROR(IF(Match(L64,IMPORTRANGE(""https://docs.google.com/spreadsheets/d/1CAXKDiOnZb21bZOY_nacH9xI9AiD-nH8ZZQAwYKkVC0/edit?usp=drivesdk"",""Completed Exams!A1:A135""),0),1), 0)"),0.0) -> 0 | V64: =IF(COUNTIF(B$416:B$535,L64)=0,0,1) -> 1 | W64: =IF(COUNTIF(B$535:B$602,L64)=0,0,1) -> 0 | X64: =IF(COUNTIF(B$603:B$725,L64)=0,0,1) -> 1 | Y64: 0.5 | Z64: =IF(COUNTIF(B$845:B$969,L64)=0,0,1) -> 0 | AA64: =IF(COUNTIF(B$971:B$1124,L64)=0,0,1) -> 1 | AB64: =IFERROR(__xludf.DUMMYFUNCTION("IFERROR(IF(Match(L64,IMPORTRANGE(""https://docs.google.com/spreadsheets/d/1n1sT_Q_W3mKmn2Yrd8qcNzuRD4zr4DB9gqARnjQ30B4/edit?gid=1918970062#gid=1918970062"",""Form Responses 1!B2:B49""),0),1), 0)"),0.0) -> 0 | AC64: 0.5 | AD64: 0 | AE64: =IFERROR(__xludf.DUMMYFUNCTION("IFERROR(IF(Match(L64,IMPORTRANGE(""https://docs.google.com/spreadsheets/d/1hvckjcCpxEuDQDPrBMml_I1kBhYyjrgR8qBKC9QGVUc/edit?resourcekey=&gid=230793720#gid=230793720"",""Form Responses 1!B2:B199""),0),1), 0)"),0.0) -> 0 | AF64: =IFERROR(__xludf.DUMMYFUNCTION("IFERROR(IF(Match(L64,IMPORTRANGE(""https://docs.google.com/spreadsheets/d/1UY0hI2S83Fmafa5P-C1LM9yqe4v4qIKTnVy_CzLzRPs/edit?resourcekey=&gid=1583835601#gid=1583835601"",""Form Responses 1!B2:B194""),0),1), 0)"),0.0) -> 0 | AG64: =IFERROR(__xludf.DUMMYFUNCTION("IFERROR(IF(Match(L64,IMPORTRANGE(""https://docs.google.com/spreadsheets/d/1hO4mQ22n6cudUygJ2ss_JeJdm2Ua_7hJl_79lWWEtic/edit?resourcekey=&gid=2087212010#gid=2087212010"",""Form Responses 1!B2:B104""),0),1), 0)"),0.0) -> 0 | AH64: =IFERROR(__xludf.DUMMYFUNCTION("IFERROR(IF(Match(L64,IMPORTRANGE(""https://docs.google.com/spreadsheets/d/1HbfCXhSXbtTODKKY1MOFwJccyhgDKD0J9sO1k5l_6lM/edit?resourcekey=&gid=1616384832#gid=1616384832"",""Form Responses 1!E2:E143""),0),1), 0)"),0.0) -> 0
A65: 45917.665 | B65: hongyao.fan@warriorlife.net | C65: Hongyao | D65: Fan | E65: G105 | F65: Novice (1st year or 2nd years who haven't placed top 10 (SCDC) or top 3 (SVCDC)) | G65: Mia Tran | H65: use renewable energy, sustainable sourcing, donations to charities, !@#$%^&*... | K65: Shalom Kommu | L65: shalom.kommu@warriorlife.net | M65: Isabella Yu | N65: N | O65: 1st Year | P65: 12 | Q65: IMCP | R65: =IF(COUNTIF(B$2:B$149,L65)=0,0,1) -> 1 | S65: =IF(COUNTIF(B$150:B$274,L65)=0,0,1) -> 1 | T65: =IF(COUNTIF(B$275:B$401,L65)=0,0,1) -> 1 | U65: =IFERROR(__xludf.DUMMYFUNCTION("IFERROR(IF(Match(L65,IMPORTRANGE(""https://docs.google.com/spreadsheets/d/1CAXKDiOnZb21bZOY_nacH9xI9AiD-nH8ZZQAwYKkVC0/edit?usp=drivesdk"",""Completed Exams!A1:A135""),0),1), 0)"),0.0) -> 0 | V65: =IF(COUNTIF(B$416:B$535,L65)=0,0,1) -> 1 | W65: =IF(COUNTIF(B$535:B$602,L65)=0,0,1) -> 0 | X65: =IF(COUNTIF(B$603:B$725,L65)=0,0,1) -> 0 | Y65: =IF(COUNTIF(B$725:B$844,L65)=0,0,1) -> 1 | Z65: =IF(COUNTIF(B$845:B$969,L65)=0,0,1) -> 1 | AA65: =IF(COUNTIF(B$971:B$1124,L65)=0,0,1) -> 1 | AB65: =IFERROR(__xludf.DUMMYFUNCTION("IFERROR(IF(Match(L65,IMPORTRANGE(""https://docs.google.com/spreadsheets/d/1n1sT_Q_W3mKmn2Yrd8qcNzuRD4zr4DB9gqARnjQ30B4/edit?gid=1918970062#gid=1918970062"",""Form Responses 1!B2:B49""),0),1), 0)"),0.0) -> 0 | AC65: =IF(COUNTIF(B$1145:B$1305,L65)=0,0,1) -> 1 | AD65: 1 | AE65: =IFERROR(__xludf.DUMMYFUNCTION("IFERROR(IF(Match(L65,IMPORTRANGE(""https://docs.google.com/spreadsheets/d/1hvckjcCpxEuDQDPrBMml_I1kBhYyjrgR8qBKC9QGVUc/edit?resourcekey=&gid=230793720#gid=230793720"",""Form Responses 1!B2:B199""),0),1), 0)"),0.0) -> 0 | AF65: =IFERROR(__xludf.DUMMYFUNCTION("IFERROR(IF(Match(L65,IMPORTRANGE(""https://docs.google.com/spreadsheets/d/1UY0hI2S83Fmafa5P-C1LM9yqe4v4qIKTnVy_CzLzRPs/edit?resourcekey=&gid=1583835601#gid=1583835601"",""Form Responses 1!B2:B194""),0),1), 0)"),0.0) -> 0 | AG65: =IFERROR(__xludf.DUMMYFUNCTION("IFERROR(IF(Match(L65,IMPORTRANGE(""https://docs.google.com/spreadsheets/d/1hO4mQ22n6cudUygJ2ss_JeJdm2Ua_7hJl_79lWWEtic/edit?resourcekey=&gid=2087212010#gid=2087212010"",""Form Responses 1!B2:B104""),0),1), 0)"),0.0) -> 0 | AH65: =IFERROR(__xludf.DUMMYFUNCTION("IFERROR(IF(Match(L65,IMPORTRANGE(""https://docs.google.com/spreadsheets/d/1HbfCXhSXbtTODKKY1MOFwJccyhgDKD0J9sO1k5l_6lM/edit?resourcekey=&gid=1616384832#gid=1616384832"",""Form Responses 1!E2:E143""),0),1), 0)"),0.0) -> 0
A66: 45917.665 | B66: shanzhi.weng@warriorlife.net | C66: Shanzhi | D66: Weng | E66: G108 | F66: Novice (1st year or 2nd years who haven't placed top 10 (SCDC) or top 3 (SVCDC)) | G66: Kyle Chen | H66: SWOT | K66: Ava Shu | L66: ava.shu@warriorlife.net | M66: Isabella Yu | N66: N | O66: 1st Year | P66: 12 | Q66: IMCS | R66: =IF(COUNTIF(B$2:B$149,L66)=0,0,1) -> 1 | S66: =IF(COUNTIF(B$150:B$274,L66)=0,0,1) -> 1 | T66: =IF(COUNTIF(B$275:B$401,L66)=0,0,1) -> 1 | U66: =IFERROR(__xludf.DUMMYFUNCTION("IFERROR(IF(Match(L66,IMPORTRANGE(""https://docs.google.com/spreadsheets/d/1CAXKDiOnZb21bZOY_nacH9xI9AiD-nH8ZZQAwYKkVC0/edit?usp=drivesdk"",""Completed Exams!A1:A135""),0),1), 0)"),0.0) -> 0 | V66: =IF(COUNTIF(B$416:B$535,L66)=0,0,1) -> 1 | W66: =IF(COUNTIF(B$535:B$602,L66)=0,0,1) -> 0 | X66: =IF(COUNTIF(B$603:B$725,L66)=0,0,1) -> 1 | Y66: =IF(COUNTIF(B$725:B$844,L66)=0,0,1) -> 1 | Z66: =IF(COUNTIF(B$845:B$969,L66)=0,0,1) -> 1 | AA66: =IF(COUNTIF(B$971:B$1124,L66)=0,0,1) -> 1 | AB66: =IFERROR(__xludf.DUMMYFUNCTION("IFERROR(IF(Match(L66,IMPORTRANGE(""https://docs.google.com/spreadsheets/d/1n1sT_Q_W3mKmn2Yrd8qcNzuRD4zr4DB9gqARnjQ30B4/edit?gid=1918970062#gid=1918970062"",""Form Responses 1!B2:B49""),0),1), 0)"),0.0) -> 0 | AC66: =IF(COUNTIF(B$1145:B$1305,L66)=0,0,1) -> 1 | AD66: 0 | AE66: =IFERROR(__xludf.DUMMYFUNCTION("IFERROR(IF(Match(L66,IMPORTRANGE(""https://docs.google.com/spreadsheets/d/1hvckjcCpxEuDQDPrBMml_I1kBhYyjrgR8qBKC9QGVUc/edit?resourcekey=&gid=230793720#gid=230793720"",""Form Responses 1!B2:B199""),0),1), 0)"),0.0) -> 0 | AF66: =IFERROR(__xludf.DUMMYFUNCTION("IFERROR(IF(Match(L66,IMPORTRANGE(""https://docs.google.com/spreadsheets/d/1UY0hI2S83Fmafa5P-C1LM9yqe4v4qIKTnVy_CzLzRPs/edit?resourcekey=&gid=1583835601#gid=1583835601"",""Form Responses 1!B2:B194""),0),1), 0)"),0.0) -> 0 | AG66: =IFERROR(__xludf.DUMMYFUNCTION("IFERROR(IF(Match(L66,IMPORTRANGE(""https://docs.google.com/spreadsheets/d/1hO4mQ22n6cudUygJ2ss_JeJdm2Ua_7hJl_79lWWEtic/edit?resourcekey=&gid=2087212010#gid=2087212010"",""Form Responses 1!B2:B104""),0),1), 0)"),0.0) -> 0 | AH66: =IFERROR(__xludf.DUMMYFUNCTION("IFERROR(IF(Match(L66,IMPORTRANGE(""https://docs.google.com/spreadsheets/d/1HbfCXhSXbtTODKKY1MOFwJccyhgDKD0J9sO1k5l_6lM/edit?resourcekey=&gid=1616384832#gid=1616384832"",""Form Responses 1!E2:E143""),0),1), 0)"),0.0) -> 0
A67: 45917.665 | B67: jayden.cha@warriorlife.net | C67: Jayden | D67: Cha | E67: G107 | F67: Novice (1st year or 2nd years who haven't placed top 10 (SCDC) or top 3 (SVCDC)) | G67: Evelyn | H67: Sustainability Goals | K67: Elaine Choi | L67: elaine.choi@warriorlife.net | M67: Isabella Yu | N67: N | O67: 1st Year | P67: 12 | Q67: IMCS | R67: =IF(COUNTIF(B$2:B$149,L67)=0,0,1) -> 1 | S67: =IF(COUNTIF(B$150:B$274,L67)=0,0,1) -> 1 | T67: =IF(COUNTIF(B$275:B$401,L67)=0,0,1) -> 1 | U67: =IFERROR(__xludf.DUMMYFUNCTION("IFERROR(IF(Match(L67,IMPORTRANGE(""https://docs.google.com/spreadsheets/d/1CAXKDiOnZb21bZOY_nacH9xI9AiD-nH8ZZQAwYKkVC0/edit?usp=drivesdk"",""Completed Exams!A1:A135""),0),1), 0)"),0.0) -> 0 | V67: =IF(COUNTIF(B$416:B$535,L67)=0,0,1) -> 1 | W67: =IF(COUNTIF(B$535:B$602,L67)=0,0,1) -> 1 | X67: =IF(COUNTIF(B$603:B$725,L67)=0,0,1) -> 1 | Y67: =IF(COUNTIF(B$725:B$844,L67)=0,0,1) -> 1 | Z67: =IF(COUNTIF(B$845:B$969,L67)=0,0,1) -> 1 | AA67: =IF(COUNTIF(B$971:B$1124,L67)=0,0,1) -> 1 | AB67: 1 | AC67: =IF(COUNTIF(B$1145:B$1305,L67)=0,0,1) -> 1 | AD67: 1 | AE67: =IFERROR(__xludf.DUMMYFUNCTION("IFERROR(IF(Match(L67,IMPORTRANGE(""https://docs.google.com/spreadsheets/d/1hvckjcCpxEuDQDPrBMml_I1kBhYyjrgR8qBKC9QGVUc/edit?resourcekey=&gid=230793720#gid=230793720"",""Form Responses 1!B2:B199""),0),1), 0)"),0.0) -> 0 | AF67: =IFERROR(__xludf.DUMMYFUNCTION("IFERROR(IF(Match(L67,IMPORTRANGE(""https://docs.google.com/spreadsheets/d/1UY0hI2S83Fmafa5P-C1LM9yqe4v4qIKTnVy_CzLzRPs/edit?resourcekey=&gid=1583835601#gid=1583835601"",""Form Responses 1!B2:B194""),0),1), 0)"),0.0) -> 0 | AG67: =IFERROR(__xludf.DUMMYFUNCTION("IFERROR(IF(Match(L67,IMPORTRANGE(""https://docs.google.com/spreadsheets/d/1hO4mQ22n6cudUygJ2ss_JeJdm2Ua_7hJl_79lWWEtic/edit?resourcekey=&gid=2087212010#gid=2087212010"",""Form Responses 1!B2:B104""),0),1), 0)"),0.0) -> 0 | AH67: =IFERROR(__xludf.DUMMYFUNCTION("IFERROR(IF(Match(L67,IMPORTRANGE(""https://docs.google.com/spreadsheets/d/1HbfCXhSXbtTODKKY1MOFwJccyhgDKD0J9sO1k5l_6lM/edit?resourcekey=&gid=1616384832#gid=1616384832"",""Form Responses 1!E2:E143""),0),1), 0)"),0.0) -> 0
A68: 45917.665 | B68: brooke.harvey@warriorlife.net | C68: Brooke | D68: Harvey | E68: G109 | F68: Novice (1st year or 2nd years who haven't placed top 10 (SCDC) or top 3 (SVCDC)) | G68: Grace Xu | H68: Competition | K68: Alyssa Doan | L68: alyssa.doan@warriorlife.net | M68: Jayden Peterson | N68: E | O68: 4th Year | P68: 13 | Q68: EIB | R68: =IF(COUNTIF(B$2:B$149,L68)=0,0,1) -> 0 | S68: =IF(COUNTIF(B$150:B$274,L68)=0,0,1) -> 1 | T68: =IF(COUNTIF(B$275:B$401,L68)=0,0,1) -> 1 | U68: =IFERROR(__xludf.DUMMYFUNCTION("IFERROR(IF(Match(L68,IMPORTRANGE(""https://docs.google.com/spreadsheets/d/1CAXKDiOnZb21bZOY_nacH9xI9AiD-nH8ZZQAwYKkVC0/edit?usp=drivesdk"",""Completed Exams!A1:A135""),0),1), 0)"),0.0) -> 0 | V68: =IF(COUNTIF(B$416:B$535,L68)=0,0,1) -> 0 | W68: =IF(COUNTIF(B$535:B$602,L68)=0,0,1) -> 0 | X68: 0.5 | Y68: =IF(COUNTIF(B$725:B$844,L68)=0,0,1) -> 0 | Z68: =IF(COUNTIF(B$845:B$969,L68)=0,0,1) -> 0 | AA68: =IF(COUNTIF(B$971:B$1124,L68)=0,0,1) -> 1 | AB68: =IFERROR(__xludf.DUMMYFUNCTION("IFERROR(IF(Match(L68,IMPORTRANGE(""https://docs.google.com/spreadsheets/d/1n1sT_Q_W3mKmn2Yrd8qcNzuRD4zr4DB9gqARnjQ30B4/edit?gid=1918970062#gid=1918970062"",""Form Responses 1!B2:B49""),0),1), 0)"),0.0) -> 0 | AC68: =IF(COUNTIF(B$1145:B$1305,L68)=0,0,1) -> 1 | AD68: 1 | AE68: 0.5 | AF68: =IFERROR(__xludf.DUMMYFUNCTION("IFERROR(IF(Match(L68,IMPORTRANGE(""https://docs.google.com/spreadsheets/d/1UY0hI2S83Fmafa5P-C1LM9yqe4v4qIKTnVy_CzLzRPs/edit?resourcekey=&gid=1583835601#gid=1583835601"",""Form Responses 1!B2:B194""),0),1), 0)"),0.0) -> 0 | AG68: 0.5 | AH68: =IFERROR(__xludf.DUMMYFUNCTION("IFERROR(IF(Match(L68,IMPORTRANGE(""https://docs.google.com/spreadsheets/d/1HbfCXhSXbtTODKKY1MOFwJccyhgDKD0J9sO1k5l_6lM/edit?resourcekey=&gid=1616384832#gid=1616384832"",""Form Responses 1!E2:E143""),0),1), 0)"),0.0) -> 0
A69: 45917.665 | B69: weichen.huang@warriorlife.net | C69: Weichen | D69: Huang | E69: G109 | F69: Novice (1st year or 2nd years who haven't placed top 10 (SCDC) or top 3 (SVCDC)) | G69: Ranjani | H69: Strengths | K69: Armaan Arya | L69: armaan.arya@warriorlife.net | M69: Jayden Peterson | N69: E | O69: 2nd Year | P69: 13 | Q69: IBP | R69: =IF(COUNTIF(B$2:B$149,L69)=0,0,1) -> 0 | S69: =IF(COUNTIF(B$150:B$274,L69)=0,0,1) -> 1 | T69: =IF(COUNTIF(B$275:B$401,L69)=0,0,1) -> 0 | U69: =IFERROR(__xludf.DUMMYFUNCTION("IFERROR(IF(Match(L69,IMPORTRANGE(""https://docs.google.com/spreadsheets/d/1CAXKDiOnZb21bZOY_nacH9xI9AiD-nH8ZZQAwYKkVC0/edit?usp=drivesdk"",""Completed Exams!A1:A135""),0),1), 0)"),0.0) -> 0 | V69: =IF(COUNTIF(B$416:B$535,L69)=0,0,1) -> 1 | W69: =IF(COUNTIF(B$535:B$602,L69)=0,0,1) -> 1 | X69: =IF(COUNTIF(B$603:B$725,L69)=0,0,1) -> 1 | Y69: =IF(COUNTIF(B$725:B$844,L69)=0,0,1) -> 1 | Z69: =IF(COUNTIF(B$845:B$969,L69)=0,0,1) -> 0 | AA69: =IF(COUNTIF(B$971:B$1124,L69)=0,0,1) -> 1 | AB69: 1 | AC69: =IF(COUNTIF(B$1145:B$1305,L69)=0,0,1) -> 1 | AD69: 0 | AE69: =IFERROR(__xludf.DUMMYFUNCTION("IFERROR(IF(Match(L69,IMPORTRANGE(""https://docs.google.com/spreadsheets/d/1hvckjcCpxEuDQDPrBMml_I1kBhYyjrgR8qBKC9QGVUc/edit?resourcekey=&gid=230793720#gid=230793720"",""Form Responses 1!B2:B199""),0),1), 0)"),0.0) -> 0 | AF69: =IFERROR(__xludf.DUMMYFUNCTION("IFERROR(IF(Match(L69,IMPORTRANGE(""https://docs.google.com/spreadsheets/d/1UY0hI2S83Fmafa5P-C1LM9yqe4v4qIKTnVy_CzLzRPs/edit?resourcekey=&gid=1583835601#gid=1583835601"",""Form Responses 1!B2:B194""),0),1), 0)"),0.0) -> 0 | AG69: =IFERROR(__xludf.DUMMYFUNCTION("IFERROR(IF(Match(L69,IMPORTRANGE(""https://docs.google.com/spreadsheets/d/1hO4mQ22n6cudUygJ2ss_JeJdm2Ua_7hJl_79lWWEtic/edit?resourcekey=&gid=2087212010#gid=2087212010"",""Form Responses 1!B2:B104""),0),1), 0)"),0.0) -> 0 | AH69: 0.5
A70: 45917.665 | B70: aaryan.shah@warriorlife.net | C70: Aaryan | D70: Shah | E70: G106 | F70: Experienced (2nd years who have placed top 10 (SCDC) or top 3 (SVCDC) or 3rd and 4th years) | G70: Evelyn | H70: Being environmentally friendly | K70: Kalie Bach | L70: an.bach@warriorlife.net | M70: Jayden Peterson | N70: N | O70: 2nd Year | P70: 13 | Q70: IBP | R70: =IF(COUNTIF(B$2:B$149,L70)=0,0,1) -> 1 | S70: =IF(COUNTIF(B$150:B$274,L70)=0,0,1) -> 1 | T70: =IF(COUNTIF(B$275:B$401,L70)=0,0,1) -> 1 | U70: =IFERROR(__xludf.DUMMYFUNCTION("IFERROR(IF(Match(L70,IMPORTRANGE(""https://docs.google.com/spreadsheets/d/1CAXKDiOnZb21bZOY_nacH9xI9AiD-nH8ZZQAwYKkVC0/edit?usp=drivesdk"",""Completed Exams!A1:A135""),0),1), 0)"),0.0) -> 0 | V70: =IF(COUNTIF(B$416:B$535,L70)=0,0,1) -> 1 | W70: 0.5 | X70: =IF(COUNTIF(B$603:B$725,L70)=0,0,1) -> 1 | Y70: =IF(COUNTIF(B$725:B$844,L70)=0,0,1) -> 0 | Z70: =IF(COUNTIF(B$845:B$969,L70)=0,0,1) -> 1 | AA70: =IF(COUNTIF(B$971:B$1124,L70)=0,0,1) -> 1 | AB70: =IFERROR(__xludf.DUMMYFUNCTION("IFERROR(IF(Match(L70,IMPORTRANGE(""https://docs.google.com/spreadsheets/d/1n1sT_Q_W3mKmn2Yrd8qcNzuRD4zr4DB9gqARnjQ30B4/edit?gid=1918970062#gid=1918970062"",""Form Responses 1!B2:B49""),0),1), 0)"),0.0) -> 0 | AC70: =IF(COUNTIF(B$1145:B$1305,L70)=0,0,1) -> 1 | AD70: 0 | AE70: =IFERROR(__xludf.DUMMYFUNCTION("IFERROR(IF(Match(L70,IMPORTRANGE(""https://docs.google.com/spreadsheets/d/1hvckjcCpxEuDQDPrBMml_I1kBhYyjrgR8qBKC9QGVUc/edit?resourcekey=&gid=230793720#gid=230793720"",""Form Responses 1!B2:B199""),0),1), 0)"),0.0) -> 0 | AF70: =IFERROR(__xludf.DUMMYFUNCTION("IFERROR(IF(Match(L70,IMPORTRANGE(""https://docs.google.com/spreadsheets/d/1UY0hI2S83Fmafa5P-C1LM9yqe4v4qIKTnVy_CzLzRPs/edit?resourcekey=&gid=1583835601#gid=1583835601"",""Form Responses 1!B2:B194""),0),1), 0)"),0.0) -> 0 | AG70: =IFERROR(__xludf.DUMMYFUNCTION("IFERROR(IF(Match(L70,IMPORTRANGE(""https://docs.google.com/spreadsheets/d/1hO4mQ22n6cudUygJ2ss_JeJdm2Ua_7hJl_79lWWEtic/edit?resourcekey=&gid=2087212010#gid=2087212010"",""Form Responses 1!B2:B104""),0),1), 0)"),0.0) -> 0 | AH70: 0.5
A71: 45917.665 | B71: connor.lam@warriorlife.net | C71: Connor | D71: Lam | E71: G106 | F71: Novice (1st year or 2nd years who haven't placed top 10 (SCDC) or top 3 (SVCDC)) | G71: Sophia white | H71: Giving back to the community | K71: Dana Sun | L71: dana.sun@warriorlife.net | M71: Jayden Peterson | N71: N | O71: 2nd Year | P71: 13 | Q71: FOR | R71: =IF(COUNTIF(B$2:B$149,L71)=0,0,1) -> 1 | S71: =IF(COUNTIF(B$150:B$274,L71)=0,0,1) -> 1 | T71: =IF(COUNTIF(B$275:B$401,L71)=0,0,1) -> 1 | U71: 0.5 | V71: 0.5 | W71: =IF(COUNTIF(B$535:B$602,L71)=0,0,1) -> 1 | X71: =IF(COUNTIF(B$603:B$725,L71)=0,0,1) -> 1 | Y71: =IF(COUNTIF(B$725:B$844,L71)=0,0,1) -> 1 | Z71: =IF(COUNTIF(B$845:B$969,L71)=0,0,1) -> 1 | AA71: =IF(COUNTIF(B$971:B$1124,L71)=0,0,1) -> 1 | AB71: =IFERROR(__xludf.DUMMYFUNCTION("IFERROR(IF(Match(L71,IMPORTRANGE(""https://docs.google.com/spreadsheets/d/1n1sT_Q_W3mKmn2Yrd8qcNzuRD4zr4DB9gqARnjQ30B4/edit?gid=1918970062#gid=1918970062"",""Form Responses 1!B2:B49""),0),1), 0)"),0.0) -> 0 | AC71: =IF(COUNTIF(B$1145:B$1305,L71)=0,0,1) -> 1 | AD71: 1 | AE71: =IFERROR(__xludf.DUMMYFUNCTION("IFERROR(IF(Match(L71,IMPORTRANGE(""https://docs.google.com/spreadsheets/d/1hvckjcCpxEuDQDPrBMml_I1kBhYyjrgR8qBKC9QGVUc/edit?resourcekey=&gid=230793720#gid=230793720"",""Form Responses 1!B2:B199""),0),1), 0)"),0.0) -> 0 | AF71: =IFERROR(__xludf.DUMMYFUNCTION("IFERROR(IF(Match(L71,IMPORTRANGE(""https://docs.google.com/spreadsheets/d/1UY0hI2S83Fmafa5P-C1LM9yqe4v4qIKTnVy_CzLzRPs/edit?resourcekey=&gid=1583835601#gid=1583835601"",""Form Responses 1!B2:B194""),0),1), 0)"),0.0) -> 0 | AG71: =IFERROR(__xludf.DUMMYFUNCTION("IFERROR(IF(Match(L71,IMPORTRANGE(""https://docs.google.com/spreadsheets/d/1hO4mQ22n6cudUygJ2ss_JeJdm2Ua_7hJl_79lWWEtic/edit?resourcekey=&gid=2087212010#gid=2087212010"",""Form Responses 1!B2:B104""),0),1), 0)"),0.0) -> 0 | AH71: =IFERROR(__xludf.DUMMYFUNCTION("IFERROR(IF(Match(L71,IMPORTRANGE(""https://docs.google.com/spreadsheets/d/1HbfCXhSXbtTODKKY1MOFwJccyhgDKD0J9sO1k5l_6lM/edit?resourcekey=&gid=1616384832#gid=1616384832"",""Form Responses 1!E2:E143""),0),1), 0)"),0.0) -> 0
A72: 45917.665 | B72: audrey.sansone@warriorlife.net | C72: Audrey | D72: Sansone | E72: G105 | F72: Novice (1st year or 2nd years who haven't placed top 10 (SCDC) or top 3 (SVCDC)) | G72: Evelyn | H72: Donating to a nonprofit. | K72: Nishanth Duvedi | L72: nishanth.duvedi@warriorlife.net | M72: Jayden Peterson | N72: N | O72: 2nd Year | P72: 13 | Q72: EIP | R72: =IF(COUNTIF(B$2:B$149,L72)=0,0,1) -> 1 | S72: =IF(COUNTIF(B$150:B$274,L72)=0,0,1) -> 1 | T72: =IF(COUNTIF(B$275:B$401,L72)=0,0,1) -> 1 | U72: =IFERROR(__xludf.DUMMYFUNCTION("IFERROR(IF(Match(L72,IMPORTRANGE(""https://docs.google.com/spreadsheets/d/1CAXKDiOnZb21bZOY_nacH9xI9AiD-nH8ZZQAwYKkVC0/edit?usp=drivesdk"",""Completed Exams!A1:A135""),0),1), 0)"),0.0) -> 0 | V72: =IF(COUNTIF(B$416:B$535,L72)=0,0,1) -> 1 | W72: 1 | X72: =IF(COUNTIF(B$603:B$725,L72)=0,0,1) -> 1 | Y72: =IF(COUNTIF(B$725:B$844,L72)=0,0,1) -> 0 | Z72: =IF(COUNTIF(B$845:B$969,L72)=0,0,1) -> 1 | AA72: =IF(COUNTIF(B$971:B$1124,L72)=0,0,1) -> 1 | AB72: =IFERROR(__xludf.DUMMYFUNCTION("IFERROR(IF(Match(L72,IMPORTRANGE(""https://docs.google.com/spreadsheets/d/1n1sT_Q_W3mKmn2Yrd8qcNzuRD4zr4DB9gqARnjQ30B4/edit?gid=1918970062#gid=1918970062"",""Form Responses 1!B2:B49""),0),1), 0)"),0.0) -> 0 | AC72: =IF(COUNTIF(B$1145:B$1305,L72)=0,0,1) -> 1 | AD72: 0.5 | AE72: 0.5 | AF72: =IFERROR(__xludf.DUMMYFUNCTION("IFERROR(IF(Match(L72,IMPORTRANGE(""https://docs.google.com/spreadsheets/d/1UY0hI2S83Fmafa5P-C1LM9yqe4v4qIKTnVy_CzLzRPs/edit?resourcekey=&gid=1583835601#gid=1583835601"",""Form Responses 1!B2:B194""),0),1), 0)"),0.0) -> 0 | AG72: =IFERROR(__xludf.DUMMYFUNCTION("IFERROR(IF(Match(L72,IMPORTRANGE(""https://docs.google.com/spreadsheets/d/1hO4mQ22n6cudUygJ2ss_JeJdm2Ua_7hJl_79lWWEtic/edit?resourcekey=&gid=2087212010#gid=2087212010"",""Form Responses 1!B2:B104""),0),1), 0)"),0.0) -> 0 | AH72: 0.5
A73: 45917.665 | B73: audrey.truong@warriorlife.net | C73: Audrey | D73: Truong | E73: G109 | F73: Novice (1st year or 2nd years who haven't placed top 10 (SCDC) or top 3 (SVCDC)) | G73: Grace Xu | H73: The competition that the idea’s market would have | K73: Saira Bhatia | L73: saira.bhatia@warriorlife.net | M73: Kyle Chen | N73: N | O73: 2nd Year | P73: 14 | Q73: FOR | R73: =IF(COUNTIF(B$2:B$149,L73)=0,0,1) -> 1 | S73: =IF(COUNTIF(B$150:B$274,L73)=0,0,1) -> 1 | T73: 0.5 | U73: =IFERROR(__xludf.DUMMYFUNCTION("IFERROR(IF(Match(L73,IMPORTRANGE(""https://docs.google.com/spreadsheets/d/1CAXKDiOnZb21bZOY_nacH9xI9AiD-nH8ZZQAwYKkVC0/edit?usp=drivesdk"",""Completed Exams!A1:A135""),0),1), 0)"),0.0) -> 0 | V73: =IF(COUNTIF(B$416:B$535,L73)=0,0,1) -> 1 | W73: =IF(COUNTIF(B$535:B$602,L73)=0,0,1) -> 1 | X73: =IF(COUNTIF(B$603:B$725,L73)=0,0,1) -> 1 | Y73: =IF(COUNTIF(B$725:B$844,L73)=0,0,1) -> 1 | Z73: =IF(COUNTIF(B$845:B$969,L73)=0,0,1) -> 1 | AA73: =IF(COUNTIF(B$971:B$1124,L73)=0,0,1) -> 1 | AB73: 1 | AC73: 1 | AD73: 1 | AE73: =IFERROR(__xludf.DUMMYFUNCTION("IFERROR(IF(Match(L73,IMPORTRANGE(""https://docs.google.com/spreadsheets/d/1hvckjcCpxEuDQDPrBMml_I1kBhYyjrgR8qBKC9QGVUc/edit?resourcekey=&gid=230793720#gid=230793720"",""Form Responses 1!B2:B199""),0),1), 0)"),0.0) -> 0 | AF73: =IFERROR(__xludf.DUMMYFUNCTION("IFERROR(IF(Match(L73,IMPORTRANGE(""https://docs.google.com/spreadsheets/d/1UY0hI2S83Fmafa5P-C1LM9yqe4v4qIKTnVy_CzLzRPs/edit?resourcekey=&gid=1583835601#gid=1583835601"",""Form Responses 1!B2:B194""),0),1), 0)"),0.0) -> 0 | AG73: =IFERROR(__xludf.DUMMYFUNCTION("IFERROR(IF(Match(L73,IMPORTRANGE(""https://docs.google.com/spreadsheets/d/1hO4mQ22n6cudUygJ2ss_JeJdm2Ua_7hJl_79lWWEtic/edit?resourcekey=&gid=2087212010#gid=2087212010"",""Form Responses 1!B2:B104""),0),1), 0)"),0.0) -> 0 | AH73: =IFERROR(__xludf.DUMMYFUNCTION("IFERROR(IF(Match(L73,IMPORTRANGE(""https://docs.google.com/spreadsheets/d/1HbfCXhSXbtTODKKY1MOFwJccyhgDKD0J9sO1k5l_6lM/edit?resourcekey=&gid=1616384832#gid=1616384832"",""Form Responses 1!E2:E143""),0),1), 0)"),0.0) -> 0
A74: 45917.665 | B74: saranya.malladi@warriorlife.net | C74: Saranya | D74: Malladi | E74: G106 | F74: Novice (1st year or 2nd years who haven't placed top 10 (SCDC) or top 3 (SVCDC)) | G74: Ruby Han | H74: Employee wellness programs | K74: Ella Weng | L74: shanzhi.weng@warriorlife.net | M74: Kyle Chen | N74: N | O74: 2nd Year | P74: 14 | Q74: IBP | R74: =IF(COUNTIF(B$2:B$149,L74)=0,0,1) -> 1 | S74: =IF(COUNTIF(B$150:B$274,L74)=0,0,1) -> 1 | T74: =IF(COUNTIF(B$275:B$401,L74)=0,0,1) -> 1 | U74: =IFERROR(__xludf.DUMMYFUNCTION("IFERROR(IF(Match(L74,IMPORTRANGE(""https://docs.google.com/spreadsheets/d/1CAXKDiOnZb21bZOY_nacH9xI9AiD-nH8ZZQAwYKkVC0/edit?usp=drivesdk"",""Completed Exams!A1:A135""),0),1), 0)"),0.0) -> 0 | V74: =IF(COUNTIF(B$416:B$535,L74)=0,0,1) -> 1 | W74: =IF(COUNTIF(B$535:B$602,L74)=0,0,1) -> 1 | X74: =IF(COUNTIF(B$603:B$725,L74)=0,0,1) -> 1 | Y74: =IF(COUNTIF(B$725:B$844,L74)=0,0,1) -> 1 | Z74: =IF(COUNTIF(B$845:B$969,L74)=0,0,1) -> 1 | AA74: =IF(COUNTIF(B$971:B$1124,L74)=0,0,1) -> 1 | AB74: =IFERROR(__xludf.DUMMYFUNCTION("IFERROR(IF(Match(L74,IMPORTRANGE(""https://docs.google.com/spreadsheets/d/1n1sT_Q_W3mKmn2Yrd8qcNzuRD4zr4DB9gqARnjQ30B4/edit?gid=1918970062#gid=1918970062"",""Form Responses 1!B2:B49""),0),1), 0)"),0.0) -> 0 | AC74: =IF(COUNTIF(B$1145:B$1305,L74)=0,0,1) -> 1 | AD74: 1 | AE74: =IFERROR(__xludf.DUMMYFUNCTION("IFERROR(IF(Match(L74,IMPORTRANGE(""https://docs.google.com/spreadsheets/d/1hvckjcCpxEuDQDPrBMml_I1kBhYyjrgR8qBKC9QGVUc/edit?resourcekey=&gid=230793720#gid=230793720"",""Form Responses 1!B2:B199""),0),1), 0)"),0.0) -> 0 | AF74: =IFERROR(__xludf.DUMMYFUNCTION("IFERROR(IF(Match(L74,IMPORTRANGE(""https://docs.google.com/spreadsheets/d/1UY0hI2S83Fmafa5P-C1LM9yqe4v4qIKTnVy_CzLzRPs/edit?resourcekey=&gid=1583835601#gid=1583835601"",""Form Responses 1!B2:B194""),0),1), 0)"),0.0) -> 0 | AG74: =IFERROR(__xludf.DUMMYFUNCTION("IFERROR(IF(Match(L74,IMPORTRANGE(""https://docs.google.com/spreadsheets/d/1hO4mQ22n6cudUygJ2ss_JeJdm2Ua_7hJl_79lWWEtic/edit?resourcekey=&gid=2087212010#gid=2087212010"",""Form Responses 1!B2:B104""),0),1), 0)"),0.0) -> 0 | AH74: =IFERROR(__xludf.DUMMYFUNCTION("IFERROR(IF(Match(L74,IMPORTRANGE(""https://docs.google.com/spreadsheets/d/1HbfCXhSXbtTODKKY1MOFwJccyhgDKD0J9sO1k5l_6lM/edit?resourcekey=&gid=1616384832#gid=1616384832"",""Form Responses 1!E2:E143""),0),1), 0)"),0.0) -> 0
A75: 45917.665 | B75: aisha.chadha@warriorlife.net | C75: Aisha | D75: Chadha | E75: G109 | F75: Novice (1st year or 2nd years who haven't placed top 10 (SCDC) or top 3 (SVCDC)) | G75: Natalie Zhang | H75: Strength | K75: Tristan Sansone | L75: tristan.sansone@warriorlife.net | M75: Kyle Chen | N75: E | O75: 4th Year | P75: 14 | Q75: IBP | R75: =IF(COUNTIF(B$2:B$149,L75)=0,0,1) -> 0 | S75: =IF(COUNTIF(B$150:B$274,L75)=0,0,1) -> 0 | T75: =IF(COUNTIF(B$275:B$401,L75)=0,0,1) -> 0 | U75: =IFERROR(__xludf.DUMMYFUNCTION("IFERROR(IF(Match(L75,IMPORTRANGE(""https://docs.google.com/spreadsheets/d/1CAXKDiOnZb21bZOY_nacH9xI9AiD-nH8ZZQAwYKkVC0/edit?usp=drivesdk"",""Completed Exams!A1:A135""),0),1), 0)"),0.0) -> 0 | V75: =IF(COUNTIF(B$416:B$535,L75)=0,0,1) -> 0 | W75: =IF(COUNTIF(B$535:B$602,L75)=0,0,1) -> 1 | X75: =IF(COUNTIF(B$603:B$725,L75)=0,0,1) -> 0 | Y75: =IF(COUNTIF(B$725:B$844,L75)=0,0,1) -> 1 | Z75: =IF(COUNTIF(B$845:B$969,L75)=0,0,1) -> 0 | AA75: =IF(COUNTIF(B$971:B$1124,L75)=0,0,1) -> 1 | AB75: =IFERROR(__xludf.DUMMYFUNCTION("IFERROR(IF(Match(L75,IMPORTRANGE(""https://docs.google.com/spreadsheets/d/1n1sT_Q_W3mKmn2Yrd8qcNzuRD4zr4DB9gqARnjQ30B4/edit?gid=1918970062#gid=1918970062"",""Form Responses 1!B2:B49""),0),1), 0)"),0.0) -> 0 | AC75: =IF(COUNTIF(B$1145:B$1305,L75)=0,0,1) -> 1 | AD75: 0 | AE75: =IFERROR(__xludf.DUMMYFUNCTION("IFERROR(IF(Match(L75,IMPORTRANGE(""https://docs.google.com/spreadsheets/d/1hvckjcCpxEuDQDPrBMml_I1kBhYyjrgR8qBKC9QGVUc/edit?resourcekey=&gid=230793720#gid=230793720"",""Form Responses 1!B2:B199""),0),1), 0)"),0.0) -> 0 | AF75: =IFERROR(__xludf.DUMMYFUNCTION("IFERROR(IF(Match(L75,IMPORTRANGE(""https://docs.google.com/spreadsheets/d/1UY0hI2S83Fmafa5P-C1LM9yqe4v4qIKTnVy_CzLzRPs/edit?resourcekey=&gid=1583835601#gid=1583835601"",""Form Responses 1!B2:B194""),0),1), 0)"),0.0) -> 0 | AG75: 1 | AH75: 1
A76: 45917.665 | B76: gordon.li@warriorlife.net | C76: Gordon | D76: Li | E76: G105 | F76: Novice (1st year or 2nd years who haven't placed top 10 (SCDC) or top 3 (SVCDC)) | G76: Nicholas | H76: Donating to nonprofit | K76: Preston Lee | L76: preston.lee@warriorlife.net | M76: Kyle Chen | N76: E | O76: 2nd Year | P76: 14 | Q76: SEOR | R76: =IF(COUNTIF(B$2:B$149,L76)=0,0,1) -> 0 | S76: =IF(COUNTIF(B$150:B$274,L76)=0,0,1) -> 0 | T76: =IF(COUNTIF(B$275:B$401,L76)=0,0,1) -> 0 | U76: 1 | V76: =IF(COUNTIF(B$416:B$535,L76)=0,0,1) -> 0 | W76: =IF(COUNTIF(B$535:B$602,L76)=0,0,1) -> 0 | X76: =IF(COUNTIF(B$603:B$725,L76)=0,0,1) -> 0 | Y76: =IF(COUNTIF(B$725:B$844,L76)=0,0,1) -> 0 | Z76: =IF(COUNTIF(B$845:B$969,L76)=0,0,1) -> 0 | AA76: =IF(COUNTIF(B$971:B$1124,L76)=0,0,1) -> 1 | AB76: =IFERROR(__xludf.DUMMYFUNCTION("IFERROR(IF(Match(L76,IMPORTRANGE(""https://docs.google.com/spreadsheets/d/1n1sT_Q_W3mKmn2Yrd8qcNzuRD4zr4DB9gqARnjQ30B4/edit?gid=1918970062#gid=1918970062"",""Form Responses 1!B2:B49""),0),1), 0)"),0.0) -> 0 | AC76: 1 | AD76: 0 | AE76: =IFERROR(__xludf.DUMMYFUNCTION("IFERROR(IF(Match(L76,IMPORTRANGE(""https://docs.google.com/spreadsheets/d/1hvckjcCpxEuDQDPrBMml_I1kBhYyjrgR8qBKC9QGVUc/edit?resourcekey=&gid=230793720#gid=230793720"",""Form Responses 1!B2:B199""),0),1), 0)"),0.0) -> 0 | AF76: =IFERROR(__xludf.DUMMYFUNCTION("IFERROR(IF(Match(L76,IMPORTRANGE(""https://docs.google.com/spreadsheets/d/1UY0hI2S83Fmafa5P-C1LM9yqe4v4qIKTnVy_CzLzRPs/edit?resourcekey=&gid=1583835601#gid=1583835601"",""Form Responses 1!B2:B194""),0),1), 0)"),0.0) -> 0 | AG76: =IFERROR(__xludf.DUMMYFUNCTION("IFERROR(IF(Match(L76,IMPORTRANGE(""https://docs.google.com/spreadsheets/d/1hO4mQ22n6cudUygJ2ss_JeJdm2Ua_7hJl_79lWWEtic/edit?resourcekey=&gid=2087212010#gid=2087212010"",""Form Responses 1!B2:B104""),0),1), 0)"),0.0) -> 0 | AH76: =IFERROR(__xludf.DUMMYFUNCTION("IFERROR(IF(Match(L76,IMPORTRANGE(""https://docs.google.com/spreadsheets/d/1HbfCXhSXbtTODKKY1MOFwJccyhgDKD0J9sO1k5l_6lM/edit?resourcekey=&gid=1616384832#gid=1616384832"",""Form Responses 1!E2:E143""),0),1), 0)"),0.0) -> 0
A77: 45917.665 | B77: chaebin.jang@warriorlife.net | C77: Chaebin | D77: Jang | E77: G109 | F77: Novice (1st year or 2nd years who haven't placed top 10 (SCDC) or top 3 (SVCDC)) | G77: Ranjani | H77: Use the SWAT method! | K77: Romir Bhatt | L77: romir.bhatt@warriorlife.net | M77: Kyle Chen | N77: E | O77: 3rd Year | P77: 14 | Q77: SEOR | R77: =IF(COUNTIF(B$2:B$149,L77)=0,0,1) -> 0 | S77: =IF(COUNTIF(B$150:B$274,L77)=0,0,1) -> 0 | T77: =IF(COUNTIF(B$275:B$401,L77)=0,0,1) -> 0 | U77: 1 | V77: =IF(COUNTIF(B$416:B$535,L77)=0,0,1) -> 0 | W77: =IF(COUNTIF(B$535:B$602,L77)=0,0,1) -> 0 | X77: =IF(COUNTIF(B$603:B$725,L77)=0,0,1) -> 0 | Y77: =IF(COUNTIF(B$725:B$844,L77)=0,0,1) -> 1 | Z77: =IF(COUNTIF(B$845:B$969,L77)=0,0,1) -> 0 | AA77: =IF(COUNTIF(B$971:B$1124,L77)=0,0,1) -> 1 | AB77: =IFERROR(__xludf.DUMMYFUNCTION("IFERROR(IF(Match(L77,IMPORTRANGE(""https://docs.google.com/spreadsheets/d/1n1sT_Q_W3mKmn2Yrd8qcNzuRD4zr4DB9gqARnjQ30B4/edit?gid=1918970062#gid=1918970062"",""Form Responses 1!B2:B49""),0),1), 0)"),0.0) -> 0 | AC77: 1 | AD77: 0 | AE77: =IFERROR(__xludf.DUMMYFUNCTION("IFERROR(IF(Match(L77,IMPORTRANGE(""https://docs.google.com/spreadsheets/d/1hvckjcCpxEuDQDPrBMml_I1kBhYyjrgR8qBKC9QGVUc/edit?resourcekey=&gid=230793720#gid=230793720"",""Form Responses 1!B2:B199""),0),1), 0)"),0.0) -> 0 | AF77: =IFERROR(__xludf.DUMMYFUNCTION("IFERROR(IF(Match(L77,IMPORTRANGE(""https://docs.google.com/spreadsheets/d/1UY0hI2S83Fmafa5P-C1LM9yqe4v4qIKTnVy_CzLzRPs/edit?resourcekey=&gid=1583835601#gid=1583835601"",""Form Responses 1!B2:B194""),0),1), 0)"),0.0) -> 0 | AG77: =IFERROR(__xludf.DUMMYFUNCTION("IFERROR(IF(Match(L77,IMPORTRANGE(""https://docs.google.com/spreadsheets/d/1hO4mQ22n6cudUygJ2ss_JeJdm2Ua_7hJl_79lWWEtic/edit?resourcekey=&gid=2087212010#gid=2087212010"",""Form Responses 1!B2:B104""),0),1), 0)"),0.0) -> 0 | AH77: =IFERROR(__xludf.DUMMYFUNCTION("IFERROR(IF(Match(L77,IMPORTRANGE(""https://docs.google.com/spreadsheets/d/1HbfCXhSXbtTODKKY1MOFwJccyhgDKD0J9sO1k5l_6lM/edit?resourcekey=&gid=1616384832#gid=1616384832"",""Form Responses 1!E2:E143""),0),1), 0)"),0.0) -> 0
A78: 45917.665 | B78: hongbo.li@warriorlife.net | C78: Hong Bo | D78: Li | E78: G109 | F78: Novice (1st year or 2nd years who haven't placed top 10 (SCDC) or top 3 (SVCDC)) | G78: Sophia White | H78: THREATS!! | K78: Tiffany Le | L78: tiffany.le@warriorlife.net | M78: Kyle Chen | N78: E | O78: 3rd Year | P78: 14 | Q78: SEOR | R78: =IF(COUNTIF(B$2:B$149,L78)=0,0,1) -> 0 | S78: =IF(COUNTIF(B$150:B$274,L78)=0,0,1) -> 0 | T78: =IF(COUNTIF(B$275:B$401,L78)=0,0,1) -> 0 | U78: =IFERROR(__xludf.DUMMYFUNCTION("IFERROR(IF(Match(L78,IMPORTRANGE(""https://docs.google.com/spreadsheets/d/1CAXKDiOnZb21bZOY_nacH9xI9AiD-nH8ZZQAwYKkVC0/edit?usp=drivesdk"",""Completed Exams!A1:A135""),0),1), 0)"),0.0) -> 0 | V78: =IF(COUNTIF(B$416:B$535,L78)=0,0,1) -> 1 | W78: 0.5 | X78: =IF(COUNTIF(B$603:B$725,L78)=0,0,1) -> 1 | Y78: =IF(COUNTIF(B$725:B$844,L78)=0,0,1) -> 0 | Z78: =IF(COUNTIF(B$845:B$969,L78)=0,0,1) -> 0 | AA78: =IF(COUNTIF(B$971:B$1124,L78)=0,0,1) -> 1 | AB78: =IFERROR(__xludf.DUMMYFUNCTION("IFERROR(IF(Match(L78,IMPORTRANGE(""https://docs.google.com/spreadsheets/d/1n1sT_Q_W3mKmn2Yrd8qcNzuRD4zr4DB9gqARnjQ30B4/edit?gid=1918970062#gid=1918970062"",""Form Responses 1!B2:B49""),0),1), 0)"),0.0) -> 0 | AC78: 1 | AD78: 0 | AE78: =IFERROR(__xludf.DUMMYFUNCTION("IFERROR(IF(Match(L78,IMPORTRANGE(""https://docs.google.com/spreadsheets/d/1hvckjcCpxEuDQDPrBMml_I1kBhYyjrgR8qBKC9QGVUc/edit?resourcekey=&gid=230793720#gid=230793720"",""Form Responses 1!B2:B199""),0),1), 0)"),0.0) -> 0 | AF78: =IFERROR(__xludf.DUMMYFUNCTION("IFERROR(IF(Match(L78,IMPORTRANGE(""https://docs.google.com/spreadsheets/d/1UY0hI2S83Fmafa5P-C1LM9yqe4v4qIKTnVy_CzLzRPs/edit?resourcekey=&gid=1583835601#gid=1583835601"",""Form Responses 1!B2:B194""),0),1), 0)"),0.0) -> 0 | AG78: =IFERROR(__xludf.DUMMYFUNCTION("IFERROR(IF(Match(L78,IMPORTRANGE(""https://docs.google.com/spreadsheets/d/1hO4mQ22n6cudUygJ2ss_JeJdm2Ua_7hJl_79lWWEtic/edit?resourcekey=&gid=2087212010#gid=2087212010"",""Form Responses 1!B2:B104""),0),1), 0)"),0.0) -> 0 | AH78: =IFERROR(__xludf.DUMMYFUNCTION("IFERROR(IF(Match(L78,IMPORTRANGE(""https://docs.google.com/spreadsheets/d/1HbfCXhSXbtTODKKY1MOFwJccyhgDKD0J9sO1k5l_6lM/edit?resourcekey=&gid=1616384832#gid=1616384832"",""Form Responses 1!E2:E143""),0),1), 0)"),0.0) -> 0
A79: 45917.665 | B79: nishanth.duvedi@warriorlife.net | C79: Nishanth | D79: Duvedi | E79: G109 | F79: Novice (1st year or 2nd years who haven't placed top 10 (SCDC) or top 3 (SVCDC)) | G79: Jayden Peterson | H79: SWOT analysis | K79: Timothy Feng | L79: timothy.feng@warriorlife.net | M79: Melody Leong | N79: N | O79: 1st Year | P79: 1 | Q79: FOR | R79: =IF(COUNTIF(B$2:B$149,L79)=0,0,1) -> 1 | S79: =IF(COUNTIF(B$150:B$274,L79)=0,0,1) -> 1 | T79: =IF(COUNTIF(B$275:B$401,L79)=0,0,1) -> 1 | U79: =IFERROR(__xludf.DUMMYFUNCTION("IFERROR(IF(Match(L79,IMPORTRANGE(""https://docs.google.com/spreadsheets/d/1CAXKDiOnZb21bZOY_nacH9xI9AiD-nH8ZZQAwYKkVC0/edit?usp=drivesdk"",""Completed Exams!A1:A135""),0),1), 0)"),0.0) -> 0 | V79: =IF(COUNTIF(B$416:B$535,L79)=0,0,1) -> 1 | W79: =IF(COUNTIF(B$535:B$602,L79)=0,0,1) -> 1 | X79: =IF(COUNTIF(B$603:B$725,L79)=0,0,1) -> 0 | Y79: 1 | Z79: =IF(COUNTIF(B$845:B$969,L79)=0,0,1) -> 1 | AA79: =IF(COUNTIF(B$971:B$1124,L79)=0,0,1) -> 1 | AB79: =IFERROR(__xludf.DUMMYFUNCTION("IFERROR(IF(Match(L79,IMPORTRANGE(""https://docs.google.com/spreadsheets/d/1n1sT_Q_W3mKmn2Yrd8qcNzuRD4zr4DB9gqARnjQ30B4/edit?gid=1918970062#gid=1918970062"",""Form Responses 1!B2:B49""),0),1), 0)"),0.0) -> 0 | AC79: =IF(COUNTIF(B$1145:B$1305,L79)=0,0,1) -> 1 | AD79: 1 | AE79: =IFERROR(__xludf.DUMMYFUNCTION("IFERROR(IF(Match(L79,IMPORTRANGE(""https://docs.google.com/spreadsheets/d/1hvckjcCpxEuDQDPrBMml_I1kBhYyjrgR8qBKC9QGVUc/edit?resourcekey=&gid=230793720#gid=230793720"",""Form Responses 1!B2:B199""),0),1), 0)"),0.0) -> 0 | AF79: =IFERROR(__xludf.DUMMYFUNCTION("IFERROR(IF(Match(L79,IMPORTRANGE(""https://docs.google.com/spreadsheets/d/1UY0hI2S83Fmafa5P-C1LM9yqe4v4qIKTnVy_CzLzRPs/edit?resourcekey=&gid=1583835601#gid=1583835601"",""Form Responses 1!B2:B194""),0),1), 0)"),0.0) -> 0 | AG79: =IFERROR(__xludf.DUMMYFUNCTION("IFERROR(IF(Match(L79,IMPORTRANGE(""https://docs.google.com/spreadsheets/d/1hO4mQ22n6cudUygJ2ss_JeJdm2Ua_7hJl_79lWWEtic/edit?resourcekey=&gid=2087212010#gid=2087212010"",""Form Responses 1!B2:B104""),0),1), 0)"),0.0) -> 0 | AH79: =IFERROR(__xludf.DUMMYFUNCTION("IFERROR(IF(Match(L79,IMPORTRANGE(""https://docs.google.com/spreadsheets/d/1HbfCXhSXbtTODKKY1MOFwJccyhgDKD0J9sO1k5l_6lM/edit?resourcekey=&gid=1616384832#gid=1616384832"",""Form Responses 1!E2:E143""),0),1), 0)"),0.0) -> 0
